Workbook

Sheet README
A1: Semester financial operating model: three-year, driver-based, monthly
A2: STATUS: PLANNING MODEL. Not an approved budget, price book, forecast or accounting record. No figure here is a legal, tax or accounting conclusion.
A4: How to read it
A5: 1. Assumptions holds every input, tagged: FACT (in the repository), POLICY (proposed default already in deal-desk.ts), HYP (hypothesis, no evidence yet), VENDOR (verify the vendor price), PRO (needs a qualified professional), ILLUS (placeholder), DECIDE (a founder / authorized-reviewer decision not yet made, mainly gate timing).
A6: 2. Scenarios holds the seven scenario columns. Each scenario has its own calculation sheet (Cons, Base, Aggr, EntDelay, HiAI, Incident, EntGated, FullScope) built from identical formulas.
A7: 3. Headcount and Schedules hold the hiring plan and the institutional pipeline schedule. Change them there, not in formulas.
A8: 4. Dashboard shows one scenario (pick 1-8 in B3). Compare shows all seven side by side. Checks must all read OK.
A9: 5. Blue cells are inputs. Black cells are formulas. Nothing is pasted from a calculation.
A11: Conventions
A12: Month 1 = January 2027. USD. Revenue is recognized as a PLANNING PROXY (ratable for subscriptions, pilots and add-ons; services over 3 months). The real policy is an accountant determination.
A13: Institutional counts are expected values, so fractions of an account appear. Collection lag on invoiced billings is fixed at 2 months. No income tax, D&A, capitalized software or financing costs are modeled.
A14: Opening capital is ILLUSTRATIVE and only drives the cash-out month. The honest funding number is "peak cumulative burn" on the Compare sheet.
A16: Regenerate: python3 docs/finance/model/build_workbook.py, then python3 docs/finance/model/verify.py (recalculates in LibreOffice and compares with the Python reference run).

Sheet Dashboard
A1: Dashboard: one scenario at a time
A3: Scenario (1-8) | B3: 2 | C3: =INDEX(Scenarios!$C$3:$J$3,B3) -> Base
A4: 1 Conservative, 2 Base, 3 Aggressive, 4 Enterprise-delayed, 5 High AI cost, 6 Incident, 7 Enterprise-delayed with gated hiring, 8 Full-scope staffing (CTO pack)
A6: Revenue and margin | B6: Year 1 (2027) | C6: Year 2 (2028) | D6: Year 3 (2029)
A7: Student subscriptions | B7: =CHOOSE($B$3,Cons!AN42,Base!AN42,Aggr!AN42,EntDelay!AN42,HiAI!AN42,Incident!AN42,EntGated!AN42,FullScope!AN42) -> 0 | C7: =CHOOSE($B$3,Cons!AO42,Base!AO42,Aggr!AO42,EntDelay!AO42,HiAI!AO42,Incident!AO42,EntGated!AO42,FullScope!AO42) -> 7305.2982 | D7: =CHOOSE($B$3,Cons!AP42,Base!AP42,Aggr!AP42,EntDelay!AP42,HiAI!AP42,Incident!AP42,EntGated!AP42,FullScope!AP42) -> 33510.939
A8: Pilot software | B8: =CHOOSE($B$3,Cons!AN129,Base!AN129,Aggr!AN129,EntDelay!AN129,HiAI!AN129,Incident!AN129,EntGated!AN129,FullScope!AN129) -> 0 | C8: =CHOOSE($B$3,Cons!AO129,Base!AO129,Aggr!AO129,EntDelay!AO129,HiAI!AO129,Incident!AO129,EntGated!AO129,FullScope!AO129) -> 150000 | D8: =CHOOSE($B$3,Cons!AP129,Base!AP129,Aggr!AP129,EntDelay!AP129,HiAI!AP129,Incident!AP129,EntGated!AP129,FullScope!AP129) -> 445000
A9: Institutional platform | B9: =CHOOSE($B$3,Cons!AN127,Base!AN127,Aggr!AN127,EntDelay!AN127,HiAI!AN127,Incident!AN127,EntGated!AN127,FullScope!AN127) -> 1320 | C9: =CHOOSE($B$3,Cons!AO127,Base!AO127,Aggr!AO127,EntDelay!AO127,HiAI!AO127,Incident!AO127,EntGated!AO127,FullScope!AO127) -> 67595.26 | D9: =CHOOSE($B$3,Cons!AP127,Base!AP127,Aggr!AP127,EntDelay!AP127,HiAI!AP127,Incident!AP127,EntGated!AP127,FullScope!AP127) -> 528450.38
A10: Implementation services | B10: =CHOOSE($B$3,Cons!AN131,Base!AN131,Aggr!AN131,EntDelay!AN131,HiAI!AN131,Incident!AN131,EntGated!AN131,FullScope!AN131) -> 0 | C10: =CHOOSE($B$3,Cons!AO131,Base!AO131,Aggr!AO131,EntDelay!AO131,HiAI!AO131,Incident!AO131,EntGated!AO131,FullScope!AO131) -> 278000 | D10: =CHOOSE($B$3,Cons!AP131,Base!AP131,Aggr!AP131,EntDelay!AP131,HiAI!AP131,Incident!AP131,EntGated!AP131,FullScope!AP131) -> 1125000
A11: AI capacity add-on | B11: =CHOOSE($B$3,Cons!AN136,Base!AN136,Aggr!AN136,EntDelay!AN136,HiAI!AN136,Incident!AN136,EntGated!AN136,FullScope!AN136) -> 0 | C11: =CHOOSE($B$3,Cons!AO136,Base!AO136,Aggr!AO136,EntDelay!AO136,HiAI!AO136,Incident!AO136,EntGated!AO136,FullScope!AO136) -> 4025.6 | D11: =CHOOSE($B$3,Cons!AP136,Base!AP136,Aggr!AP136,EntDelay!AP136,HiAI!AP136,Incident!AP136,EntGated!AP136,FullScope!AP136) -> 53345.728
A12: Alumni module | B12: =CHOOSE($B$3,Cons!AN137,Base!AN137,Aggr!AN137,EntDelay!AN137,HiAI!AN137,Incident!AN137,EntGated!AN137,FullScope!AN137) -> 0 | C12: =CHOOSE($B$3,Cons!AO137,Base!AO137,Aggr!AO137,EntDelay!AO137,HiAI!AO137,Incident!AO137,EntGated!AO137,FullScope!AO137) -> 0 | D12: =CHOOSE($B$3,Cons!AP137,Base!AP137,Aggr!AP137,EntDelay!AP137,HiAI!AP137,Incident!AP137,EntGated!AP137,FullScope!AP137) -> 6325.7
A13: Career / employer | B13: =CHOOSE($B$3,Cons!AN140,Base!AN140,Aggr!AN140,EntDelay!AN140,HiAI!AN140,Incident!AN140,EntGated!AN140,FullScope!AN140) -> 0 | C13: =CHOOSE($B$3,Cons!AO140,Base!AO140,Aggr!AO140,EntDelay!AO140,HiAI!AO140,Incident!AO140,EntGated!AO140,FullScope!AO140) -> 0 | D13: =CHOOSE($B$3,Cons!AP140,Base!AP140,Aggr!AP140,EntDelay!AP140,HiAI!AP140,Incident!AP140,EntGated!AP140,FullScope!AP140) -> 92869.806
A14: Marketplace (net take) | B14: =CHOOSE($B$3,Cons!AN144,Base!AN144,Aggr!AN144,EntDelay!AN144,HiAI!AN144,Incident!AN144,EntGated!AN144,FullScope!AN144) -> 0 | C14: =CHOOSE($B$3,Cons!AO144,Base!AO144,Aggr!AO144,EntDelay!AO144,HiAI!AO144,Incident!AO144,EntGated!AO144,FullScope!AO144) -> 0 | D14: =CHOOSE($B$3,Cons!AP144,Base!AP144,Aggr!AP144,EntDelay!AP144,HiAI!AP144,Incident!AP144,EntGated!AP144,FullScope!AP144) -> 17439.158
A15: TOTAL REVENUE | B15: =CHOOSE($B$3,Cons!AN146,Base!AN146,Aggr!AN146,EntDelay!AN146,HiAI!AN146,Incident!AN146,EntGated!AN146,FullScope!AN146) -> 1320 | C15: =CHOOSE($B$3,Cons!AO146,Base!AO146,Aggr!AO146,EntDelay!AO146,HiAI!AO146,Incident!AO146,EntGated!AO146,FullScope!AO146) -> 506926.16 | D15: =CHOOSE($B$3,Cons!AP146,Base!AP146,Aggr!AP146,EntDelay!AP146,HiAI!AP146,Incident!AP146,EntGated!AP146,FullScope!AP146) -> 2301941.7
A16: Cost of revenue | B16: =CHOOSE($B$3,Cons!AN184,Base!AN184,Aggr!AN184,EntDelay!AN184,HiAI!AN184,Incident!AN184,EntGated!AN184,FullScope!AN184) -> 208558.37 | C16: =CHOOSE($B$3,Cons!AO184,Base!AO184,Aggr!AO184,EntDelay!AO184,HiAI!AO184,Incident!AO184,EntGated!AO184,FullScope!AO184) -> 867095.12 | D16: =CHOOSE($B$3,Cons!AP184,Base!AP184,Aggr!AP184,EntDelay!AP184,HiAI!AP184,Incident!AP184,EntGated!AP184,FullScope!AP184) -> 1936630.8
A17: Gross profit | B17: =CHOOSE($B$3,Cons!AN223,Base!AN223,Aggr!AN223,EntDelay!AN223,HiAI!AN223,Incident!AN223,EntGated!AN223,FullScope!AN223) -> -207238.37 | C17: =CHOOSE($B$3,Cons!AO223,Base!AO223,Aggr!AO223,EntDelay!AO223,HiAI!AO223,Incident!AO223,EntGated!AO223,FullScope!AO223) -> -360168.96 | D17: =CHOOSE($B$3,Cons!AP223,Base!AP223,Aggr!AP223,EntDelay!AP223,HiAI!AP223,Incident!AP223,EntGated!AP223,FullScope!AP223) -> 365310.91
A19: Operating expenses | B19: Year 1 (2027) | C19: Year 2 (2028) | D19: Year 3 (2029)
A20: Engineering and product | B20: =CHOOSE($B$3,Cons!AN213,Base!AN213,Aggr!AN213,EntDelay!AN213,HiAI!AN213,Incident!AN213,EntGated!AN213,FullScope!AN213) -> 1091391.7 | C20: =CHOOSE($B$3,Cons!AO213,Base!AO213,Aggr!AO213,EntDelay!AO213,HiAI!AO213,Incident!AO213,EntGated!AO213,FullScope!AO213) -> 1931666.7 | D20: =CHOOSE($B$3,Cons!AP213,Base!AP213,Aggr!AP213,EntDelay!AP213,HiAI!AP213,Incident!AP213,EntGated!AP213,FullScope!AP213) -> 2192950
A21: Security and privacy | B21: =CHOOSE($B$3,Cons!AN214,Base!AN214,Aggr!AN214,EntDelay!AN214,HiAI!AN214,Incident!AN214,EntGated!AN214,FullScope!AN214) -> 209500 | C21: =CHOOSE($B$3,Cons!AO214,Base!AO214,Aggr!AO214,EntDelay!AO214,HiAI!AO214,Incident!AO214,EntGated!AO214,FullScope!AO214) -> 353000 | D21: =CHOOSE($B$3,Cons!AP214,Base!AP214,Aggr!AP214,EntDelay!AP214,HiAI!AP214,Incident!AP214,EntGated!AP214,FullScope!AP214) -> 418000
A22: Sales and partnerships | B22: =CHOOSE($B$3,Cons!AN215,Base!AN215,Aggr!AN215,EntDelay!AN215,HiAI!AN215,Incident!AN215,EntGated!AN215,FullScope!AN215) -> 83633.867 | C22: =CHOOSE($B$3,Cons!AO215,Base!AO215,Aggr!AO215,EntDelay!AO215,HiAI!AO215,Incident!AO215,EntGated!AO215,FullScope!AO215) -> 504057.2 | D22: =CHOOSE($B$3,Cons!AP215,Base!AP215,Aggr!AP215,EntDelay!AP215,HiAI!AP215,Incident!AP215,EntGated!AP215,FullScope!AP215) -> 980858
A23: Marketing | B23: =CHOOSE($B$3,Cons!AN216,Base!AN216,Aggr!AN216,EntDelay!AN216,HiAI!AN216,Incident!AN216,EntGated!AN216,FullScope!AN216) -> 139333.33 | C23: =CHOOSE($B$3,Cons!AO216,Base!AO216,Aggr!AO216,EntDelay!AO216,HiAI!AO216,Incident!AO216,EntGated!AO216,FullScope!AO216) -> 419608.33 | D23: =CHOOSE($B$3,Cons!AP216,Base!AP216,Aggr!AP216,EntDelay!AP216,HiAI!AP216,Incident!AP216,EntGated!AP216,FullScope!AP216) -> 601100
A24: Legal | B24: =CHOOSE($B$3,Cons!AN217,Base!AN217,Aggr!AN217,EntDelay!AN217,HiAI!AN217,Incident!AN217,EntGated!AN217,FullScope!AN217) -> 95000 | C24: =CHOOSE($B$3,Cons!AO217,Base!AO217,Aggr!AO217,EntDelay!AO217,HiAI!AO217,Incident!AO217,EntGated!AO217,FullScope!AO217) -> 112000 | D24: =CHOOSE($B$3,Cons!AP217,Base!AP217,Aggr!AP217,EntDelay!AP217,HiAI!AP217,Incident!AP217,EntGated!AP217,FullScope!AP217) -> 155000
A25: Insurance | B25: =CHOOSE($B$3,Cons!AN218,Base!AN218,Aggr!AN218,EntDelay!AN218,HiAI!AN218,Incident!AN218,EntGated!AN218,FullScope!AN218) -> 41000 | C25: =CHOOSE($B$3,Cons!AO218,Base!AO218,Aggr!AO218,EntDelay!AO218,HiAI!AO218,Incident!AO218,EntGated!AO218,FullScope!AO218) -> 70000 | D25: =CHOOSE($B$3,Cons!AP218,Base!AP218,Aggr!AP218,EntDelay!AP218,HiAI!AP218,Incident!AP218,EntGated!AP218,FullScope!AP218) -> 120000
A26: G&A | B26: =CHOOSE($B$3,Cons!AN219,Base!AN219,Aggr!AN219,EntDelay!AN219,HiAI!AN219,Incident!AN219,EntGated!AN219,FullScope!AN219) -> 587321.73 | C26: =CHOOSE($B$3,Cons!AO219,Base!AO219,Aggr!AO219,EntDelay!AO219,HiAI!AO219,Incident!AO219,EntGated!AO219,FullScope!AO219) -> 1047095.9 | D26: =CHOOSE($B$3,Cons!AP219,Base!AP219,Aggr!AP219,EntDelay!AP219,HiAI!AP219,Incident!AP219,EntGated!AP219,FullScope!AP219) -> 1342888.3
A27: Incident response | B27: =CHOOSE($B$3,Cons!AN220,Base!AN220,Aggr!AN220,EntDelay!AN220,HiAI!AN220,Incident!AN220,EntGated!AN220,FullScope!AN220) -> 0 | C27: =CHOOSE($B$3,Cons!AO220,Base!AO220,Aggr!AO220,EntDelay!AO220,HiAI!AO220,Incident!AO220,EntGated!AO220,FullScope!AO220) -> 0 | D27: =CHOOSE($B$3,Cons!AP220,Base!AP220,Aggr!AP220,EntDelay!AP220,HiAI!AP220,Incident!AP220,EntGated!AP220,FullScope!AP220) -> 0
A28: TOTAL OPERATING EXPENSES | B28: =CHOOSE($B$3,Cons!AN221,Base!AN221,Aggr!AN221,EntDelay!AN221,HiAI!AN221,Incident!AN221,EntGated!AN221,FullScope!AN221) -> 2247180.6 | C28: =CHOOSE($B$3,Cons!AO221,Base!AO221,Aggr!AO221,EntDelay!AO221,HiAI!AO221,Incident!AO221,EntGated!AO221,FullScope!AO221) -> 4437428.1 | D28: =CHOOSE($B$3,Cons!AP221,Base!AP221,Aggr!AP221,EntDelay!AP221,HiAI!AP221,Incident!AP221,EntGated!AP221,FullScope!AP221) -> 5810796.3
A29: Operating result (EBITDA) | B29: =CHOOSE($B$3,Cons!AN225,Base!AN225,Aggr!AN225,EntDelay!AN225,HiAI!AN225,Incident!AN225,EntGated!AN225,FullScope!AN225) -> -2454419 | C29: =CHOOSE($B$3,Cons!AO225,Base!AO225,Aggr!AO225,EntDelay!AO225,HiAI!AO225,Incident!AO225,EntGated!AO225,FullScope!AO225) -> -4797597.1 | D29: =CHOOSE($B$3,Cons!AP225,Base!AP225,Aggr!AP225,EntDelay!AP225,HiAI!AP225,Incident!AP225,EntGated!AP225,FullScope!AP225) -> -5445485.4
A31: Cash | B31: Year 1 (2027) | C31: Year 2 (2028) | D31: Year 3 (2029)
A32: Cash collected | B32: =CHOOSE($B$3,Cons!AN153,Base!AN153,Aggr!AN153,EntDelay!AN153,HiAI!AN153,Incident!AN153,EntGated!AN153,FullScope!AN153) -> 0 | C32: =CHOOSE($B$3,Cons!AO153,Base!AO153,Aggr!AO153,EntDelay!AO153,HiAI!AO153,Incident!AO153,EntGated!AO153,FullScope!AO153) -> 524233.94 | D32: =CHOOSE($B$3,Cons!AP153,Base!AP153,Aggr!AP153,EntDelay!AP153,HiAI!AP153,Incident!AP153,EntGated!AP153,FullScope!AP153) -> 2256267.3
A33: Operating cash flow | B33: =CHOOSE($B$3,Cons!AN226,Base!AN226,Aggr!AN226,EntDelay!AN226,HiAI!AN226,Incident!AN226,EntGated!AN226,FullScope!AN226) -> -2455739 | C33: =CHOOSE($B$3,Cons!AO226,Base!AO226,Aggr!AO226,EntDelay!AO226,HiAI!AO226,Incident!AO226,EntGated!AO226,FullScope!AO226) -> -4780289.3 | D33: =CHOOSE($B$3,Cons!AP226,Base!AP226,Aggr!AP226,EntDelay!AP226,HiAI!AP226,Incident!AP226,EntGated!AP226,FullScope!AP226) -> -5491159.8
A34: Cumulative operating cash flow | B34: =CHOOSE($B$3,Cons!AN227,Base!AN227,Aggr!AN227,EntDelay!AN227,HiAI!AN227,Incident!AN227,EntGated!AN227,FullScope!AN227) -> -2455739 | C34: =CHOOSE($B$3,Cons!AO227,Base!AO227,Aggr!AO227,EntDelay!AO227,HiAI!AO227,Incident!AO227,EntGated!AO227,FullScope!AO227) -> -7236028.2 | D34: =CHOOSE($B$3,Cons!AP227,Base!AP227,Aggr!AP227,EntDelay!AP227,HiAI!AP227,Incident!AP227,EntGated!AP227,FullScope!AP227) -> -12727188
A35: Illustrative cash balance | B35: =CHOOSE($B$3,Cons!AN228,Base!AN228,Aggr!AN228,EntDelay!AN228,HiAI!AN228,Incident!AN228,EntGated!AN228,FullScope!AN228) -> 544261.03 | C35: =CHOOSE($B$3,Cons!AO228,Base!AO228,Aggr!AO228,EntDelay!AO228,HiAI!AO228,Incident!AO228,EntGated!AO228,FullScope!AO228) -> -4236028.2 | D35: =CHOOSE($B$3,Cons!AP228,Base!AP228,Aggr!AP228,EntDelay!AP228,HiAI!AP228,Incident!AP228,EntGated!AP228,FullScope!AP228) -> -9727188
A36: Deferred revenue | B36: =CHOOSE($B$3,Cons!AN154,Base!AN154,Aggr!AN154,EntDelay!AN154,HiAI!AN154,Incident!AN154,EntGated!AN154,FullScope!AN154) -> 14520 | C36: =CHOOSE($B$3,Cons!AO154,Base!AO154,Aggr!AO154,EntDelay!AO154,HiAI!AO154,Incident!AO154,EntGated!AO154,FullScope!AO154) -> 120222.61 | D36: =CHOOSE($B$3,Cons!AP154,Base!AP154,Aggr!AP154,EntDelay!AP154,HiAI!AP154,Incident!AP154,EntGated!AP154,FullScope!AP154) -> 1013459.2
A37: Receivables | B37: =CHOOSE($B$3,Cons!AN155,Base!AN155,Aggr!AN155,EntDelay!AN155,HiAI!AN155,Incident!AN155,EntGated!AN155,FullScope!AN155) -> 15681.6 | C37: =CHOOSE($B$3,Cons!AO155,Base!AO155,Aggr!AO155,EntDelay!AO155,HiAI!AO155,Incident!AO155,EntGated!AO155,FullScope!AO155) -> 98102.189 | D37: =CHOOSE($B$3,Cons!AP155,Base!AP155,Aggr!AP155,EntDelay!AP155,HiAI!AP155,Incident!AP155,EntGated!AP155,FullScope!AP155) -> 1007154.9
A39: Scale | B39: Year 1 (2027) | C39: Year 2 (2028) | D39: Year 3 (2029)
A40: ARR | B40: =CHOOSE($B$3,Cons!AN148,Base!AN148,Aggr!AN148,EntDelay!AN148,HiAI!AN148,Incident!AN148,EntGated!AN148,FullScope!AN148) -> 15840 | C40: =CHOOSE($B$3,Cons!AO148,Base!AO148,Aggr!AO148,EntDelay!AO148,HiAI!AO148,Incident!AO148,EntGated!AO148,FullScope!AO148) -> 163394.4 | D40: =CHOOSE($B$3,Cons!AP148,Base!AP148,Aggr!AP148,EntDelay!AP148,HiAI!AP148,Incident!AP148,EntGated!AP148,FullScope!AP148) -> 1527680.4
A41: ARR, institutional | B41: =CHOOSE($B$3,Cons!AN149,Base!AN149,Aggr!AN149,EntDelay!AN149,HiAI!AN149,Incident!AN149,EntGated!AN149,FullScope!AN149) -> 15840 | C41: =CHOOSE($B$3,Cons!AO149,Base!AO149,Aggr!AO149,EntDelay!AO149,HiAI!AO149,Incident!AO149,EntGated!AO149,FullScope!AO149) -> 146050.32 | D41: =CHOOSE($B$3,Cons!AP149,Base!AP149,Aggr!AP149,EntDelay!AP149,HiAI!AP149,Incident!AP149,EntGated!AP149,FullScope!AP149) -> 1479349.3
A42: ARR, student | B42: =CHOOSE($B$3,Cons!AN150,Base!AN150,Aggr!AN150,EntDelay!AN150,HiAI!AN150,Incident!AN150,EntGated!AN150,FullScope!AN150) -> 0 | C42: =CHOOSE($B$3,Cons!AO150,Base!AO150,Aggr!AO150,EntDelay!AO150,HiAI!AO150,Incident!AO150,EntGated!AO150,FullScope!AO150) -> 17344.081 | D42: =CHOOSE($B$3,Cons!AP150,Base!AP150,Aggr!AP150,EntDelay!AP150,HiAI!AP150,Incident!AP150,EntGated!AP150,FullScope!AP150) -> 48331.129
A43: Annual logos | B43: =CHOOSE($B$3,Cons!AN122,Base!AN122,Aggr!AN122,EntDelay!AN122,HiAI!AN122,Incident!AN122,EntGated!AN122,FullScope!AN122) -> 0.6 | C43: =CHOOSE($B$3,Cons!AO122,Base!AO122,Aggr!AO122,EntDelay!AO122,HiAI!AO122,Incident!AO122,EntGated!AO122,FullScope!AO122) -> 3.578 | D43: =CHOOSE($B$3,Cons!AP122,Base!AP122,Aggr!AP122,EntDelay!AP122,HiAI!AP122,Incident!AP122,EntGated!AP122,FullScope!AP122) -> 24.39864
A44: Pilots running | B44: =CHOOSE($B$3,Cons!AN123,Base!AN123,Aggr!AN123,EntDelay!AN123,HiAI!AN123,Incident!AN123,EntGated!AN123,FullScope!AN123) -> 1 | C44: =CHOOSE($B$3,Cons!AO123,Base!AO123,Aggr!AO123,EntDelay!AO123,HiAI!AO123,Incident!AO123,EntGated!AO123,FullScope!AO123) -> 6 | D44: =CHOOSE($B$3,Cons!AP123,Base!AP123,Aggr!AP123,EntDelay!AP123,HiAI!AP123,Incident!AP123,EntGated!AP123,FullScope!AP123) -> 12
A45: Paying students | B45: =CHOOSE($B$3,Cons!AN39,Base!AN39,Aggr!AN39,EntDelay!AN39,HiAI!AN39,Incident!AN39,EntGated!AN39,FullScope!AN39) -> 0 | C45: =CHOOSE($B$3,Cons!AO39,Base!AO39,Aggr!AO39,EntDelay!AO39,HiAI!AO39,Incident!AO39,EntGated!AO39,FullScope!AO39) -> 256.9664 | D45: =CHOOSE($B$3,Cons!AP39,Base!AP39,Aggr!AP39,EntDelay!AP39,HiAI!AP39,Incident!AP39,EntGated!AP39,FullScope!AP39) -> 719.9672
A46: Active free students | B46: =CHOOSE($B$3,Cons!AN29,Base!AN29,Aggr!AN29,EntDelay!AN29,HiAI!AN29,Incident!AN29,EntGated!AN29,FullScope!AN29) -> 1806.2157 | C46: =CHOOSE($B$3,Cons!AO29,Base!AO29,Aggr!AO29,EntDelay!AO29,HiAI!AO29,Incident!AO29,EntGated!AO29,FullScope!AO29) -> 16506.248 | D46: =CHOOSE($B$3,Cons!AP29,Base!AP29,Aggr!AP29,EntDelay!AP29,HiAI!AP29,Incident!AP29,EntGated!AP29,FullScope!AP29) -> 27287.799
A47: Sponsored students | B47: =CHOOSE($B$3,Cons!AN126,Base!AN126,Aggr!AN126,EntDelay!AN126,HiAI!AN126,Incident!AN126,EntGated!AN126,FullScope!AN126) -> 1235 | C47: =CHOOSE($B$3,Cons!AO126,Base!AO126,Aggr!AO126,EntDelay!AO126,HiAI!AO126,Incident!AO126,EntGated!AO126,FullScope!AO126) -> 6731.8 | D47: =CHOOSE($B$3,Cons!AP126,Base!AP126,Aggr!AP126,EntDelay!AP126,HiAI!AP126,Incident!AP126,EntGated!AP126,FullScope!AP126) -> 46689.784
A48: All monthly-active users | B48: =CHOOSE($B$3,Cons!AN157,Base!AN157,Aggr!AN157,EntDelay!AN157,HiAI!AN157,Incident!AN157,EntGated!AN157,FullScope!AN157) -> 3041.2157 | C48: =CHOOSE($B$3,Cons!AO157,Base!AO157,Aggr!AO157,EntDelay!AO157,HiAI!AO157,Incident!AO157,EntGated!AO157,FullScope!AO157) -> 23495.015 | D48: =CHOOSE($B$3,Cons!AP157,Base!AP157,Aggr!AP157,EntDelay!AP157,HiAI!AP157,Incident!AP157,EntGated!AP157,FullScope!AP157) -> 74697.55
A49: Headcount (FTE) | B49: =CHOOSE($B$3,Cons!AN196,Base!AN196,Aggr!AN196,EntDelay!AN196,HiAI!AN196,Incident!AN196,EntGated!AN196,FullScope!AN196) -> 18.4 | C49: =CHOOSE($B$3,Cons!AO196,Base!AO196,Aggr!AO196,EntDelay!AO196,HiAI!AO196,Incident!AO196,EntGated!AO196,FullScope!AO196) -> 31.4 | D49: =CHOOSE($B$3,Cons!AP196,Base!AP196,Aggr!AP196,EntDelay!AP196,HiAI!AP196,Incident!AP196,EntGated!AP196,FullScope!AP196) -> 40.4
A51: Unit-economics dashboard | B51: Year 1 (2027) | C51: Year 2 (2028) | D51: Year 3 (2029)
A52: Total revenue | B52: =CHOOSE($B$3,Cons!AN235,Base!AN235,Aggr!AN235,EntDelay!AN235,HiAI!AN235,Incident!AN235,EntGated!AN235,FullScope!AN235) -> 1320 | C52: =CHOOSE($B$3,Cons!AO235,Base!AO235,Aggr!AO235,EntDelay!AO235,HiAI!AO235,Incident!AO235,EntGated!AO235,FullScope!AO235) -> 506926.16 | D52: =CHOOSE($B$3,Cons!AP235,Base!AP235,Aggr!AP235,EntDelay!AP235,HiAI!AP235,Incident!AP235,EntGated!AP235,FullScope!AP235) -> 2301941.7
A53: ARR at year end | B53: =CHOOSE($B$3,Cons!AN236,Base!AN236,Aggr!AN236,EntDelay!AN236,HiAI!AN236,Incident!AN236,EntGated!AN236,FullScope!AN236) -> 15840 | C53: =CHOOSE($B$3,Cons!AO236,Base!AO236,Aggr!AO236,EntDelay!AO236,HiAI!AO236,Incident!AO236,EntGated!AO236,FullScope!AO236) -> 163394.4 | D53: =CHOOSE($B$3,Cons!AP236,Base!AP236,Aggr!AP236,EntDelay!AP236,HiAI!AP236,Incident!AP236,EntGated!AP236,FullScope!AP236) -> 1527680.4
A54: Gross margin | B54: =CHOOSE($B$3,Cons!AN237,Base!AN237,Aggr!AN237,EntDelay!AN237,HiAI!AN237,Incident!AN237,EntGated!AN237,FullScope!AN237) -> -156.99877 | C54: =CHOOSE($B$3,Cons!AO237,Base!AO237,Aggr!AO237,EntDelay!AO237,HiAI!AO237,Incident!AO237,EntGated!AO237,FullScope!AO237) -> -0.7104959 | D54: =CHOOSE($B$3,Cons!AP237,Base!AP237,Aggr!AP237,EntDelay!AP237,HiAI!AP237,Incident!AP237,EntGated!AP237,FullScope!AP237) -> 0.15869686
A55: Contribution margin | B55: =CHOOSE($B$3,Cons!AN238,Base!AN238,Aggr!AN238,EntDelay!AN238,HiAI!AN238,Incident!AN238,EntGated!AN238,FullScope!AN238) -> -157.95877 | C55: =CHOOSE($B$3,Cons!AO238,Base!AO238,Aggr!AO238,EntDelay!AO238,HiAI!AO238,Incident!AO238,EntGated!AO238,FullScope!AO238) -> -0.87562291 | D55: =CHOOSE($B$3,Cons!AP238,Base!AP238,Aggr!AP238,EntDelay!AP238,HiAI!AP238,Incident!AP238,EntGated!AP238,FullScope!AP238) -> 0.03132265
A56: Variable gross margin: student subscriptions (incl. free-user cost) | B56: =CHOOSE($B$3,Cons!AN239,Base!AN239,Aggr!AN239,EntDelay!AN239,HiAI!AN239,Incident!AN239,EntGated!AN239,FullScope!AN239) -> 0 | C56: =CHOOSE($B$3,Cons!AO239,Base!AO239,Aggr!AO239,EntDelay!AO239,HiAI!AO239,Incident!AO239,EntGated!AO239,FullScope!AO239) -> -4.9758766 | D56: =CHOOSE($B$3,Cons!AP239,Base!AP239,Aggr!AP239,EntDelay!AP239,HiAI!AP239,Incident!AP239,EntGated!AP239,FullScope!AP239) -> -2.1546171
A57: Gross margin: institutional platform, pilots and add-ons (incl. customer success) | B57: =CHOOSE($B$3,Cons!AN240,Base!AN240,Aggr!AN240,EntDelay!AN240,HiAI!AN240,Incident!AN240,EntGated!AN240,FullScope!AN240) -> -3.2582302 | C57: =CHOOSE($B$3,Cons!AO240,Base!AO240,Aggr!AO240,EntDelay!AO240,HiAI!AO240,Incident!AO240,EntGated!AO240,FullScope!AO240) -> 0.52106844 | D57: =CHOOSE($B$3,Cons!AP240,Base!AP240,Aggr!AP240,EntDelay!AP240,HiAI!AP240,Incident!AP240,EntGated!AP240,FullScope!AP240) -> 0.66427877
A58: Implementation margin (actual team cost) | B58: =CHOOSE($B$3,Cons!AN241,Base!AN241,Aggr!AN241,EntDelay!AN241,HiAI!AN241,Incident!AN241,EntGated!AN241,FullScope!AN241) -> 0 | C58: =CHOOSE($B$3,Cons!AO241,Base!AO241,Aggr!AO241,EntDelay!AO241,HiAI!AO241,Incident!AO241,EntGated!AO241,FullScope!AO241) -> -0.57254197 | D58: =CHOOSE($B$3,Cons!AP241,Base!AP241,Aggr!AP241,EntDelay!AP241,HiAI!AP241,Incident!AP241,EntGated!AP241,FullScope!AP241) -> 0.21377778
A59: Implementation margin at standard cost (pricing check) | B59: =CHOOSE($B$3,Cons!AN242,Base!AN242,Aggr!AN242,EntDelay!AN242,HiAI!AN242,Incident!AN242,EntGated!AN242,FullScope!AN242) -> 0 | C59: =CHOOSE($B$3,Cons!AO242,Base!AO242,Aggr!AO242,EntDelay!AO242,HiAI!AO242,Incident!AO242,EntGated!AO242,FullScope!AO242) -> 0.31663669 | D59: =CHOOSE($B$3,Cons!AP242,Base!AP242,Aggr!AP242,EntDelay!AP242,HiAI!AP242,Incident!AP242,EntGated!AP242,FullScope!AP242) -> 0.21732
A60: Implementation utilization (demand / capacity) | B60: =CHOOSE($B$3,Cons!AN243,Base!AN243,Aggr!AN243,EntDelay!AN243,HiAI!AN243,Incident!AN243,EntGated!AN243,FullScope!AN243) -> 0.40454545 | C60: =CHOOSE($B$3,Cons!AO243,Base!AO243,Aggr!AO243,EntDelay!AO243,HiAI!AO243,Incident!AO243,EntGated!AO243,FullScope!AO243) -> 0.47251586 | D60: =CHOOSE($B$3,Cons!AP243,Base!AP243,Aggr!AP243,EntDelay!AP243,HiAI!AP243,Incident!AP243,EntGated!AP243,FullScope!AP243) -> 1.0824451
A61: Operating result (EBITDA) | B61: =CHOOSE($B$3,Cons!AN244,Base!AN244,Aggr!AN244,EntDelay!AN244,HiAI!AN244,Incident!AN244,EntGated!AN244,FullScope!AN244) -> -2454419 | C61: =CHOOSE($B$3,Cons!AO244,Base!AO244,Aggr!AO244,EntDelay!AO244,HiAI!AO244,Incident!AO244,EntGated!AO244,FullScope!AO244) -> -4797597.1 | D61: =CHOOSE($B$3,Cons!AP244,Base!AP244,Aggr!AP244,EntDelay!AP244,HiAI!AP244,Incident!AP244,EntGated!AP244,FullScope!AP244) -> -5445485.4
A62: Net burn (negative operating cash flow) | B62: =CHOOSE($B$3,Cons!AN245,Base!AN245,Aggr!AN245,EntDelay!AN245,HiAI!AN245,Incident!AN245,EntGated!AN245,FullScope!AN245) -> 2455739 | C62: =CHOOSE($B$3,Cons!AO245,Base!AO245,Aggr!AO245,EntDelay!AO245,HiAI!AO245,Incident!AO245,EntGated!AO245,FullScope!AO245) -> 4780289.3 | D62: =CHOOSE($B$3,Cons!AP245,Base!AP245,Aggr!AP245,EntDelay!AP245,HiAI!AP245,Incident!AP245,EntGated!AP245,FullScope!AP245) -> 5491159.8
A63: Cumulative operating cash flow at year end | B63: =CHOOSE($B$3,Cons!AN246,Base!AN246,Aggr!AN246,EntDelay!AN246,HiAI!AN246,Incident!AN246,EntGated!AN246,FullScope!AN246) -> -2455739 | C63: =CHOOSE($B$3,Cons!AO246,Base!AO246,Aggr!AO246,EntDelay!AO246,HiAI!AO246,Incident!AO246,EntGated!AO246,FullScope!AO246) -> -7236028.2 | D63: =CHOOSE($B$3,Cons!AP246,Base!AP246,Aggr!AP246,EntDelay!AP246,HiAI!AP246,Incident!AP246,EntGated!AP246,FullScope!AP246) -> -12727188
... A66: Burn multiple (net burn / net new ARR) | B66: =CHOOSE($B$3,Cons!AN249,Base!AN249,Aggr!AN249,EntDelay!AN249,HiAI!AN249,Incident!AN249,EntGated!AN249,FullScope!AN249) -> 155.03403 | C66: =CHOOSE($B$3,Cons!AO249,Base!AO249,Aggr!AO249,EntDelay!AO249,HiAI!AO249,Incident!AO249,EntGated!AO249,FullScope!AO249) -> 32.396792 | D66: =CHOOSE($B$3,Cons!AP249,Base!AP249,Aggr!AP249,EntDelay!AP249,HiAI!AP249,Incident!AP249,EntGated!AP249,FullScope!AP249) -> 4.0249331
A67: Student CAC (paid test budget + half of marketing) / new paying subscribers | B67: =CHOOSE($B$3,Cons!AN251,Base!AN251,Aggr!AN251,EntDelay!AN251,HiAI!AN251,Incident!AN251,EntGated!AN251,FullScope!AN251) -> 0 | C67: =CHOOSE($B$3,Cons!AO251,Base!AO251,Aggr!AO251,EntDelay!AO251,HiAI!AO251,Incident!AO251,EntGated!AO251,FullScope!AO251) -> 932.41163 | D67: =CHOOSE($B$3,Cons!AP251,Base!AP251,Aggr!AP251,EntDelay!AP251,HiAI!AP251,Incident!AP251,EntGated!AP251,FullScope!AP251) -> 622.40125
A68: Student CAC, fully loaded (test budget + half of marketing + free-tier cost) / new paying subscribers | B68: =CHOOSE($B$3,Cons!AN251,Base!AN251,Aggr!AN251,EntDelay!AN251,HiAI!AN251,Incident!AN251,EntGated!AN251,FullScope!AN251) -> 0 | C68: =CHOOSE($B$3,Cons!AO251,Base!AO251,Aggr!AO251,EntDelay!AO251,HiAI!AO251,Incident!AO251,EntGated!AO251,FullScope!AO251) -> 932.41163 | D68: =CHOOSE($B$3,Cons!AP251,Base!AP251,Aggr!AP251,EntDelay!AP251,HiAI!AP251,Incident!AP251,EntGated!AP251,FullScope!AP251) -> 622.40125
A69: Student ARPU, monthly (average subscribers) | B69: =CHOOSE($B$3,Cons!AN252,Base!AN252,Aggr!AN252,EntDelay!AN252,HiAI!AN252,Incident!AN252,EntGated!AN252,FullScope!AN252) -> 0 | C69: =CHOOSE($B$3,Cons!AO252,Base!AO252,Aggr!AO252,EntDelay!AO252,HiAI!AO252,Incident!AO252,EntGated!AO252,FullScope!AO252) -> 4.738167 | D69: =CHOOSE($B$3,Cons!AP252,Base!AP252,Aggr!AP252,EntDelay!AP252,HiAI!AP252,Incident!AP252,EntGated!AP252,FullScope!AP252) -> 5.7170278
A70: Margin on paying subscribers (own variable cost only) | B70: =CHOOSE($B$3,Cons!AN253,Base!AN253,Aggr!AN253,EntDelay!AN253,HiAI!AN253,Incident!AN253,EntGated!AN253,FullScope!AN253) -> 0 | C70: =CHOOSE($B$3,Cons!AO253,Base!AO253,Aggr!AO253,EntDelay!AO253,HiAI!AO253,Incident!AO253,EntGated!AO253,FullScope!AO253) -> 0.74494831 | D70: =CHOOSE($B$3,Cons!AP253,Base!AP253,Aggr!AP253,EntDelay!AP253,HiAI!AP253,Incident!AP253,EntGated!AP253,FullScope!AP253) -> 0.76676162
A71: Student CAC payback (months, on paying-subscriber margin) | B71: =CHOOSE($B$3,Cons!AN254,Base!AN254,Aggr!AN254,EntDelay!AN254,HiAI!AN254,Incident!AN254,EntGated!AN254,FullScope!AN254) -> 0 | C71: =CHOOSE($B$3,Cons!AO254,Base!AO254,Aggr!AO254,EntDelay!AO254,HiAI!AO254,Incident!AO254,EntGated!AO254,FullScope!AO254) -> 264.16251 | D71: =CHOOSE($B$3,Cons!AP254,Base!AP254,Aggr!AP254,EntDelay!AP254,HiAI!AP254,Incident!AP254,EntGated!AP254,FullScope!AP254) -> 141.98412
A72: Institution CAC per new annual contract (sales + half of non-student marketing) | B72: =CHOOSE($B$3,Cons!AN255,Base!AN255,Aggr!AN255,EntDelay!AN255,HiAI!AN255,Incident!AN255,EntGated!AN255,FullScope!AN255) -> 255500.89 | C72: =CHOOSE($B$3,Cons!AO255,Base!AO255,Aggr!AO255,EntDelay!AO255,HiAI!AO255,Incident!AO255,EntGated!AO255,FullScope!AO255) -> 228151.27 | D72: =CHOOSE($B$3,Cons!AP255,Base!AP255,Aggr!AP255,EntDelay!AP255,HiAI!AP255,Incident!AP255,EntGated!AP255,FullScope!AP255) -> 58889.788
A73: Institution CAC per new institution started (pilot or direct) | B73: =CHOOSE($B$3,Cons!AN256,Base!AN256,Aggr!AN256,EntDelay!AN256,HiAI!AN256,Incident!AN256,EntGated!AN256,FullScope!AN256) -> 0 | C73: =CHOOSE($B$3,Cons!AO256,Base!AO256,Aggr!AO256,EntDelay!AO256,HiAI!AO256,Incident!AO256,EntGated!AO256,FullScope!AO256) -> 69586.137 | D73: =CHOOSE($B$3,Cons!AP256,Base!AP256,Aggr!AP256,EntDelay!AP256,HiAI!AP256,Incident!AP256,EntGated!AP256,FullScope!AP256) -> 34761.333
A74: Net revenue retention, core platform (renewal x expansion) | B74: =CHOOSE($B$3,Cons!AN257,Base!AN257,Aggr!AN257,EntDelay!AN257,HiAI!AN257,Incident!AN257,EntGated!AN257,FullScope!AN257) -> 0.968 | C74: =CHOOSE($B$3,Cons!AO257,Base!AO257,Aggr!AO257,EntDelay!AO257,HiAI!AO257,Incident!AO257,EntGated!AO257,FullScope!AO257) -> 0.968 | D74: =CHOOSE($B$3,Cons!AP257,Base!AP257,Aggr!AP257,EntDelay!AP257,HiAI!AP257,Incident!AP257,EntGated!AP257,FullScope!AP257) -> 0.968
A75: Gross logo retention, institutions | B75: =CHOOSE($B$3,Cons!AN258,Base!AN258,Aggr!AN258,EntDelay!AN258,HiAI!AN258,Incident!AN258,EntGated!AN258,FullScope!AN258) -> 0.88 | C75: =CHOOSE($B$3,Cons!AO258,Base!AO258,Aggr!AO258,EntDelay!AO258,HiAI!AO258,Incident!AO258,EntGated!AO258,FullScope!AO258) -> 0.88 | D75: =CHOOSE($B$3,Cons!AP258,Base!AP258,Aggr!AP258,EntDelay!AP258,HiAI!AP258,Incident!AP258,EntGated!AP258,FullScope!AP258) -> 0.88
A76: Annual logos at year end | B76: =CHOOSE($B$3,Cons!AN259,Base!AN259,Aggr!AN259,EntDelay!AN259,HiAI!AN259,Incident!AN259,EntGated!AN259,FullScope!AN259) -> 0.6 | C76: =CHOOSE($B$3,Cons!AO259,Base!AO259,Aggr!AO259,EntDelay!AO259,HiAI!AO259,Incident!AO259,EntGated!AO259,FullScope!AO259) -> 3.578 | D76: =CHOOSE($B$3,Cons!AP259,Base!AP259,Aggr!AP259,EntDelay!AP259,HiAI!AP259,Incident!AP259,EntGated!AP259,FullScope!AP259) -> 24.39864
A77: Paying subscribers at year end | B77: =CHOOSE($B$3,Cons!AN260,Base!AN260,Aggr!AN260,EntDelay!AN260,HiAI!AN260,Incident!AN260,EntGated!AN260,FullScope!AN260) -> 0 | C77: =CHOOSE($B$3,Cons!AO260,Base!AO260,Aggr!AO260,EntDelay!AO260,HiAI!AO260,Incident!AO260,EntGated!AO260,FullScope!AO260) -> 256.9664 | D77: =CHOOSE($B$3,Cons!AP260,Base!AP260,Aggr!AP260,EntDelay!AP260,HiAI!AP260,Incident!AP260,EntGated!AP260,FullScope!AP260) -> 719.9672
A78: Monthly-active users at year end | B78: =CHOOSE($B$3,Cons!AN261,Base!AN261,Aggr!AN261,EntDelay!AN261,HiAI!AN261,Incident!AN261,EntGated!AN261,FullScope!AN261) -> 3041.2157 | C78: =CHOOSE($B$3,Cons!AO261,Base!AO261,Aggr!AO261,EntDelay!AO261,HiAI!AO261,Incident!AO261,EntGated!AO261,FullScope!AO261) -> 23495.015 | D78: =CHOOSE($B$3,Cons!AP261,Base!AP261,Aggr!AP261,EntDelay!AP261,HiAI!AP261,Incident!AP261,EntGated!AP261,FullScope!AP261) -> 74697.55
A79: AI cost per MAU per month (average) | B79: =CHOOSE($B$3,Cons!AN262,Base!AN262,Aggr!AN262,EntDelay!AN262,HiAI!AN262,Incident!AN262,EntGated!AN262,FullScope!AN262) -> 1.5059971 | C79: =CHOOSE($B$3,Cons!AO262,Base!AO262,Aggr!AO262,EntDelay!AO262,HiAI!AO262,Incident!AO262,EntGated!AO262,FullScope!AO262) -> 0.42927147 | D79: =CHOOSE($B$3,Cons!AP262,Base!AP262,Aggr!AP262,EntDelay!AP262,HiAI!AP262,Incident!AP262,EntGated!AP262,FullScope!AP262) -> 0.30885092
... A88: Paying share of consumer users at year end | B88: =CHOOSE($B$3,Cons!AN271,Base!AN271,Aggr!AN271,EntDelay!AN271,HiAI!AN271,Incident!AN271,EntGated!AN271,FullScope!AN271) -> 0 | C88: =CHOOSE($B$3,Cons!AO271,Base!AO271,Aggr!AO271,EntDelay!AO271,HiAI!AO271,Incident!AO271,EntGated!AO271,FullScope!AO271) -> 0.015329184 | D88: =CHOOSE($B$3,Cons!AP271,Base!AP271,Aggr!AP271,EntDelay!AP271,HiAI!AP271,Incident!AP271,EntGated!AP271,FullScope!AP271) -> 0.025705985
A91: Monthly series (selected scenario)
A92: Month | B92: 1 | C92: 2 | D92: 3 | E92: 4 | F92: 5 | G92: 6 | H92: 7 | I92: 8 | J92: 9 | K92: 10 | L92: 11 | M92: 12 | N92: 13 | O92: 14 | P92: 15 | Q92: 16 | R92: 17 | S92: 18 | T92: 19 | U92: 20 | V92: 21 | W92: 22 | X92: 23 | Y92: 24 | Z92: 25 | AA92: 26 | AB92: 27 | AC92: 28 | AD92: 29 | AE92: 30 | AF92: 31 | AG92: 32 | AH92: 33 | AI92: 34 | AJ92: 35 | AK92: 36
A93: ARR | B93: =CHOOSE($B$3,Cons!C148,Base!C148,Aggr!C148,EntDelay!C148,HiAI!C148,Incident!C148,EntGated!C148,FullScope!C148) -> 0 | C93: =CHOOSE($B$3,Cons!D148,Base!D148,Aggr!D148,EntDelay!D148,HiAI!D148,Incident!D148,EntGated!D148,FullScope!D148) -> 0 | D93: =CHOOSE($B$3,Cons!E148,Base!E148,Aggr!E148,EntDelay!E148,HiAI!E148,Incident!E148,EntGated!E148,FullScope!E148) -> 0 | E93: =CHOOSE($B$3,Cons!F148,Base!F148,Aggr!F148,EntDelay!F148,HiAI!F148,Incident!F148,EntGated!F148,FullScope!F148) -> 0 | F93: =CHOOSE($B$3,Cons!G148,Base!G148,Aggr!G148,EntDelay!G148,HiAI!G148,Incident!G148,EntGated!G148,FullScope!G148) -> 0 | G93: =CHOOSE($B$3,Cons!H148,Base!H148,Aggr!H148,EntDelay!H148,HiAI!H148,Incident!H148,EntGated!H148,FullScope!H148) -> 0 | H93: =CHOOSE($B$3,Cons!I148,Base!I148,Aggr!I148,EntDelay!I148,HiAI!I148,Incident!I148,EntGated!I148,FullScope!I148) -> 0 | I93: =CHOOSE($B$3,Cons!J148,Base!J148,Aggr!J148,EntDelay!J148,HiAI!J148,Incident!J148,EntGated!J148,FullScope!J148) -> 0 | ... AK93: =CHOOSE($B$3,Cons!AL148,Base!AL148,Aggr!AL148,EntDelay!AL148,HiAI!AL148,Incident!AL148,EntGated!AL148,FullScope!AL148) -> 1527680.4
A94: Monthly revenue | B94: =CHOOSE($B$3,Cons!C146,Base!C146,Aggr!C146,EntDelay!C146,HiAI!C146,Incident!C146,EntGated!C146,FullScope!C146) -> 0 | C94: =CHOOSE($B$3,Cons!D146,Base!D146,Aggr!D146,EntDelay!D146,HiAI!D146,Incident!D146,EntGated!D146,FullScope!D146) -> 0 | D94: =CHOOSE($B$3,Cons!E146,Base!E146,Aggr!E146,EntDelay!E146,HiAI!E146,Incident!E146,EntGated!E146,FullScope!E146) -> 0 | E94: =CHOOSE($B$3,Cons!F146,Base!F146,Aggr!F146,EntDelay!F146,HiAI!F146,Incident!F146,EntGated!F146,FullScope!F146) -> 0 | F94: =CHOOSE($B$3,Cons!G146,Base!G146,Aggr!G146,EntDelay!G146,HiAI!G146,Incident!G146,EntGated!G146,FullScope!G146) -> 0 | G94: =CHOOSE($B$3,Cons!H146,Base!H146,Aggr!H146,EntDelay!H146,HiAI!H146,Incident!H146,EntGated!H146,FullScope!H146) -> 0 | H94: =CHOOSE($B$3,Cons!I146,Base!I146,Aggr!I146,EntDelay!I146,HiAI!I146,Incident!I146,EntGated!I146,FullScope!I146) -> 0 | I94: =CHOOSE($B$3,Cons!J146,Base!J146,Aggr!J146,EntDelay!J146,HiAI!J146,Incident!J146,EntGated!J146,FullScope!J146) -> 0 | ... AK94: =CHOOSE($B$3,Cons!AL146,Base!AL146,Aggr!AL146,EntDelay!AL146,HiAI!AL146,Incident!AL146,EntGated!AL146,FullScope!AL146) -> 359931.63
A95: Operating cash flow | B95: =CHOOSE($B$3,Cons!C226,Base!C226,Aggr!C226,EntDelay!C226,HiAI!C226,Incident!C226,EntGated!C226,FullScope!C226) -> -104365.44 | C95: =CHOOSE($B$3,Cons!D226,Base!D226,Aggr!D226,EntDelay!D226,HiAI!D226,Incident!D226,EntGated!D226,FullScope!D226) -> -104417.58 | D95: =CHOOSE($B$3,Cons!E226,Base!E226,Aggr!E226,EntDelay!E226,HiAI!E226,Incident!E226,EntGated!E226,FullScope!E226) -> -130322.14 | E95: =CHOOSE($B$3,Cons!F226,Base!F226,Aggr!F226,EntDelay!F226,HiAI!F226,Incident!F226,EntGated!F226,FullScope!F226) -> -145435.8 | F95: =CHOOSE($B$3,Cons!G226,Base!G226,Aggr!G226,EntDelay!G226,HiAI!G226,Incident!G226,EntGated!G226,FullScope!G226) -> -185783.88 | G95: =CHOOSE($B$3,Cons!H226,Base!H226,Aggr!H226,EntDelay!H226,HiAI!H226,Incident!H226,EntGated!H226,FullScope!H226) -> -213418.93 | H95: =CHOOSE($B$3,Cons!I226,Base!I226,Aggr!I226,EntDelay!I226,HiAI!I226,Incident!I226,EntGated!I226,FullScope!I226) -> -217744.5 | I95: =CHOOSE($B$3,Cons!J226,Base!J226,Aggr!J226,EntDelay!J226,HiAI!J226,Incident!J226,EntGated!J226,FullScope!J226) -> -206733.01 | ... AK95: =CHOOSE($B$3,Cons!AL226,Base!AL226,Aggr!AL226,EntDelay!AL226,HiAI!AL226,Incident!AL226,EntGated!AL226,FullScope!AL226) -> -372324.6
A96: Cumulative operating cash flow | B96: =CHOOSE($B$3,Cons!C227,Base!C227,Aggr!C227,EntDelay!C227,HiAI!C227,Incident!C227,EntGated!C227,FullScope!C227) -> -104365.44 | C96: =CHOOSE($B$3,Cons!D227,Base!D227,Aggr!D227,EntDelay!D227,HiAI!D227,Incident!D227,EntGated!D227,FullScope!D227) -> -208783.02 | D96: =CHOOSE($B$3,Cons!E227,Base!E227,Aggr!E227,EntDelay!E227,HiAI!E227,Incident!E227,EntGated!E227,FullScope!E227) -> -339105.16 | E96: =CHOOSE($B$3,Cons!F227,Base!F227,Aggr!F227,EntDelay!F227,HiAI!F227,Incident!F227,EntGated!F227,FullScope!F227) -> -484540.96 | F96: =CHOOSE($B$3,Cons!G227,Base!G227,Aggr!G227,EntDelay!G227,HiAI!G227,Incident!G227,EntGated!G227,FullScope!G227) -> -670324.84 | G96: =CHOOSE($B$3,Cons!H227,Base!H227,Aggr!H227,EntDelay!H227,HiAI!H227,Incident!H227,EntGated!H227,FullScope!H227) -> -883743.78 | H96: =CHOOSE($B$3,Cons!I227,Base!I227,Aggr!I227,EntDelay!I227,HiAI!I227,Incident!I227,EntGated!I227,FullScope!I227) -> -1101488.3 | I96: =CHOOSE($B$3,Cons!J227,Base!J227,Aggr!J227,EntDelay!J227,HiAI!J227,Incident!J227,EntGated!J227,FullScope!J227) -> -1308221.3 | ... AK96: =CHOOSE($B$3,Cons!AL227,Base!AL227,Aggr!AL227,EntDelay!AL227,HiAI!AL227,Incident!AL227,EntGated!AL227,FullScope!AL227) -> -12727188

Sheet Compare
A1: Scenario comparison (live: every cell reads the scenario sheets)
A3: Metric | B3: Conservative | C3: Base | D3: Aggressive | E3: Enterprise-delayed | F3: High AI cost | G3: Incident (SEV-0, month 14) | H3: Enterprise-delayed, gated hiring (mitigation) | I3: Full-scope staffing (CTO pack S1-S4), Base revenue
A4: Revenue, Year 1 | B4: =Cons!AN146 -> 0 | C4: =Base!AN146 -> 1320 | D4: =Aggr!AN146 -> 28052 | E4: =EntDelay!AN146 -> 0 | F4: =HiAI!AN146 -> 1320 | G4: =Incident!AN146 -> 1320 | H4: =EntGated!AN146 -> 0 | I4: =FullScope!AN146 -> 1320
A5: Revenue, Year 2 | B5: =Cons!AO146 -> 227178.67 | C5: =Base!AO146 -> 506926.16 | D5: =Aggr!AO146 -> 915384.65 | E5: =EntDelay!AO146 -> 166843.3 | F5: =HiAI!AO146 -> 506926.16 | G5: =Incident!AO146 -> 343437.13 | H5: =EntGated!AO146 -> 166843.3 | I5: =FullScope!AO146 -> 506926.16
A6: Revenue, Year 3 | B6: =Cons!AP146 -> 1059403.9 | C6: =Base!AP146 -> 2301941.7 | D6: =Aggr!AP146 -> 3998129.9 | E6: =EntDelay!AP146 -> 1255579.2 | F6: =HiAI!AP146 -> 2301941.7 | G6: =Incident!AP146 -> 2244826.9 | H6: =EntGated!AP146 -> 1255579.2 | I6: =FullScope!AP146 -> 2301941.7
A7: ARR, month 12 | B7: =Cons!AN148 -> 0 | C7: =Base!AN148 -> 15840 | D7: =Aggr!AN148 -> 17424 | E7: =EntDelay!AN148 -> 0 | F7: =HiAI!AN148 -> 15840 | G7: =Incident!AN148 -> 15840 | H7: =EntGated!AN148 -> 0 | I7: =FullScope!AN148 -> 15840
A8: ARR, month 24 | B8: =Cons!AO148 -> 64050.328 | C8: =Base!AO148 -> 163394.4 | D8: =Aggr!AO148 -> 456730.18 | E8: =EntDelay!AO148 -> 77176.081 | F8: =HiAI!AO148 -> 163394.4 | G8: =Incident!AO148 -> 135929.75 | H8: =EntGated!AO148 -> 77176.081 | I8: =FullScope!AO148 -> 163394.4
A9: ARR, month 36 | B9: =Cons!AP148 -> 531664.39 | C9: =Base!AP148 -> 1527680.4 | D9: =Aggr!AP148 -> 2818093.1 | E9: =EntDelay!AP148 -> 728214.21 | F9: =HiAI!AP148 -> 1527680.4 | G9: =Incident!AP148 -> 1463532.3 | H9: =EntGated!AP148 -> 728214.21 | I9: =FullScope!AP148 -> 1527680.4
A10: Annual logos, month 36 | B10: =Cons!AP122 -> 9.204 | C10: =Base!AP122 -> 24.39864 | D10: =Aggr!AP122 -> 45.950975 | E10: =EntDelay!AP122 -> 10.8654 | F10: =HiAI!AP122 -> 24.39864 | G10: =Incident!AP122 -> 22.94784 | H10: =EntGated!AP122 -> 10.8654 | I10: =FullScope!AP122 -> 24.39864
A11: Paying students, month 36 | B11: =Cons!AP39 -> 354.29378 | C11: =Base!AP39 -> 719.9672 | D11: =Aggr!AP39 -> 1266.8546 | E11: =EntDelay!AP39 -> 719.9672 | F11: =HiAI!AP39 -> 719.9672 | G11: =Incident!AP39 -> 718.96313 | H11: =EntGated!AP39 -> 719.9672 | I11: =FullScope!AP39 -> 719.9672
A12: Gross margin, Year 3 | B12: =Cons!AP237 -> -0.6899905 | C12: =Base!AP237 -> 0.15869686 | D12: =Aggr!AP237 -> 0.46284003 | E12: =EntDelay!AP237 -> -0.45185041 | F12: =HiAI!AP237 -> 0.012996709 | G12: =Incident!AP237 -> 0.14402104 | H12: =EntGated!AP237 -> -0.20488604 | I12: =FullScope!AP237 -> 0.15869686
A13: Contribution margin, Year 3 | B13: =Cons!AP238 -> -0.83333492 | C13: =Base!AP238 -> 0.03132265 | D13: =Aggr!AP238 -> 0.35232348 | E13: =EntDelay!AP238 -> -0.59516989 | F13: =HiAI!AP238 -> -0.1143775 | G13: =Incident!AP238 -> 0.014690296 | H13: =EntGated!AP238 -> -0.34820552 | I13: =FullScope!AP238 -> 0.03132265
A14: Operating result, Year 1 | B14: =Cons!AN225 -> -2452578.1 | C14: =Base!AN225 -> -2454419 | D14: =Aggr!AN225 -> -2435255.3 | E14: =EntDelay!AN225 -> -2453970.7 | F14: =HiAI!AN225 -> -2463990 | G14: =Incident!AN225 -> -2454419 | H14: =EntGated!AN225 -> -2318170.7 | I14: =FullScope!AN225 -> -3138185.6
A15: Operating result, Year 2 | B15: =Cons!AO225 -> -5018193 | C15: =Base!AO225 -> -4797597.1 | D15: =Aggr!AO225 -> -4505533.6 | E15: =EntDelay!AO225 -> -5076094.5 | F15: =HiAI!AO225 -> -4886552.6 | G15: =Incident!AO225 -> -5634046.3 | H15: =EntGated!AO225 -> -4620244.5 | I15: =FullScope!AO225 -> -8109980.4
A16: Operating result, Year 3 | B16: =Cons!AP225 -> -6382264.8 | C16: =Base!AP225 -> -5445485.4 | D16: =Aggr!AP225 -> -4129633.2 | E16: =EntDelay!AP225 -> -6250150.8 | F16: =HiAI!AP225 -> -5780878.6 | G16: =Incident!AP225 -> -5484038.8 | H16: =EntGated!AP225 -> -5816367.5 | I16: =FullScope!AP225 -> -10842352
A17: Net burn, Year 1 | B17: =Cons!AN245 -> 2452578.1 | C17: =Base!AN245 -> 2455739 | D17: =Aggr!AN245 -> 2463307.3 | E17: =EntDelay!AN245 -> 2453970.7 | F17: =HiAI!AN245 -> 2465310 | G17: =Incident!AN245 -> 2455739 | H17: =EntGated!AN245 -> 2318170.7 | I17: =FullScope!AN245 -> 3139505.6
A18: Net burn, Year 2 | B18: =Cons!AO245 -> 5019727.7 | C18: =Base!AO245 -> 4780289.3 | D18: =Aggr!AO245 -> 4575996.8 | E18: =EntDelay!AO245 -> 5028976.3 | F18: =HiAI!AO245 -> 4869244.8 | G18: =Incident!AO245 -> 5611294.4 | H18: =EntGated!AO245 -> 4573126.3 | I18: =FullScope!AO245 -> 8092672.6
A19: Net burn, Year 3 | B19: =Cons!AP245 -> 6258663.4 | C19: =Base!AP245 -> 5491159.8 | D19: =Aggr!AP245 -> 3620884.8 | E19: =EntDelay!AP245 -> 6254569.5 | F19: =HiAI!AP245 -> 5826553 | G19: =Incident!AP245 -> 5530591.5 | H19: =EntGated!AP245 -> 5820786.2 | I19: =FullScope!AP245 -> 10888026
A20: Cumulative cash need through month 12 | B20: =-Cons!AN227 -> 2452578.1 | C20: =-Base!AN227 -> 2455739 | D20: =-Aggr!AN227 -> 2463307.3 | E20: =-EntDelay!AN227 -> 2453970.7 | F20: =-HiAI!AN227 -> 2465310 | G20: =-Incident!AN227 -> 2455739 | H20: =-EntGated!AN227 -> 2318170.7 | I20: =-FullScope!AN227 -> 3139505.6
A21: Cumulative cash need through month 24 | B21: =-Cons!AO227 -> 7472305.8 | C21: =-Base!AO227 -> 7236028.2 | D21: =-Aggr!AO227 -> 7039304.1 | E21: =-EntDelay!AO227 -> 7482947 | F21: =-HiAI!AO227 -> 7334554.8 | G21: =-Incident!AO227 -> 8067033.3 | H21: =-EntGated!AO227 -> 6891297 | I21: =-FullScope!AO227 -> 11232178
A22: Cumulative cash need through month 36 | B22: =-Cons!AP227 -> 13730969 | C22: =-Base!AP227 -> 12727188 | D22: =-Aggr!AP227 -> 10660189 | E22: =-EntDelay!AP227 -> 13737516 | F22: =-HiAI!AP227 -> 13161108 | G22: =-Incident!AP227 -> 13597625 | H22: =-EntGated!AP227 -> 12712083 | I22: =-FullScope!AP227 -> 22120205
A23: PEAK FUNDING NEED (deepest cumulative cash trough, months 1-36) | B23: =-MIN(Cons!C227:AL227) -> 13730969 | C23: =-MIN(Base!C227:AL227) -> 12727188 | D23: =-MIN(Aggr!C227:AL227) -> 10694710 | E23: =-MIN(EntDelay!C227:AL227) -> 13737516 | F23: =-MIN(HiAI!C227:AL227) -> 13161108 | G23: =-MIN(Incident!C227:AL227) -> 13597625 | H23: =-MIN(EntGated!C227:AL227) -> 12712083 | I23: =-MIN(FullScope!C227:AL227) -> 22120205
A24: Month cash runs out on the illustrative opening capital (blank = not within 36 months) | B24: =IFERROR(MATCH(1,Cons!C229:AL229,0),"") -> 14 | C24: =IFERROR(MATCH(1,Base!C229:AL229,0),"") -> 14 | D24: =IFERROR(MATCH(1,Aggr!C229:AL229,0),"") -> 14 | E24: =IFERROR(MATCH(1,EntDelay!C229:AL229,0),"") -> 14 | F24: =IFERROR(MATCH(1,HiAI!C229:AL229,0),"") -> 14 | G24: =IFERROR(MATCH(1,Incident!C229:AL229,0),"") -> 14 | H24: =IFERROR(MATCH(1,EntGated!C229:AL229,0),"") -> 15 | I24: =IFERROR(MATCH(1,FullScope!C229:AL229,0),"") -> 12
A25: Burn multiple, Year 3 | B25: =Cons!AP249 -> 13.38425 | C25: =Base!AP249 -> 4.0249331 | D25: =Aggr!AP249 -> 1.5333876 | E25: =EntDelay!AP249 -> 9.6070709 | F25: =HiAI!AP249 -> 4.270771 | G25: =Incident!AP249 -> 4.1658489 | H25: =EntGated!AP249 -> 8.9407761 | I25: =FullScope!AP249 -> 7.9807508
A26: Implementation margin, Year 3 (actual team cost) | B26: =Cons!AP241 -> -0.69558133 | C26: =Base!AP241 -> 0.21377778 | D26: =Aggr!AP241 -> 0.54383703 | E26: =EntDelay!AP241 -> -0.42202572 | F26: =HiAI!AP241 -> 0.21377778 | G26: =Incident!AP241 -> 0.21377778 | H26: =EntGated!AP241 -> -0.078778135 | I26: =FullScope!AP241 -> 0.21377778
A27: Implementation utilization, Year 3 | B27: =Cons!AP243 -> 0.47680251 | C27: =Base!AP243 -> 1.0824451 | D27: =Aggr!AP243 -> 1.694629 | E27: =EntDelay!AP243 -> 0.59435737 | F27: =HiAI!AP243 -> 1.0824451 | G27: =Incident!AP243 -> 1.0824451 | H27: =EntGated!AP243 -> 0.78347107 | I27: =FullScope!AP243 -> 1.0824451
A28: Student LTV / CAC, Year 3 | B28: =Cons!AP268 -> 0.090155814 | C28: =Base!AP268 -> 0.20017006 | D28: =Aggr!AP268 -> 0.36857617 | E28: =EntDelay!AP268 -> 0.20017006 | F28: =HiAI!AP268 -> 0.092456588 | G28: =Incident!AP268 -> 0.2003196 | H28: =EntGated!AP268 -> 0.20017006 | I28: =FullScope!AP268 -> 0.20017006
A29: AI cost as share of revenue, Year 3 | B29: =Cons!AP263 -> 0.11501075 | C29: =Base!AP263 -> 0.079046824 | D29: =Aggr!AP263 -> 0.068024311 | E29: =EntDelay!AP263 -> 0.10726571 | F29: =HiAI!AP263 -> 0.22474697 | G29: =Incident!AP263 -> 0.078215714 | H29: =EntGated!AP263 -> 0.10726571 | I29: =FullScope!AP263 -> 0.079046824
A30: Headcount, month 36 (FTE) | B30: =Cons!AP196 -> 40.4 | C30: =Base!AP196 -> 40.4 | D30: =Aggr!AP196 -> 40.4 | E30: =EntDelay!AP196 -> 40.4 | F30: =HiAI!AP196 -> 40.4 | G30: =Incident!AP196 -> 40.4 | H30: =EntGated!AP196 -> 38.4 | I30: =FullScope!AP196 -> 70.4

Sheet Checks
A1: Model integrity checks (every line must read OK)
A3: Check | B3: Cons | C3: Base | D3: Aggr | E3: EntDelay | F3: HiAI | G3: Incident | H3: EntGated | I3: FullScope
A4: Cost-of-revenue lines sum to the allocated total (max abs difference < $0.01) | B4: =IF(AND(MAX(Cons!C185:AL185)<0.01,MIN(Cons!C185:AL185)>-0.01),"OK","FAIL") -> OK | C4: =IF(AND(MAX(Base!C185:AL185)<0.01,MIN(Base!C185:AL185)>-0.01),"OK","FAIL") -> OK | D4: =IF(AND(MAX(Aggr!C185:AL185)<0.01,MIN(Aggr!C185:AL185)>-0.01),"OK","FAIL") -> OK | E4: =IF(AND(MAX(EntDelay!C185:AL185)<0.01,MIN(EntDelay!C185:AL185)>-0.01),"OK","FAIL") -> OK | F4: =IF(AND(MAX(HiAI!C185:AL185)<0.01,MIN(HiAI!C185:AL185)>-0.01),"OK","FAIL") -> OK | G4: =IF(AND(MAX(Incident!C185:AL185)<0.01,MIN(Incident!C185:AL185)>-0.01),"OK","FAIL") -> OK | H4: =IF(AND(MAX(EntGated!C185:AL185)<0.01,MIN(EntGated!C185:AL185)>-0.01),"OK","FAIL") -> OK | I4: =IF(AND(MAX(FullScope!C185:AL185)<0.01,MIN(FullScope!C185:AL185)>-0.01),"OK","FAIL") -> OK
A5: Deferred revenue never negative | B5: =IF(MIN(Cons!C154:AL154)>-0.01,"OK","FAIL") -> OK | C5: =IF(MIN(Base!C154:AL154)>-0.01,"OK","FAIL") -> OK | D5: =IF(MIN(Aggr!C154:AL154)>-0.01,"OK","FAIL") -> OK | E5: =IF(MIN(EntDelay!C154:AL154)>-0.01,"OK","FAIL") -> OK | F5: =IF(MIN(HiAI!C154:AL154)>-0.01,"OK","FAIL") -> OK | G5: =IF(MIN(Incident!C154:AL154)>-0.01,"OK","FAIL") -> OK | H5: =IF(MIN(EntGated!C154:AL154)>-0.01,"OK","FAIL") -> OK | I5: =IF(MIN(FullScope!C154:AL154)>-0.01,"OK","FAIL") -> OK
A6: Receivables never negative | B6: =IF(MIN(Cons!C155:AL155)>-0.01,"OK","FAIL") -> OK | C6: =IF(MIN(Base!C155:AL155)>-0.01,"OK","FAIL") -> OK | D6: =IF(MIN(Aggr!C155:AL155)>-0.01,"OK","FAIL") -> OK | E6: =IF(MIN(EntDelay!C155:AL155)>-0.01,"OK","FAIL") -> OK | F6: =IF(MIN(HiAI!C155:AL155)>-0.01,"OK","FAIL") -> OK | G6: =IF(MIN(Incident!C155:AL155)>-0.01,"OK","FAIL") -> OK | H6: =IF(MIN(EntGated!C155:AL155)>-0.01,"OK","FAIL") -> OK | I6: =IF(MIN(FullScope!C155:AL155)>-0.01,"OK","FAIL") -> OK
A7: Cumulative cash equals the sum of monthly operating cash flow | B7: =IF(ABS(SUM(Cons!C226:AL226)-Cons!AL227)<0.01,"OK","FAIL") -> OK | C7: =IF(ABS(SUM(Base!C226:AL226)-Base!AL227)<0.01,"OK","FAIL") -> OK | D7: =IF(ABS(SUM(Aggr!C226:AL226)-Aggr!AL227)<0.01,"OK","FAIL") -> OK | E7: =IF(ABS(SUM(EntDelay!C226:AL226)-EntDelay!AL227)<0.01,"OK","FAIL") -> OK | F7: =IF(ABS(SUM(HiAI!C226:AL226)-HiAI!AL227)<0.01,"OK","FAIL") -> OK | G7: =IF(ABS(SUM(Incident!C226:AL226)-Incident!AL227)<0.01,"OK","FAIL") -> OK | H7: =IF(ABS(SUM(EntGated!C226:AL226)-EntGated!AL227)<0.01,"OK","FAIL") -> OK | I7: =IF(ABS(SUM(FullScope!C226:AL226)-FullScope!AL227)<0.01,"OK","FAIL") -> OK
A8: Billings less revenue equals deferred revenue at month 36 | B8: =IF(ABS(SUM(Cons!C151:AL151)-SUM(Cons!C146:AL146)-Cons!AL154)<0.01,"OK","FAIL") -> OK | C8: =IF(ABS(SUM(Base!C151:AL151)-SUM(Base!C146:AL146)-Base!AL154)<0.01,"OK","FAIL") -> OK | D8: =IF(ABS(SUM(Aggr!C151:AL151)-SUM(Aggr!C146:AL146)-Aggr!AL154)<0.01,"OK","FAIL") -> OK | E8: =IF(ABS(SUM(EntDelay!C151:AL151)-SUM(EntDelay!C146:AL146)-EntDelay!AL154)<0.01,"OK","FAIL") -> OK | F8: =IF(ABS(SUM(HiAI!C151:AL151)-SUM(HiAI!C146:AL146)-HiAI!AL154)<0.01,"OK","FAIL") -> OK | G8: =IF(ABS(SUM(Incident!C151:AL151)-SUM(Incident!C146:AL146)-Incident!AL154)<0.01,"OK","FAIL") -> OK | H8: =IF(ABS(SUM(EntGated!C151:AL151)-SUM(EntGated!C146:AL146)-EntGated!AL154)<0.01,"OK","FAIL") -> OK | I8: =IF(ABS(SUM(FullScope!C151:AL151)-SUM(FullScope!C146:AL146)-FullScope!AL154)<0.01,"OK","FAIL") -> OK
A9: Headcount at month 36 equals month-1 headcount plus hires from month 2 | B9: =IF(ABS(Cons!C196+SUM(Cons!D198:AL198)-Cons!AL196)<0.001,"OK","FAIL") -> OK | C9: =IF(ABS(Base!C196+SUM(Base!D198:AL198)-Base!AL196)<0.001,"OK","FAIL") -> OK | D9: =IF(ABS(Aggr!C196+SUM(Aggr!D198:AL198)-Aggr!AL196)<0.001,"OK","FAIL") -> OK | E9: =IF(ABS(EntDelay!C196+SUM(EntDelay!D198:AL198)-EntDelay!AL196)<0.001,"OK","FAIL") -> OK | F9: =IF(ABS(HiAI!C196+SUM(HiAI!D198:AL198)-HiAI!AL196)<0.001,"OK","FAIL") -> OK | G9: =IF(ABS(Incident!C196+SUM(Incident!D198:AL198)-Incident!AL196)<0.001,"OK","FAIL") -> OK | H9: =IF(ABS(EntGated!C196+SUM(EntGated!D198:AL198)-EntGated!AL196)<0.001,"OK","FAIL") -> OK | I9: =IF(ABS(FullScope!C196+SUM(FullScope!D198:AL198)-FullScope!AL196)<0.001,"OK","FAIL") -> OK
A10: No subscriber, user or logo count below zero | B10: =IF(MIN(Cons!C29:AL29,Cons!C39:AL39,Cons!C122:AL122)>-0.001,"OK","FAIL") -> OK | C10: =IF(MIN(Base!C29:AL29,Base!C39:AL39,Base!C122:AL122)>-0.001,"OK","FAIL") -> OK | D10: =IF(MIN(Aggr!C29:AL29,Aggr!C39:AL39,Aggr!C122:AL122)>-0.001,"OK","FAIL") -> OK | E10: =IF(MIN(EntDelay!C29:AL29,EntDelay!C39:AL39,EntDelay!C122:AL122)>-0.001,"OK","FAIL") -> OK | F10: =IF(MIN(HiAI!C29:AL29,HiAI!C39:AL39,HiAI!C122:AL122)>-0.001,"OK","FAIL") -> OK | G10: =IF(MIN(Incident!C29:AL29,Incident!C39:AL39,Incident!C122:AL122)>-0.001,"OK","FAIL") -> OK | H10: =IF(MIN(EntGated!C29:AL29,EntGated!C39:AL39,EntGated!C122:AL122)>-0.001,"OK","FAIL") -> OK | I10: =IF(MIN(FullScope!C29:AL29,FullScope!C39:AL39,FullScope!C122:AL122)>-0.001,"OK","FAIL") -> OK
A11: Seasonality index sums to 12 | B11: =IF(ABS(Assumptions!$C$179-12)<0.0001,"OK","FAIL") -> OK
A12: ALL CHECKS | B12: =IF(COUNTIF(B4:I11,"FAIL")=0,"OK","FAIL") -> OK

Sheet Scenarios
A1: Scenario parameters
A3: Parameter | B3: Unit | C3: Conservative | D3: Base | E3: Aggressive | F3: Enterprise-delayed | G3: High AI cost | H3: Incident (SEV-0, month 14) | I3: Enterprise-delayed, gated hiring (mitigation) | J3: Full-scope staffing (CTO pack S1-S4), Base revenue | K3: Note
A4: Organic student acquisition multiplier | B4: x | C4: 0.6 | D4: 1 | E4: 1.5 | F4: 1 | G4: 1 | H4: 1 | I4: 1 | J4: 1
A5: Free-to-paid conversion multiplier | B5: x | C5: 0.8 | D5: 1 | E5: 1.2 | F5: 1 | G5: 1 | H5: 1 | I5: 1 | J5: 1
A6: Churn multiplier (students and institutions) | B6: x | C6: 1.25 | D6: 1 | E6: 0.85 | F6: 1 | G6: 1 | H6: 1 | I6: 1 | J6: 1
A7: Pilot and direct-deal volume multiplier | B7: x | C7: 0.6 | D7: 1 | E7: 1.4 | F7: 1 | G7: 1 | H7: 1 | I7: 1 | J7: 1
A8: Pilot-to-annual conversion multiplier | B8: x | C8: 0.8 | D8: 1 | E8: 1.1 | F8: 0.9 | G8: 1 | H8: 1 | I8: 0.9 | J8: 1
A9: Institutional gates slip by (months) | B9: months | C9: 2 | D9: 0 | E9: -2 | F9: 6 | G9: 0 | H9: 0 | I9: 6 | J9: 0 | K9: Slips (negative = earlier) the paid-pilot, direct and enterprise gates (and design-partner conversion).
A10: Institutional price realization multiplier | B10: x | C10: 0.95 | D10: 1 | E10: 1 | F10: 1 | G10: 1 | H10: 1 | I10: 1 | J10: 1
A11: Paid acquisition cost multiplier | B11: x | C11: 1.25 | D11: 1 | E11: 0.85 | F11: 1 | G11: 1 | H11: 1 | I11: 1 | J11: 1
A12: AI unit cost multiplier (price or model-mix shift) | B12: x | C12: 1 | D12: 1 | E12: 1 | F12: 1 | G12: 2.5 | H12: 1 | I12: 1 | J12: 1
A13: AI usage multiplier (requests per user) | B13: x | C13: 1 | D13: 1 | E13: 1 | F13: 1 | G13: 1.5 | H13: 1 | I13: 1 | J13: 1
A14: Incident switch (1 = on) | B14: 0/1 | C14: 0 | D14: 0 | E14: 0 | F14: 0 | G14: 0 | H14: 1 | I14: 0 | J14: 0
A15: Delay for gated hires (months) | B15: months | C15: 0 | D15: 0 | E15: 0 | F15: 0 | G15: 0 | H15: 0 | I15: 6 | J15: 0 | K15: Mitigation lever: sales, implementation, CS, partnerships roles wait for the evidence gate.
A16: Full-scope staffing switch (1 = include the CTO-pack staffing roles) | B16: 0/1 | C16: 0 | D16: 0 | E16: 0 | F16: 0 | G16: 0 | H16: 0 | I16: 0 | J16: 1 | K16: Same revenue as Base; costs the staffing plan proposed in docs/target-architecture/08.
A19: Incident cost inputs live on Assumptions (group: Incident scenario). They apply only where the incident switch is 1.

Sheet Assumptions
A1: Assumptions register (every number is a planning assumption unless tagged FACT)
A3: ID | B3: Assumption | C3: Value | D3: Unit | E3: Tag | F3: Source / what would change it
A4: Go / no-go gates (controlling document: GO-NO-GO-DECISION.md, 3 Oct 2026)
A5: gate_plus | B5: Month broad / paid individual acquisition may begin (checkout hold lifted) | C5: 13 | D5: month | E5: DECIDE | F5: Today NO-GO (INDIVIDUAL_PAID_ACQUISITION_ENABLED = false). Needs invitation-validation closeout + a separate broad-rollout decision.
A6: pre_gate_share | B6: Share of organic signups before that gate (invitation-only, unpaid validation cohorts) | C6: 0.25 | D6: % | E6: DECIDE | F6: Conditional GO covers invitation-only, unpaid validation only.
A7: gate_pilot | B7: Month the first PAID institutional pilot may begin | C7: 12 | D7: month | E7: DECIDE | F7: Today NO-GO. Reconsidered only after a design-partner pilot has an approved activation record and a measured 26-week closeout (D-134).
A8: gate_direct | B8: Month direct annual sales (no pilot first) may begin | C8: 22 | D8: month | E8: DECIDE | F8: After the first pilot-to-annual conversions are evidenced.
A9: gate_ent | B9: Month System-tier / broad enterprise sale may begin | C9: 26 | D9: month | E9: DECIDE | F9: Last motion to reconsider: repeated deployments and independent assurance first.
A10: dp_rho | B10: Design-partner pilot to paid annual conversion | C10: 0.6 | D10: % | E10: HYP | F10: Unpaid design partners; converts only after the paid-pilot gate.
A11: Student subscription
A12: price_m | B12: Plus list price, monthly | C12: 7.99 | D12: $/mo | E12: FACT | F12: D-134 and docs/COMMERCIAL-CORE.md; the catalog charges this.
A13: price_a | B13: Plus list price, annual | C13: 59 | D13: $/yr | E13: FACT | F13: D-134. Effective $4.92/mo.
A14: stud_disc | B14: Average promotional / edu discount on list | C14: 0.1 | D14: % | E14: HYP | F14: No promo program exists. Counsel to review any student-pricing claim.
A15: refund | B15: Refunds + chargebacks, share of billings | C15: 0.033 | D15: % | E15: HYP | F15: Contra-revenue. Refund policy is not yet approved.
A16: organic_start | B16: Organic + campus-led free signups, month 1 | C16: 1200 | D16: users/mo | E16: HYP | F16: No acquisition history. Pre-seasonality trend.
A17: cps | B17: Paid acquisition: cost per free signup | C17: 3 | D17: $ | E17: HYP | F17: Test in paid channels before scaling; student CPI varies widely.
A18: activation | B18: Signups that become monthly-active | C18: 0.6 | D18: % | E18: HYP | F18: Measure with the activation definition in ANALYTICS.md.
A19: free_churn | B19: Monthly churn of active free users | C19: 0.12 | D19: % | E19: HYP | F19: Academic-calendar driven; calibrate on cohorts.
A20: conv | B20: Free-to-paid conversion, monthly, of active free base | C20: 0.0025 | D20: % | E20: HYP | F20: No paying cohort evidenced. Single most sensitive consumer input.
A21: annual_mix | B21: Share of new paid on annual plan | C21: 0.45 | D21: % | E21: HYP
A22: churn_m | B22: Monthly plan churn (per month) | C22: 0.05 | D22: % | E22: HYP | F22: Summer and graduation churn are folded into the average.
A23: renew_a | B23: Annual plan renewal rate at term | C23: 0.55 | D23: % | E23: HYP
A24: iap_share | B24: Student billings through app stores (native apps) | C24: 0.25 | D24: % | E24: PRO | F24: App-store purchase rules for digital subscriptions: platform-policy and counsel review.
A25: iap_fee | B25: App-store commission | C25: 0.15 | D25: % | E25: VENDOR | F25: Assumes a reduced-rate program; verify current store terms.
A26: stripe_pct | B26: Card processing, percent | C26: 0.029 | D26: % | E26: VENDOR | F26: Verify current Stripe pricing and any negotiated rate.
A27: stripe_fix | B27: Card processing, fixed fee per charge | C27: 0.3 | D27: $ | E27: VENDOR | F27: Verify.
A28: Institutional platform
A29: inst_disc | B29: Average realized discount off institutional list | C29: 0.12 | D29: % | E29: POLICY | F29: Within the deal-desk ladder (<=20% needs finance).
A30: rr_i | B30: Gross logo renewal rate at term | C30: 0.88 | D30: % | E30: HYP | F30: No contract has reached term.
A31: expansion | B31: Expansion on retained contract value (modules, bands) | C31: 0.1 | D31: % | E31: HYP | F31: NRR (core) = renewal x (1 + expansion).
A32: pilot_share | B32: Share of full rollout active during a pilot | C32: 0.35 | D32: % | E32: HYP | F32: Pilot is a bounded cohort (D-134: 26 weeks).
A33: bad_debt | B33: Bad debt, share of institutional billings | C33: 0.01 | D33: % | E33: HYP | F33: Accountant to set reserve method.
A34: attach_int | B34: New institutions buying an integration package | C34: 0.4 | D34: % | E34: HYP | F34: SIS/LMS connectors scoped separately (PRICING-AND-PACKAGING.md).
A35: int_fee | B35: Integration package fee | C35: 15000 | D35: $ | E35: HYP
A36: int_hours | B36: Integration package delivery hours | C36: 110 | D36: hours | E36: HYP | F36: Measure on the first integration.
A37: loaded_rate | B37: Loaded implementation cost per hour | C37: 85 | D37: $/hr | E37: HYP | F37: ~$100k salary x 1.22 burden / ~1,430 productive hours.
A38: hrs_per_fte | B38: Billable implementation hours per FTE per month | C38: 110 | D38: hours | E38: HYP
A39: comm_rate | B39: Sales commission on new-logo bookings | C39: 0.08 | D39: % | E39: HYP | F39: Plan not designed; counsel/accountant review of commission accounting.
A40: Add-on streams
A41: ai_start | B41: AI capacity add-on available from month | C41: 20 | D41: month | E41: HYP
A42: ai_attach | B42: Annual institutions buying the AI add-on | C42: 0.4 | D42: % | E42: HYP
A43: alu_start | B43: Alumni module available from month | C43: 30 | D43: month | E43: HYP | F43: Needs live annual customers first; no replacement claim before it is earned.
A44: alu_attach | B44: Campus/System institutions buying alumni module | C44: 0.15 | D44: % | E44: HYP
A45: career_start | B45: Career/employer product sells from month | C45: 25 | D45: month | E45: HYP | F45: Employment-law and anti-discrimination review first (PRO).
A46: career_acv | B46: Employer account ACV | C46: 4000 | D46: $/yr | E46: HYP
A47: career_churn | B47: Employer account monthly churn | C47: 0.02 | D47: % | E47: HYP
A48: mk_start | B48: Marketplace opens from month | C48: 31 | D48: month | E48: HYP | F48: ADVERTISING-AND-MONETIZATION-POLICY.md and provider governance must be mature first.
A49: mk_init | B49: Marketplace providers at opening | C49: 40 | D49: providers | E49: HYP
A50: mk_adds | B50: Marketplace provider adds per month | C50: 15 | D50: providers | E50: HYP
A51: mk_churn | B51: Provider monthly churn | C51: 0.04 | D51: % | E51: HYP
A52: mk_orders_pp | B52: Orders per provider per month | C52: 6 | D52: orders | E52: HYP
A53: mk_aov | B53: Average order value | C53: 45 | D53: $ | E53: HYP
A54: mk_take | B54: Platform take rate on GMV | C54: 0.15 | D54: % | E54: HYP | F54: Net-vs-gross presentation (principal/agent) is an accountant determination.
A55: mk_dispute | B55: Refund/dispute reserve, share of GMV | C55: 0.015 | D55: % | E55: HYP
A56: mk_ts_order | B56: Trust & safety cost per order | C56: 0.4 | D56: $ | E56: HYP
A57: Infrastructure (variable, per monthly-active user, all classes)
A58: infra_compute | B58: Database + compute + functions | C58: 0.03 | D58: $/MAU/mo | E58: VENDOR | F58: Planning allowance. Verify against Supabase / Vercel plans at scale.
A59: gb_per_mau | B59: Stored data per active user | C59: 0.4 | D59: GB | E59: HYP | F59: Documents, media, attachments.
A60: storage_price | B60: Object storage price | C60: 0.021 | D60: $/GB-mo | E60: VENDOR | F60: Verify.
A61: repl_factor | B61: Storage multiplier for backups and DR copy | C61: 2 | D61: x | E61: HYP | F61: RESTORE.md / DR posture.
A62: egress_gb | B62: Data egress per active user | C62: 0.5 | D62: GB/mo | E62: HYP
A63: egress_price | B63: Egress price | C63: 0.09 | D63: $/GB | E63: VENDOR | F63: Verify.
A64: cdn_offload | B64: Share of egress absorbed by CDN cache | C64: 0.5 | D64: % | E64: HYP
A65: search_per_mau | B65: Search + vector index | C65: 0.012 | D65: $/MAU/mo | E65: VENDOR
A66: notif_per_mau | B66: Email / push / SMS notifications | C66: 0.02 | D66: $/MAU/mo | E66: VENDOR
A67: obs_per_mau | B67: Observability and logging | C67: 0.01 | D67: $/MAU/mo | E67: VENDOR
A68: AI inference
A69: in_h | B69: Haiku 4.5 input price | C69: 1 | D69: $/M tok | E69: FACT | F69: Anthropic first-party API price table, cached 2026-09-25.
A70: out_h | B70: Haiku 4.5 output price | C70: 5 | D70: $/M tok | E70: FACT
A71: in_s | B71: Sonnet 5.5 input price | C71: 2 | D71: $/M tok | E71: FACT
A72: out_s | B72: Sonnet 5.5 output price | C72: 10 | D72: $/M tok | E72: FACT
A73: in_o | B73: Opus 5.5 input price | C73: 4 | D73: $/M tok | E73: FACT
A74: out_o | B74: Opus 5.5 output price | C74: 20 | D74: $/M tok | E74: FACT
A75: mix_h | B75: Request share routed to Haiku class | C75: 0.7 | D75: % | E75: HYP | F75: Routing policy: classification and extraction on the small model.
A76: mix_s | B76: Request share routed to Sonnet class | C76: 0.28 | D76: % | E76: HYP
A77: mix_o | B77: Request share routed to Opus class | C77: 0.02 | D77: % | E77: HYP
A78: tok_in | B78: Input tokens per request (incl. retrieved context) | C78: 6000 | D78: tokens | E78: HYP | F78: Measure from usage.ts / private.ai_usage_month.
A79: tok_out | B79: Output tokens per request | C79: 700 | D79: tokens | E79: HYP
A80: think_mult | B80: Output multiplier for reasoning tokens | C80: 1.5 | D80: x | E80: HYP
A81: cache_share | B81: Share of input that is cacheable prefix | C81: 0.5 | D81: % | E81: HYP
A82: cache_hit | B82: Cache hit rate on cacheable prefix | C82: 0.7 | D82: % | E82: HYP
A83: cache_read | B83: Cache read price as share of input price | C83: 0.1 | D83: % | E83: FACT | F83: Sonnet 5.5 $0.20 vs $2.00; blended.
A84: ai_overhead | B84: Embeddings, retrieval, moderation overhead on top of inference | C84: 0.15 | D84: % | E84: HYP
A85: req_free | B85: AI requests per free active user per month (capped) | C85: 10 | D85: req | E85: HYP | F85: Free-tier cap is a product decision.
A86: req_paid | B86: AI requests per paying user per month | C86: 45 | D86: req | E86: HYP
A87: req_inst | B87: AI requests per institution-sponsored active user per month | C87: 20 | D87: req | E87: HYP
A88: Integrations, support
A89: conn_cost | B89: Connector / iPaaS cost per integrated institution | C89: 300 | D89: $/mo | E89: VENDOR
A90: conn_attach | B90: Institutions with a live connector | C90: 0.6 | D90: % | E90: HYP
A91: sso_cost | B91: SSO / SCIM cost per institution connection | C91: 125 | D91: $/mo | E91: VENDOR | F91: Verify the identity vendor price per connection.
A92: tk_c | B92: Support tickets per 100 consumer MAU per month | C92: 2.5 | D92: tickets | E92: HYP | F92: Support contact rate is a defined measure; no reading yet.
A93: tk_i | B93: Support tickets per 100 institutional MAU per month | C93: 3.5 | D93: tickets | E93: HYP
A94: overflow_share | B94: Tickets handled by outsourced tier-1 overflow | C94: 0.25 | D94: % | E94: HYP
A95: overflow_cost | B95: Cost per overflow ticket | C95: 5 | D95: $ | E95: HYP
A96: People and overhead
A97: burden | B97: Payroll burden (taxes, benefits, workers comp) | C97: 0.22 | D97: % | E97: PRO | F97: PEO / benefits broker and payroll provider to confirm.
A98: sw_per_fte | B98: Software and tools per FTE | C98: 400 | D98: $/mo | E98: HYP
A99: rent_per_fte | B99: Workspace per FTE | C99: 350 | D99: $/mo | E99: HYP | F99: Hybrid / coworking.
A100: train_per_fte | B100: Training per FTE | C100: 100 | D100: $/mo | E100: HYP
A101: recruit_per_hire | B101: Recruiting cost per hire (month 2 onward) | C101: 9000 | D101: $ | E101: HYP | F101: Agency or referral mix.
...

Sheet Headcount
A1: Hiring plan (gated roles shift by the scenario hiring delay)
A3: ID | B3: Role | C3: Function | D3: FTE | E3: Start month | F3: Base salary | G3: Gated (1 = waits for evidence gate) | H3: P&L placement | I3: Extra (1 = only in full-scope staffing)
A5: GA-1 | B5: CEO / founder | C5: GA | D5: 1 | E5: 1 | F5: 90000 | G5: 0 | H5: G&A | I5: 0
A6: GA-2 | B6: Fractional CFO / controller (0.4 FTE) | C6: GA | D6: 0.4 | E6: 1 | F6: 150000 | G6: 0 | H6: G&A | I6: 0
A7: GA-3 | B7: Compliance and privacy manager | C7: GA | D7: 1 | E7: 9 | F7: 125000 | G7: 0 | H7: G&A | I7: 0
A8: GA-4 | B8: Finance and RevOps manager | C8: GA | D8: 1 | E8: 15 | F8: 120000 | G8: 0 | H8: G&A | I8: 0
A9: GA-5 | B9: Executive operations / people | C9: GA | D9: 1 | E9: 24 | F9: 85000 | G9: 0 | H9: G&A | I9: 0
A10: EN-1 | B10: CTO / co-founder | C10: ENG | D10: 1 | E10: 1 | F10: 110000 | G10: 0 | H10: Engineering | I10: 0
A11: EN-2 | B11: Senior engineers (platform, web) | C11: ENG | D11: 2 | E11: 1 | F11: 150000 | G11: 0 | H11: Engineering | I11: 0
A12: EN-3 | B12: Data / AI engineer | C12: ENG | D12: 1 | E12: 5 | F12: 160000 | G12: 0 | H12: Engineering | I12: 0
A13: EN-4 | B13: Senior engineer | C13: ENG | D13: 1 | E13: 6 | F13: 150000 | G13: 0 | H13: Engineering | I13: 0
A14: EN-5 | B14: Mobile engineer (iOS / Android, offline sync) | C14: ENG | D14: 1 | E14: 9 | F14: 145000 | G14: 0 | H14: Engineering | I14: 0
A15: EN-6 | B15: Senior engineer | C15: ENG | D15: 1 | E15: 13 | F15: 150000 | G15: 0 | H15: Engineering | I15: 0
A16: EN-7 | B16: SRE / DevOps | C16: ENG | D16: 1 | E16: 14 | F16: 150000 | G16: 0 | H16: Engineering | I16: 0
... A74: X-30 | B74: Data / analytics engineer | C74: ENG | D74: 1 | E74: 35 | F74: 160000 | G74: 0 | H74: Engineering | I74: 1

Sheet Schedules
A1: Pipeline schedules by month (month 1 = Jan 2027). Counts are expected values.
A3: ID | B3: Schedule | C3: 1 | D3: 2 | E3: 3 | F3: 4 | G3: 5 | H3: 6 | I3: 7 | J3: 8 | K3: 9 | L3: 10 | M3: 11 | N3: 12 | O3: 13 | P3: 14 | Q3: 15 | R3: 16 | S3: 17 | T3: 18 | U3: 19 | V3: 20 | W3: 21 | X3: 22 | Y3: 23 | Z3: 24 | AA3: 25 | AB3: 26 | AC3: 27 | AD3: 28 | AE3: 29 | AF3: 30 | AG3: 31 | AH3: 32 | AI3: 33 | AJ3: 34 | AK3: 35 | AL3: 36 | AM3: Total
A5: pilot_D | B5: Paid pilot starts, Department (month 1 = gate_pilot) | C5: 0 | D5: 1 | E5: 0 | F5: 0 | G5: 1 | H5: 0 | I5: 0 | J5: 2 | K5: 0 | L5: 0 | M5: 2 | N5: 0 | O5: 0 | P5: 3 | Q5: 0 | R5: 0 | S5: 3 | T5: 0 | U5: 0 | V5: 3 | W5: 0 | X5: 0 | Y5: 4 | Z5: 0 | AA5: 0 | AB5: 4 | AC5: 0 | AD5: 0 | AE5: 4 | AF5: 0 | AG5: 0 | AH5: 5 | AI5: 0 | AJ5: 0 | AK5: 5 | AL5: 0 | AM5: =SUM(C5:AL5) -> 37
A6: pilot_C | B6: Paid pilot starts, Campus (month 1 = gate_pilot) | C6: 0 | D6: 0 | E6: 0 | F6: 0 | G6: 1 | H6: 0 | I6: 0 | J6: 1 | K6: 0 | L6: 0 | M6: 1 | N6: 0 | O6: 0 | P6: 1 | Q6: 0 | R6: 0 | S6: 2 | T6: 0 | U6: 0 | V6: 2 | W6: 0 | X6: 0 | Y6: 2 | Z6: 0 | AA6: 0 | AB6: 2 | AC6: 0 | AD6: 0 | AE6: 3 | AF6: 0 | AG6: 0 | AH6: 3 | AI6: 0 | AJ6: 0 | AK6: 3 | AL6: 0 | AM6: =SUM(C6:AL6) -> 21
A7: pilot_Y | B7: Paid pilot starts, System (month 1 = gate_ent) | C7: 0 | D7: 0 | E7: 0 | F7: 0 | G7: 1 | H7: 0 | I7: 0 | J7: 0 | K7: 0 | L7: 0 | M7: 1 | N7: 0 | O7: 0 | P7: 1 | Q7: 0 | R7: 0 | S7: 1 | T7: 0 | U7: 0 | V7: 1 | W7: 0 | X7: 0 | Y7: 1 | Z7: 0 | AA7: 0 | AB7: 1 | AC7: 0 | AD7: 0 | AE7: 1 | AF7: 0 | AG7: 0 | AH7: 1 | AI7: 0 | AJ7: 0 | AK7: 1 | AL7: 0 | AM7: =SUM(C7:AL7) -> 10
A8: direct_D | B8: Direct annual starts, Department (month 1 = gate_direct) | C8: 0 | D8: 1 | E8: 0 | F8: 0 | G8: 1 | H8: 0 | I8: 0 | J8: 2 | K8: 0 | L8: 0 | M8: 2 | N8: 0 | O8: 0 | P8: 3 | Q8: 0 | R8: 0 | S8: 3 | T8: 0 | U8: 0 | V8: 3 | W8: 0 | X8: 0 | Y8: 3 | Z8: 0 | AA8: 0 | AB8: 3 | AC8: 0 | AD8: 0 | AE8: 3 | AF8: 0 | AG8: 0 | AH8: 3 | AI8: 0 | AJ8: 0 | AK8: 3 | AL8: 0 | AM8: =SUM(C8:AL8) -> 30
A9: direct_C | B9: Direct annual starts, Campus (month 1 = gate_direct) | C9: 0 | D9: 0 | E9: 0 | F9: 0 | G9: 1 | H9: 0 | I9: 0 | J9: 1 | K9: 0 | L9: 0 | M9: 1 | N9: 0 | O9: 0 | P9: 2 | Q9: 0 | R9: 0 | S9: 2 | T9: 0 | U9: 0 | V9: 2 | W9: 0 | X9: 0 | Y9: 2 | Z9: 0 | AA9: 0 | AB9: 2 | AC9: 0 | AD9: 0 | AE9: 2 | AF9: 0 | AG9: 0 | AH9: 2 | AI9: 0 | AJ9: 0 | AK9: 2 | AL9: 0 | AM9: =SUM(C9:AL9) -> 19
A10: direct_Y | B10: Direct annual starts, System (month 1 = gate_ent) | C10: 0 | D10: 0 | E10: 0 | F10: 0 | G10: 0 | H10: 0 | I10: 0 | J10: 0 | K10: 0 | L10: 0 | M10: 1 | N10: 0 | O10: 0 | P10: 1 | Q10: 0 | R10: 0 | S10: 1 | T10: 0 | U10: 0 | V10: 1 | W10: 0 | X10: 0 | Y10: 1 | Z10: 0 | AA10: 0 | AB10: 1 | AC10: 0 | AD10: 0 | AE10: 1 | AF10: 0 | AG10: 0 | AH10: 1 | AI10: 0 | AJ10: 0 | AK10: 1 | AL10: 0 | AM10: =SUM(C10:AL10) -> 9
A11: dp_D | B11: Unpaid design-partner pilot starts, Department (absolute month) | C11: 0 | D11: 0 | E11: 0 | F11: 0 | G11: 1 | H11: 0 | I11: 0 | J11: 0 | K11: 0 | L11: 0 | M11: 0 | N11: 0 | O11: 0 | P11: 0 | Q11: 0 | R11: 0 | S11: 0 | T11: 0 | U11: 0 | V11: 0 | W11: 0 | X11: 0 | Y11: 0 | Z11: 0 | AA11: 0 | AB11: 0 | AC11: 0 | AD11: 0 | AE11: 0 | AF11: 0 | AG11: 0 | AH11: 0 | AI11: 0 | AJ11: 0 | AK11: 0 | AL11: 0 | AM11: =SUM(C11:AL11) -> 1
A12: dp_C | B12: Unpaid design-partner pilot starts, Campus (absolute month) | C12: 0 | D12: 0 | E12: 0 | F12: 0 | G12: 0 | H12: 0 | I12: 0 | J12: 1 | K12: 0 | L12: 0 | M12: 0 | N12: 0 | O12: 0 | P12: 0 | Q12: 0 | R12: 0 | S12: 0 | T12: 0 | U12: 0 | V12: 0 | W12: 0 | X12: 0 | Y12: 0 | Z12: 0 | AA12: 0 | AB12: 0 | AC12: 0 | AD12: 0 | AE12: 0 | AF12: 0 | AG12: 0 | AH12: 0 | AI12: 0 | AJ12: 0 | AK12: 0 | AL12: 0 | AM12: =SUM(C12:AL12) -> 1
A13: dp_Y | B13: Unpaid design-partner pilot starts, System (absolute month) | C13: 0 | D13: 0 | E13: 0 | F13: 0 | G13: 0 | H13: 0 | I13: 0 | J13: 0 | K13: 0 | L13: 0 | M13: 0 | N13: 0 | O13: 0 | P13: 0 | Q13: 0 | R13: 0 | S13: 0 | T13: 0 | U13: 0 | V13: 0 | W13: 0 | X13: 0 | Y13: 0 | Z13: 0 | AA13: 0 | AB13: 0 | AC13: 0 | AD13: 0 | AE13: 0 | AF13: 0 | AG13: 0 | AH13: 0 | AI13: 0 | AJ13: 0 | AK13: 0 | AL13: 0 | AM13: =SUM(C13:AL13) -> 0
A14: career_adds | B14: Employer accounts added (absolute month) | C14: 0 | D14: 0 | E14: 0 | F14: 0 | G14: 0 | H14: 0 | I14: 0 | J14: 0 | K14: 0 | L14: 0 | M14: 0 | N14: 0 | O14: 0 | P14: 0 | Q14: 0 | R14: 0 | S14: 0 | T14: 0 | U14: 0 | V14: 0 | W14: 0 | X14: 0 | Y14: 0 | Z14: 0 | AA14: 3 | AB14: 3 | AC14: 3 | AD14: 3 | AE14: 3 | AF14: 3 | AG14: 6 | AH14: 6 | AI14: 6 | AJ14: 6 | AK14: 6 | AL14: 6 | AM14: =SUM(C14:AL14) -> 54

Sheet Cons
A1: Scenario 1: Conservative
A2: All cells are formulas on Assumptions, Headcount, Schedules and the scenario parameters below.
A3: Scenario parameters (linked to Scenarios sheet)
A4: Organic student acquisition multiplier | B4: x | C4: =Scenarios!C4 -> 0.6
A5: Free-to-paid conversion multiplier | B5: x | C5: =Scenarios!C5 -> 0.8
A6: Churn multiplier (students and institutions) | B6: x | C6: =Scenarios!C6 -> 1.25
A7: Pilot and direct-deal volume multiplier | B7: x | C7: =Scenarios!C7 -> 0.6
A8: Pilot-to-annual conversion multiplier | B8: x | C8: =Scenarios!C8 -> 0.8
A9: Institutional gates slip by (months) | B9: months | C9: =Scenarios!C9 -> 2
A10: Institutional price realization multiplier | B10: x | C10: =Scenarios!C10 -> 0.95
A11: Paid acquisition cost multiplier | B11: x | C11: =Scenarios!C11 -> 1.25
A12: AI unit cost multiplier (price or model-mix shift) | B12: x | C12: =Scenarios!C12 -> 1
A13: AI usage multiplier (requests per user) | B13: x | C13: =Scenarios!C13 -> 1
A14: Incident switch (1 = on) | B14: 0/1 | C14: =Scenarios!C14 -> 0
A15: Delay for gated hires (months) | B15: months | C15: =Scenarios!C15 -> 0
A16: Full-scope staffing switch (1 = include the CTO-pack staffing roles) | B16: 0/1 | C16: =Scenarios!C16 -> 0
A18: Month | C18: 1 | D18: 2 | E18: 3 | F18: 4 | G18: 5 | H18: 6 | I18: 7 | J18: 8 | K18: 9 | L18: 10 | M18: 11 | N18: 12 | O18: 13 | P18: 14 | Q18: 15 | R18: 16 | S18: 17 | T18: 18 | U18: 19 | V18: 20 | W18: 21 | X18: 22 | Y18: 23 | Z18: 24 | AA18: 25 | AB18: 26 | AC18: 27 | AD18: 28 | AE18: 29 | AF18: 30 | AG18: 31 | AH18: 32 | AI18: 33 | AJ18: 34 | AK18: 35 | AL18: 36 | AN18: Year 1 | AO18: Year 2 | AP18: Year 3
A19: Calendar | C19: Jan-27 | D19: Feb-27 | E19: Mar-27 | F19: Apr-27 | G19: May-27 | H19: Jun-27 | I19: Jul-27 | J19: Aug-27 | K19: Sep-27 | L19: Oct-27 | M19: Nov-27 | N19: Dec-27 | O19: Jan-28 | P19: Feb-28 | Q19: Mar-28 | R19: Apr-28 | S19: May-28 | T19: Jun-28 | U19: Jul-28 | V19: Aug-28 | W19: Sep-28 | X19: Oct-28 | Y19: Nov-28 | Z19: Dec-28 | AA19: Jan-29 | AB19: Feb-29 | AC19: Mar-29 | AD19: Apr-29 | AE19: May-29 | AF19: Jun-29 | AG19: Jul-29 | AH19: Aug-29 | AI19: Sep-29 | AJ19: Oct-29 | AK19: Nov-29 | AL19: Dec-29 | AN19: 2027 | AO19: 2028 | AP19: 2029
A20: Year | C20: =INT((C18-1)/12)+1 -> 1 | D20: =INT((D18-1)/12)+1 -> 1 | E20: =INT((E18-1)/12)+1 -> 1 | F20: =INT((F18-1)/12)+1 -> 1 | G20: =INT((G18-1)/12)+1 -> 1 | H20: =INT((H18-1)/12)+1 -> 1 | I20: =INT((I18-1)/12)+1 -> 1 | J20: =INT((J18-1)/12)+1 -> 1 | ... AL20: =INT((AL18-1)/12)+1 -> 3
A21: Month of year | C21: =MOD(C18-1,12)+1 -> 1 | D21: =MOD(D18-1,12)+1 -> 2 | E21: =MOD(E18-1,12)+1 -> 3 | F21: =MOD(F18-1,12)+1 -> 4 | G21: =MOD(G18-1,12)+1 -> 5 | H21: =MOD(H18-1,12)+1 -> 6 | I21: =MOD(I18-1,12)+1 -> 7 | J21: =MOD(J18-1,12)+1 -> 8 | ... AL21: =MOD(AL18-1,12)+1 -> 12
A23: Student subscription: funnel and subscribers
A24: Organic signup trend (pre-seasonality) | B24: users | C24: =IF((C$18=1),Assumptions!$C$16,(0*(1+Assumptions!$C$133))) -> 1200 | D24: =IF((D$18=1),Assumptions!$C$16,(C24*(1+Assumptions!$C$133))) -> 1272 | E24: =IF((E$18=1),Assumptions!$C$16,(D24*(1+Assumptions!$C$133))) -> 1348.32 | F24: =IF((F$18=1),Assumptions!$C$16,(E24*(1+Assumptions!$C$133))) -> 1429.2192 | G24: =IF((G$18=1),Assumptions!$C$16,(F24*(1+Assumptions!$C$133))) -> 1514.9724 | H24: =IF((H$18=1),Assumptions!$C$16,(G24*(1+Assumptions!$C$133))) -> 1605.8707 | I24: =IF((I$18=1),Assumptions!$C$16,(H24*(1+Assumptions!$C$133))) -> 1702.2229 | J24: =IF((J$18=1),Assumptions!$C$16,(I24*(1+Assumptions!$C$133))) -> 1804.3563 | K24: =IF((K$18=1),Assumptions!$C$16,(J24*(1+Assumptions!$C$133))) -> 1912.6177 | ... N24: =IF((N$18=1),Assumptions!$C$16,(M24*(1+Assumptions!$C$133))) -> 2277.9583 | O24: =IF((O$18=1),Assumptions!$C$16,(N24*(1+Assumptions!$D$133))) -> 2369.0766 | P24: =IF((P$18=1),Assumptions!$C$16,(O24*(1+Assumptions!$D$133))) -> 2463.8397 | Q24: =IF((Q$18=1),Assumptions!$C$16,(P24*(1+Assumptions!$D$133))) -> 2562.3933 | R24: =IF((R$18=1),Assumptions!$C$16,(Q24*(1+Assumptions!$D$133))) -> 2664.889 | S24: =IF((S$18=1),Assumptions!$C$16,(R24*(1+Assumptions!$D$133))) -> 2771.4845 | T24: =IF((T$18=1),Assumptions!$C$16,(S24*(1+Assumptions!$D$133))) -> 2882.3439 | U24: =IF((U$18=1),Assumptions!$C$16,(T24*(1+Assumptions!$D$133))) -> 2997.6377 | V24: =IF((V$18=1),Assumptions!$C$16,(U24*(1+Assumptions!$D$133))) -> 3117.5432 | ... Z24: =IF((Z$18=1),Assumptions!$C$16,(Y24*(1+Assumptions!$D$133))) -> 3647.0846 | AA24: =IF((AA$18=1),Assumptions!$C$16,(Z24*(1+Assumptions!$E$133))) -> 3738.2617 | AB24: =IF((AB$18=1),Assumptions!$C$16,(AA24*(1+Assumptions!$E$133))) -> 3831.7182 | AC24: =IF((AC$18=1),Assumptions!$C$16,(AB24*(1+Assumptions!$E$133))) -> 3927.5112 | AD24: =IF((AD$18=1),Assumptions!$C$16,(AC24*(1+Assumptions!$E$133))) -> 4025.699 | AE24: =IF((AE$18=1),Assumptions!$C$16,(AD24*(1+Assumptions!$E$133))) -> 4126.3415 | AF24: =IF((AF$18=1),Assumptions!$C$16,(AE24*(1+Assumptions!$E$133))) -> 4229.5 | AG24: =IF((AG$18=1),Assumptions!$C$16,(AF24*(1+Assumptions!$E$133))) -> 4335.2375 | AH24: =IF((AH$18=1),Assumptions!$C$16,(AG24*(1+Assumptions!$E$133))) -> 4443.6184 | ... AL24: =IF((AL$18=1),Assumptions!$C$16,(AK24*(1+Assumptions!$E$133))) -> 4904.9233
A25: Organic + campus-led free signups | B25: users | C25: =(((C24*INDEX(Assumptions!$C$167:$C$178,C$21))*$C$4)*IF((C$18<Assumptions!$C$5),Assumptions!$C$6,1)) -> 234 | D25: =(((D24*INDEX(Assumptions!$C$167:$C$178,D$21))*$C$4)*IF((D$18<Assumptions!$C$5),Assumptions!$C$6,1)) -> 209.88 | E25: =(((E24*INDEX(Assumptions!$C$167:$C$178,E$21))*$C$4)*IF((E$18<Assumptions!$C$5),Assumptions!$C$6,1)) -> 182.0232 | F25: =(((F24*INDEX(Assumptions!$C$167:$C$178,F$21))*$C$4)*IF((F$18<Assumptions!$C$5),Assumptions!$C$6,1)) -> 171.5063 | G25: =(((G24*INDEX(Assumptions!$C$167:$C$178,G$21))*$C$4)*IF((G$18<Assumptions!$C$5),Assumptions!$C$6,1)) -> 136.34751 | H25: =(((H24*INDEX(Assumptions!$C$167:$C$178,H$21))*$C$4)*IF((H$18<Assumptions!$C$5),Assumptions!$C$6,1)) -> 120.4403 | I25: =(((I24*INDEX(Assumptions!$C$167:$C$178,I$21))*$C$4)*IF((I$18<Assumptions!$C$5),Assumptions!$C$6,1)) -> 178.73341 | J25: =(((J24*INDEX(Assumptions!$C$167:$C$178,J$21))*$C$4)*IF((J$18<Assumptions!$C$5),Assumptions!$C$6,1)) -> 433.04551 | ... AL25: =(((AL24*INDEX(Assumptions!$C$167:$C$178,AL$21))*$C$4)*IF((AL$18<Assumptions!$C$5),Assumptions!$C$6,1)) -> 2060.0678 | AN25: =SUM(C25:N25) -> 3046.2028 | AO25: =SUM(O25:Z25) -> 21403.695 | AP25: =SUM(AA25:AL25) -> 30983.447
A26: Paid-acquisition free signups | B26: users | C26: =IF((C$18>=Assumptions!$C$5),(Assumptions!$C$134/(Assumptions!$C$17*$C$11)),0) -> 0 | D26: =IF((D$18>=Assumptions!$C$5),(Assumptions!$C$134/(Assumptions!$C$17*$C$11)),0) -> 0 | E26: =IF((E$18>=Assumptions!$C$5),(Assumptions!$C$134/(Assumptions!$C$17*$C$11)),0) -> 0 | F26: =IF((F$18>=Assumptions!$C$5),(Assumptions!$C$134/(Assumptions!$C$17*$C$11)),0) -> 0 | G26: =IF((G$18>=Assumptions!$C$5),(Assumptions!$C$134/(Assumptions!$C$17*$C$11)),0) -> 0 | H26: =IF((H$18>=Assumptions!$C$5),(Assumptions!$C$134/(Assumptions!$C$17*$C$11)),0) -> 0 | I26: =IF((I$18>=Assumptions!$C$5),(Assumptions!$C$134/(Assumptions!$C$17*$C$11)),0) -> 0 | J26: =IF((J$18>=Assumptions!$C$5),(Assumptions!$C$134/(Assumptions!$C$17*$C$11)),0) -> 0 | ... N26: =IF((N$18>=Assumptions!$C$5),(Assumptions!$C$134/(Assumptions!$C$17*$C$11)),0) -> 0 | O26: =IF((O$18>=Assumptions!$C$5),(Assumptions!$D$134/(Assumptions!$C$17*$C$11)),0) -> 800 | P26: =IF((P$18>=Assumptions!$C$5),(Assumptions!$D$134/(Assumptions!$C$17*$C$11)),0) -> 800 | Q26: =IF((Q$18>=Assumptions!$C$5),(Assumptions!$D$134/(Assumptions!$C$17*$C$11)),0) -> 800 | R26: =IF((R$18>=Assumptions!$C$5),(Assumptions!$D$134/(Assumptions!$C$17*$C$11)),0) -> 800 | S26: =IF((S$18>=Assumptions!$C$5),(Assumptions!$D$134/(Assumptions!$C$17*$C$11)),0) -> 800 | T26: =IF((T$18>=Assumptions!$C$5),(Assumptions!$D$134/(Assumptions!$C$17*$C$11)),0) -> 800 | U26: =IF((U$18>=Assumptions!$C$5),(Assumptions!$D$134/(Assumptions!$C$17*$C$11)),0) -> 800 | V26: =IF((V$18>=Assumptions!$C$5),(Assumptions!$D$134/(Assumptions!$C$17*$C$11)),0) -> 800 | ... Z26: =IF((Z$18>=Assumptions!$C$5),(Assumptions!$D$134/(Assumptions!$C$17*$C$11)),0) -> 800 | AA26: =IF((AA$18>=Assumptions!$C$5),(Assumptions!$E$134/(Assumptions!$C$17*$C$11)),0) -> 1333.3333 | AB26: =IF((AB$18>=Assumptions!$C$5),(Assumptions!$E$134/(Assumptions!$C$17*$C$11)),0) -> 1333.3333 | AC26: =IF((AC$18>=Assumptions!$C$5),(Assumptions!$E$134/(Assumptions!$C$17*$C$11)),0) -> 1333.3333 | AD26: =IF((AD$18>=Assumptions!$C$5),(Assumptions!$E$134/(Assumptions!$C$17*$C$11)),0) -> 1333.3333 | AE26: =IF((AE$18>=Assumptions!$C$5),(Assumptions!$E$134/(Assumptions!$C$17*$C$11)),0) -> 1333.3333 | AF26: =IF((AF$18>=Assumptions!$C$5),(Assumptions!$E$134/(Assumptions!$C$17*$C$11)),0) -> 1333.3333 | AG26: =IF((AG$18>=Assumptions!$C$5),(Assumptions!$E$134/(Assumptions!$C$17*$C$11)),0) -> 1333.3333 | AH26: =IF((AH$18>=Assumptions!$C$5),(Assumptions!$E$134/(Assumptions!$C$17*$C$11)),0) -> 1333.3333 | ... AL26: =IF((AL$18>=Assumptions!$C$5),(Assumptions!$E$134/(Assumptions!$C$17*$C$11)),0) -> 1333.3333 | AN26: =SUM(C26:N26) -> 0 | AO26: =SUM(O26:Z26) -> 9600 | AP26: =SUM(AA26:AL26) -> 16000
A27: New monthly-active free users | B27: users | C27: =((C25+C26)*Assumptions!$C$18) -> 140.4 | D27: =((D25+D26)*Assumptions!$C$18) -> 125.928 | E27: =((E25+E26)*Assumptions!$C$18) -> 109.21392 | F27: =((F25+F26)*Assumptions!$C$18) -> 102.90378 | G27: =((G25+G26)*Assumptions!$C$18) -> 81.808507 | H27: =((H25+H26)*Assumptions!$C$18) -> 72.264181 | I27: =((I25+I26)*Assumptions!$C$18) -> 107.24004 | J27: =((J25+J26)*Assumptions!$C$18) -> 259.82731 | ... AL27: =((AL25+AL26)*Assumptions!$C$18) -> 2036.0407 | AN27: =SUM(C27:N27) -> 1827.7217 | AO27: =SUM(O27:Z27) -> 18602.217 | AP27: =SUM(AA27:AL27) -> 28190.068
A28: New paying subscribers (conversions) | B28: users | C28: =IF((C$18>=Assumptions!$C$5),((Assumptions!$C$20*$C$5)*0),0) -> 0 | D28: =IF((D$18>=Assumptions!$C$5),((Assumptions!$C$20*$C$5)*C29),0) -> 0 | E28: =IF((E$18>=Assumptions!$C$5),((Assumptions!$C$20*$C$5)*D29),0) -> 0 | F28: =IF((F$18>=Assumptions!$C$5),((Assumptions!$C$20*$C$5)*E29),0) -> 0 | G28: =IF((G$18>=Assumptions!$C$5),((Assumptions!$C$20*$C$5)*F29),0) -> 0 | H28: =IF((H$18>=Assumptions!$C$5),((Assumptions!$C$20*$C$5)*G29),0) -> 0 | I28: =IF((I$18>=Assumptions!$C$5),((Assumptions!$C$20*$C$5)*H29),0) -> 0 | J28: =IF((J$18>=Assumptions!$C$5),((Assumptions!$C$20*$C$5)*I29),0) -> 0 | K28: =IF((K$18>=Assumptions!$C$5),((Assumptions!$C$20*$C$5)*J29),0) -> 0 | ... AL28: =IF((AL$18>=Assumptions!$C$5),((Assumptions!$C$20*$C$5)*AK29),0) -> 36.09349 | AN28: =SUM(C28:N28) -> 0 | AO28: =SUM(O28:Z28) -> 147.26145 | AP28: =SUM(AA28:AL28) -> 344.45874
A29: Active free users (end of month) | B29: users | C29: =MAX(0,(((0*(1-Assumptions!$C$19))+C27)-C28)) -> 140.4 | D29: =MAX(0,(((C29*(1-Assumptions!$C$19))+D27)-D28)) -> 249.48 | E29: =MAX(0,(((D29*(1-Assumptions!$C$19))+E27)-E28)) -> 328.75632 | F29: =MAX(0,(((E29*(1-Assumptions!$C$19))+F27)-F28)) -> 392.20934 | G29: =MAX(0,(((F29*(1-Assumptions!$C$19))+G27)-G28)) -> 426.95273 | H29: =MAX(0,(((G29*(1-Assumptions!$C$19))+H27)-H28)) -> 447.98258 | I29: =MAX(0,(((H29*(1-Assumptions!$C$19))+I27)-I28)) -> 501.46472 | J29: =MAX(0,(((I29*(1-Assumptions!$C$19))+J27)-J28)) -> 701.11626 | K29: =MAX(0,(((J29*(1-Assumptions!$C$19))+K27)-K28)) -> 926.82638 | ... AL29: =MAX(0,(((AK29*(1-Assumptions!$C$19))+AL27)-AL28)) -> 17881.083 | AN29: =N29 -> 1083.7294 | AO29: =Z29 -> 10702.998 | AP29: =AL29 -> 17881.083
A30: Incident: extra monthly paid churn | B30: % | C30: =IF(AND(($C$14=1),(C$18>=(Assumptions!$C$106+1)),(C$18<=(Assumptions!$C$106+3))),Assumptions!$C$115,0) -> 0 | D30: =IF(AND(($C$14=1),(D$18>=(Assumptions!$C$106+1)),(D$18<=(Assumptions!$C$106+3))),Assumptions!$C$115,0) -> 0 | E30: =IF(AND(($C$14=1),(E$18>=(Assumptions!$C$106+1)),(E$18<=(Assumptions!$C$106+3))),Assumptions!$C$115,0) -> 0 | F30: =IF(AND(($C$14=1),(F$18>=(Assumptions!$C$106+1)),(F$18<=(Assumptions!$C$106+3))),Assumptions!$C$115,0) -> 0 | G30: =IF(AND(($C$14=1),(G$18>=(Assumptions!$C$106+1)),(G$18<=(Assumptions!$C$106+3))),Assumptions!$C$115,0) -> 0 | H30: =IF(AND(($C$14=1),(H$18>=(Assumptions!$C$106+1)),(H$18<=(Assumptions!$C$106+3))),Assumptions!$C$115,0) -> 0 | I30: =IF(AND(($C$14=1),(I$18>=(Assumptions!$C$106+1)),(I$18<=(Assumptions!$C$106+3))),Assumptions!$C$115,0) -> 0 | J30: =IF(AND(($C$14=1),(J$18>=(Assumptions!$C$106+1)),(J$18<=(Assumptions!$C$106+3))),Assumptions!$C$115,0) -> 0 | ... AL30: =IF(AND(($C$14=1),(AL$18>=(Assumptions!$C$106+1)),(AL$18<=(Assumptions!$C$106+3))),Assumptions!$C$115,0) -> 0
A31: Effective monthly plan churn | B31: % | C31: =MIN(1,((Assumptions!$C$22*$C$6)+C30)) -> 0.0625 | D31: =MIN(1,((Assumptions!$C$22*$C$6)+D30)) -> 0.0625 | E31: =MIN(1,((Assumptions!$C$22*$C$6)+E30)) -> 0.0625 | F31: =MIN(1,((Assumptions!$C$22*$C$6)+F30)) -> 0.0625 | G31: =MIN(1,((Assumptions!$C$22*$C$6)+G30)) -> 0.0625 | H31: =MIN(1,((Assumptions!$C$22*$C$6)+H30)) -> 0.0625 | I31: =MIN(1,((Assumptions!$C$22*$C$6)+I30)) -> 0.0625 | J31: =MIN(1,((Assumptions!$C$22*$C$6)+J30)) -> 0.0625 | ... AL31: =MIN(1,((Assumptions!$C$22*$C$6)+AL30)) -> 0.0625
A32: New monthly-plan subscribers | B32: users | C32: =(C28*(1-Assumptions!$C$21)) -> 0 | D32: =(D28*(1-Assumptions!$C$21)) -> 0 | E32: =(E28*(1-Assumptions!$C$21)) -> 0 | F32: =(F28*(1-Assumptions!$C$21)) -> 0 | G32: =(G28*(1-Assumptions!$C$21)) -> 0 | H32: =(H28*(1-Assumptions!$C$21)) -> 0 | I32: =(I28*(1-Assumptions!$C$21)) -> 0 | J32: =(J28*(1-Assumptions!$C$21)) -> 0 | ... AL32: =(AL28*(1-Assumptions!$C$21)) -> 19.85142 | AN32: =SUM(C32:N32) -> 0 | AO32: =SUM(O32:Z32) -> 80.9938 | AP32: =SUM(AA32:AL32) -> 189.45231
A33: New annual-plan subscribers | B33: users | C33: =(C28*Assumptions!$C$21) -> 0 | D33: =(D28*Assumptions!$C$21) -> 0 | E33: =(E28*Assumptions!$C$21) -> 0 | F33: =(F28*Assumptions!$C$21) -> 0 | G33: =(G28*Assumptions!$C$21) -> 0 | H33: =(H28*Assumptions!$C$21) -> 0 | I33: =(I28*Assumptions!$C$21) -> 0 | J33: =(J28*Assumptions!$C$21) -> 0 | ... AL33: =(AL28*Assumptions!$C$21) -> 16.242071 | AN33: =SUM(C33:N33) -> 0 | AO33: =SUM(O33:Z33) -> 66.267654 | AP33: =SUM(AA33:AL33) -> 155.00643
A34: Monthly-plan subscribers (end) | B34: users | C34: =((0*(1-C31))+C32) -> 0 | D34: =((C34*(1-D31))+D32) -> 0 | E34: =((D34*(1-E31))+E32) -> 0 | F34: =((E34*(1-F31))+F32) -> 0 | G34: =((F34*(1-G31))+G32) -> 0 | H34: =((G34*(1-H31))+H32) -> 0 | I34: =((H34*(1-I31))+I32) -> 0 | J34: =((I34*(1-J31))+J32) -> 0 | K34: =((J34*(1-K31))+K32) -> 0 | ... AL34: =((AK34*(1-AL31))+AL32) -> 170.29524 | AN34: =N34 -> 0 | AO34: =Z34 -> 64.191711 | AP34: =AL34 -> 170.29524
A35: Effective annual renewal rate | B35: % | C35: =MAX(0,(1-((1-Assumptions!$C$23)*$C$6))) -> 0.4375 | D35: =MAX(0,(1-((1-Assumptions!$C$23)*$C$6))) -> 0.4375 | E35: =MAX(0,(1-((1-Assumptions!$C$23)*$C$6))) -> 0.4375 | F35: =MAX(0,(1-((1-Assumptions!$C$23)*$C$6))) -> 0.4375 | G35: =MAX(0,(1-((1-Assumptions!$C$23)*$C$6))) -> 0.4375 | H35: =MAX(0,(1-((1-Assumptions!$C$23)*$C$6))) -> 0.4375 | I35: =MAX(0,(1-((1-Assumptions!$C$23)*$C$6))) -> 0.4375 | J35: =MAX(0,(1-((1-Assumptions!$C$23)*$C$6))) -> 0.4375 | ... AL35: =MAX(0,(1-((1-Assumptions!$C$23)*$C$6))) -> 0.4375
A36: Annual renewals this month | B36: users | C36: =(C35*0) -> 0 | D36: =(D35*0) -> 0 | E36: =(E35*0) -> 0 | F36: =(F35*0) -> 0 | G36: =(G35*0) -> 0 | H36: =(H35*0) -> 0 | I36: =(I35*0) -> 0 | J36: =(J35*0) -> 0 | ... N36: =(N35*0) -> 0 | O36: =(O35*C37) -> 0 | P36: =(P35*D37) -> 0 | Q36: =(Q35*E37) -> 0 | R36: =(R35*F37) -> 0 | S36: =(S35*G37) -> 0 | T36: =(T35*H37) -> 0 | U36: =(U35*I37) -> 0 | V36: =(V35*J37) -> 0 | ... AL36: =(AL35*Z37) -> 4.1724641 | AN36: =SUM(C36:N36) -> 0 | AO36: =SUM(O36:Z36) -> 0 | AP36: =SUM(AA36:AL36) -> 28.992099
A37: Annual plan starts (new + renewals) | B37: users | C37: =(C33+C36) -> 0 | D37: =(D33+D36) -> 0 | E37: =(E33+E36) -> 0 | F37: =(F33+F36) -> 0 | G37: =(G33+G36) -> 0 | H37: =(H33+H36) -> 0 | I37: =(I33+I36) -> 0 | J37: =(J33+J36) -> 0 | ... AL37: =(AL33+AL36) -> 20.414535 | AN37: =SUM(C37:N37) -> 0 | AO37: =SUM(O37:Z37) -> 66.267654 | AP37: =SUM(AA37:AL37) -> 183.99853
A38: Annual-plan subscribers (end) | B38: users | C38: =C37 -> 0 | D38: =SUM(C37:D37) -> 0 | E38: =SUM(C37:E37) -> 0 | F38: =SUM(C37:F37) -> 0 | G38: =SUM(C37:G37) -> 0 | H38: =SUM(C37:H37) -> 0 | I38: =SUM(C37:I37) -> 0 | J38: =SUM(C37:J37) -> 0 | K38: =SUM(C37:K37) -> 0 | L38: =SUM(C37:L37) -> 0 | M38: =SUM(C37:M37) -> 0 | N38: =SUM(C37:N37) -> 0 | O38: =SUM(D37:O37) -> 0.9753565 | P38: =SUM(E37:P37) -> 3.2615746 | Q38: =SUM(F37:Q37) -> 6.5789865 | R38: =SUM(G37:R37) -> 10.670868 | S38: =SUM(H37:S37) -> 15.386279 | T38: =SUM(I37:T37) -> 20.497187 | U38: =SUM(J37:U37) -> 25.883504 | ... AL38: =SUM(AA37:AL37) -> 183.99853 | AN38: =N38 -> 0 | AO38: =Z38 -> 66.267654 | AP38: =AL38 -> 183.99853
A39: Paying subscribers (end) | B39: users | C39: =(C34+C38) -> 0 | D39: =(D34+D38) -> 0 | E39: =(E34+E38) -> 0 | F39: =(F34+F38) -> 0 | G39: =(G34+G38) -> 0 | H39: =(H34+H38) -> 0 | I39: =(I34+I38) -> 0 | J39: =(J34+J38) -> 0 | ... AL39: =(AL34+AL38) -> 354.29378 | AN39: =N39 -> 0 | AO39: =Z39 -> 130.45937 | AP39: =AL39 -> 354.29378
A40: Subscribers lost (churn + non-renewal) | B40: users | C40: =((0+C28)-C39) -> 0 | D40: =((C39+D28)-D39) -> 0 | E40: =((D39+E28)-E39) -> 0 | F40: =((E39+F28)-F39) -> 0 | G40: =((F39+G28)-G39) -> 0 | H40: =((G39+H28)-H39) -> 0 | I40: =((H39+I28)-I39) -> 0 | J40: =((I39+J28)-J39) -> 0 | K40: =((J39+K28)-K39) -> 0 | ... AL40: =((AK39+AL28)-AL39) -> 15.394185 | AN40: =SUM(C40:N40) -> 0 | AO40: =SUM(O40:Z40) -> 16.802088 | AP40: =SUM(AA40:AL40) -> 120.62433
A41: Student billings (net of refunds) | B41: $ | C41: =((((Assumptions!$C$12*(1-Assumptions!$C$14))*C34)+((Assumptions!$C$13*(1-Assumptions!$C$14))*C37))*(1-Assumptions!$C$15)) -> 0 | D41: =((((Assumptions!$C$12*(1-Assumptions!$C$14))*D34)+((Assumptions!$C$13*(1-Assumptions!$C$14))*D37))*(1-Assumptions!$C$15)) -> 0 | E41: =((((Assumptions!$C$12*(1-Assumptions!$C$14))*E34)+((Assumptions!$C$13*(1-Assumptions!$C$14))*E37))*(1-Assumptions!$C$15)) -> 0 | F41: =((((Assumptions!$C$12*(1-Assumptions!$C$14))*F34)+((Assumptions!$C$13*(1-Assumptions!$C$14))*F37))*(1-Assumptions!$C$15)) -> 0 | G41: =((((Assumptions!$C$12*(1-Assumptions!$C$14))*G34)+((Assumptions!$C$13*(1-Assumptions!$C$14))*G37))*(1-Assumptions!$C$15)) -> 0 | H41: =((((Assumptions!$C$12*(1-Assumptions!$C$14))*H34)+((Assumptions!$C$13*(1-Assumptions!$C$14))*H37))*(1-Assumptions!$C$15)) -> 0 | I41: =((((Assumptions!$C$12*(1-Assumptions!$C$14))*I34)+((Assumptions!$C$13*(1-Assumptions!$C$14))*I37))*(1-Assumptions!$C$15)) -> 0 | J41: =((((Assumptions!$C$12*(1-Assumptions!$C$14))*J34)+((Assumptions!$C$13*(1-Assumptions!$C$14))*J37))*(1-Assumptions!$C$15)) -> 0 | ... AL41: =((((Assumptions!$C$12*(1-Assumptions!$C$14))*AL34)+((Assumptions!$C$13*(1-Assumptions!$C$14))*AL37))*(1-Assumptions!$C$15)) -> 2232.4209 | AN41: =SUM(C41:N41) -> 0 | AO41: =SUM(O41:Z41) -> 5718.4474 | AP41: =SUM(AA41:AL41) -> 19459.027
A42: Student subscription revenue | B42: $ | C42: =((((Assumptions!$C$12*(1-Assumptions!$C$14))*C34)+(((Assumptions!$C$13*(1-Assumptions!$C$14))/12)*C38))*(1-Assumptions!$C$15)) -> 0 | D42: =((((Assumptions!$C$12*(1-Assumptions!$C$14))*D34)+(((Assumptions!$C$13*(1-Assumptions!$C$14))/12)*D38))*(1-Assumptions!$C$15)) -> 0 | E42: =((((Assumptions!$C$12*(1-Assumptions!$C$14))*E34)+(((Assumptions!$C$13*(1-Assumptions!$C$14))/12)*E38))*(1-Assumptions!$C$15)) -> 0 | F42: =((((Assumptions!$C$12*(1-Assumptions!$C$14))*F34)+(((Assumptions!$C$13*(1-Assumptions!$C$14))/12)*F38))*(1-Assumptions!$C$15)) -> 0 | G42: =((((Assumptions!$C$12*(1-Assumptions!$C$14))*G34)+(((Assumptions!$C$13*(1-Assumptions!$C$14))/12)*G38))*(1-Assumptions!$C$15)) -> 0 | H42: =((((Assumptions!$C$12*(1-Assumptions!$C$14))*H34)+(((Assumptions!$C$13*(1-Assumptions!$C$14))/12)*H38))*(1-Assumptions!$C$15)) -> 0 | I42: =((((Assumptions!$C$12*(1-Assumptions!$C$14))*I34)+(((Assumptions!$C$13*(1-Assumptions!$C$14))/12)*I38))*(1-Assumptions!$C$15)) -> 0 | J42: =((((Assumptions!$C$12*(1-Assumptions!$C$14))*J34)+(((Assumptions!$C$13*(1-Assumptions!$C$14))/12)*J38))*(1-Assumptions!$C$15)) -> 0 | ... AL42: =((((Assumptions!$C$12*(1-Assumptions!$C$14))*AL34)+(((Assumptions!$C$13*(1-Assumptions!$C$14))/12)*AL38))*(1-Assumptions!$C$15)) -> 1971.5067 | AN42: =SUM(C42:N42) -> 0 | AO42: =SUM(O42:Z42) -> 3703.867 | AP42: =SUM(AA42:AL42) -> 16603.222
A43: Institutional platform: pilots, contracts, logos
A44: Incident: multiplier on new starts | B44: x | C44: =IF(AND(($C$14=1),(C$18>=(Assumptions!$C$106+1)),(C$18<=(Assumptions!$C$106+6))),Assumptions!$C$117,1) -> 1 | D44: =IF(AND(($C$14=1),(D$18>=(Assumptions!$C$106+1)),(D$18<=(Assumptions!$C$106+6))),Assumptions!$C$117,1) -> 1 | E44: =IF(AND(($C$14=1),(E$18>=(Assumptions!$C$106+1)),(E$18<=(Assumptions!$C$106+6))),Assumptions!$C$117,1) -> 1 | F44: =IF(AND(($C$14=1),(F$18>=(Assumptions!$C$106+1)),(F$18<=(Assumptions!$C$106+6))),Assumptions!$C$117,1) -> 1 | G44: =IF(AND(($C$14=1),(G$18>=(Assumptions!$C$106+1)),(G$18<=(Assumptions!$C$106+6))),Assumptions!$C$117,1) -> 1 | H44: =IF(AND(($C$14=1),(H$18>=(Assumptions!$C$106+1)),(H$18<=(Assumptions!$C$106+6))),Assumptions!$C$117,1) -> 1 | I44: =IF(AND(($C$14=1),(I$18>=(Assumptions!$C$106+1)),(I$18<=(Assumptions!$C$106+6))),Assumptions!$C$117,1) -> 1 | J44: =IF(AND(($C$14=1),(J$18>=(Assumptions!$C$106+1)),(J$18<=(Assumptions!$C$106+6))),Assumptions!$C$117,1) -> 1 | ... AL44: =IF(AND(($C$14=1),(AL$18>=(Assumptions!$C$106+1)),(AL$18<=(Assumptions!$C$106+6))),Assumptions!$C$117,1) -> 1
A45: Effective gross logo renewal rate | B45: % | C45: =MAX(0,((1-((1-Assumptions!$C$30)*$C$6))-IF(AND(($C$14=1),(C$18>=Assumptions!$C$106),(C$18<=(Assumptions!$C$106+11))),Assumptions!$C$116,0))) -> 0.85 | D45: =MAX(0,((1-((1-Assumptions!$C$30)*$C$6))-IF(AND(($C$14=1),(D$18>=Assumptions!$C$106),(D$18<=(Assumptions!$C$106+11))),Assumptions!$C$116,0))) -> 0.85 | E45: =MAX(0,((1-((1-Assumptions!$C$30)*$C$6))-IF(AND(($C$14=1),(E$18>=Assumptions!$C$106),(E$18<=(Assumptions!$C$106+11))),Assumptions!$C$116,0))) -> 0.85 | F45: =MAX(0,((1-((1-Assumptions!$C$30)*$C$6))-IF(AND(($C$14=1),(F$18>=Assumptions!$C$106),(F$18<=(Assumptions!$C$106+11))),Assumptions!$C$116,0))) -> 0.85 | G45: =MAX(0,((1-((1-Assumptions!$C$30)*$C$6))-IF(AND(($C$14=1),(G$18>=Assumptions!$C$106),(G$18<=(Assumptions!$C$106+11))),Assumptions!$C$116,0))) -> 0.85 | H45: =MAX(0,((1-((1-Assumptions!$C$30)*$C$6))-IF(AND(($C$14=1),(H$18>=Assumptions!$C$106),(H$18<=(Assumptions!$C$106+11))),Assumptions!$C$116,0))) -> 0.85 | I45: =MAX(0,((1-((1-Assumptions!$C$30)*$C$6))-IF(AND(($C$14=1),(I$18>=Assumptions!$C$106),(I$18<=(Assumptions!$C$106+11))),Assumptions!$C$116,0))) -> 0.85 | J45: =MAX(0,((1-((1-Assumptions!$C$30)*$C$6))-IF(AND(($C$14=1),(J$18>=Assumptions!$C$106),(J$18<=(Assumptions!$C$106+11))),Assumptions!$C$116,0))) -> 0.85 | ... AL45: =MAX(0,((1-((1-Assumptions!$C$30)*$C$6))-IF(AND(($C$14=1),(AL$18>=Assumptions!$C$106),(AL$18<=(Assumptions!$C$106+11))),Assumptions!$C$116,0))) -> 0.85
A46: Paid pilot starts, Department | B46: accts | C46: =((IF(OR((C$18-(Assumptions!$C$7-1)-$C$9)<1,(C$18-(Assumptions!$C$7-1)-$C$9)>36),0,INDEX(Schedules!$C$5:$AL$5,(C$18-(Assumptions!$C$7-1)-$C$9)))*$C$7)*C44) -> 0 | D46: =((IF(OR((D$18-(Assumptions!$C$7-1)-$C$9)<1,(D$18-(Assumptions!$C$7-1)-$C$9)>36),0,INDEX(Schedules!$C$5:$AL$5,(D$18-(Assumptions!$C$7-1)-$C$9)))*$C$7)*D44) -> 0 | E46: =((IF(OR((E$18-(Assumptions!$C$7-1)-$C$9)<1,(E$18-(Assumptions!$C$7-1)-$C$9)>36),0,INDEX(Schedules!$C$5:$AL$5,(E$18-(Assumptions!$C$7-1)-$C$9)))*$C$7)*E44) -> 0 | F46: =((IF(OR((F$18-(Assumptions!$C$7-1)-$C$9)<1,(F$18-(Assumptions!$C$7-1)-$C$9)>36),0,INDEX(Schedules!$C$5:$AL$5,(F$18-(Assumptions!$C$7-1)-$C$9)))*$C$7)*F44) -> 0 | G46: =((IF(OR((G$18-(Assumptions!$C$7-1)-$C$9)<1,(G$18-(Assumptions!$C$7-1)-$C$9)>36),0,INDEX(Schedules!$C$5:$AL$5,(G$18-(Assumptions!$C$7-1)-$C$9)))*$C$7)*G44) -> 0 | H46: =((IF(OR((H$18-(Assumptions!$C$7-1)-$C$9)<1,(H$18-(Assumptions!$C$7-1)-$C$9)>36),0,INDEX(Schedules!$C$5:$AL$5,(H$18-(Assumptions!$C$7-1)-$C$9)))*$C$7)*H44) -> 0 | I46: =((IF(OR((I$18-(Assumptions!$C$7-1)-$C$9)<1,(I$18-(Assumptions!$C$7-1)-$C$9)>36),0,INDEX(Schedules!$C$5:$AL$5,(I$18-(Assumptions!$C$7-1)-$C$9)))*$C$7)*I44) -> 0 | J46: =((IF(OR((J$18-(Assumptions!$C$7-1)-$C$9)<1,(J$18-(Assumptions!$C$7-1)-$C$9)>36),0,INDEX(Schedules!$C$5:$AL$5,(J$18-(Assumptions!$C$7-1)-$C$9)))*$C$7)*J44) -> 0 | ... AL46: =((IF(OR((AL$18-(Assumptions!$C$7-1)-$C$9)<1,(AL$18-(Assumptions!$C$7-1)-$C$9)>36),0,INDEX(Schedules!$C$5:$AL$5,(AL$18-(Assumptions!$C$7-1)-$C$9)))*$C$7)*AL44) -> 2.4 | AN46: =SUM(C46:N46) -> 0 | AO46: =SUM(O46:Z46) -> 3.6 | AP46: =SUM(AA46:AL46) -> 7.8
A47: Unpaid design-partner pilot starts, Department | B47: accts | C47: =INDEX(Schedules!$C$11:$AL$11,C$18) -> 0 | D47: =INDEX(Schedules!$C$11:$AL$11,D$18) -> 0 | E47: =INDEX(Schedules!$C$11:$AL$11,E$18) -> 0 | F47: =INDEX(Schedules!$C$11:$AL$11,F$18) -> 0 | G47: =INDEX(Schedules!$C$11:$AL$11,G$18) -> 1 | H47: =INDEX(Schedules!$C$11:$AL$11,H$18) -> 0 | I47: =INDEX(Schedules!$C$11:$AL$11,I$18) -> 0 | J47: =INDEX(Schedules!$C$11:$AL$11,J$18) -> 0 | ... AL47: =INDEX(Schedules!$C$11:$AL$11,AL$18) -> 0 | AN47: =SUM(C47:N47) -> 1 | AO47: =SUM(O47:Z47) -> 0 | AP47: =SUM(AA47:AL47) -> 0
A48: All pilot starts, Department | B48: accts | C48: =(C46+C47) -> 0 | D48: =(D46+D47) -> 0 | E48: =(E46+E47) -> 0 | F48: =(F46+F47) -> 0 | G48: =(G46+G47) -> 1 | H48: =(H46+H47) -> 0 | I48: =(I46+I47) -> 0 | J48: =(J46+J47) -> 0 | ... AL48: =(AL46+AL47) -> 2.4 | AN48: =SUM(C48:N48) -> 1 | AO48: =SUM(O48:Z48) -> 3.6 | AP48: =SUM(AA48:AL48) -> 7.8
A49: Direct annual starts, Department | B49: accts | C49: =((IF(OR((C$18-(Assumptions!$C$8-1)-$C$9)<1,(C$18-(Assumptions!$C$8-1)-$C$9)>36),0,INDEX(Schedules!$C$8:$AL$8,(C$18-(Assumptions!$C$8-1)-$C$9)))*$C$7)*C44) -> 0 | D49: =((IF(OR((D$18-(Assumptions!$C$8-1)-$C$9)<1,(D$18-(Assumptions!$C$8-1)-$C$9)>36),0,INDEX(Schedules!$C$8:$AL$8,(D$18-(Assumptions!$C$8-1)-$C$9)))*$C$7)*D44) -> 0 | E49: =((IF(OR((E$18-(Assumptions!$C$8-1)-$C$9)<1,(E$18-(Assumptions!$C$8-1)-$C$9)>36),0,INDEX(Schedules!$C$8:$AL$8,(E$18-(Assumptions!$C$8-1)-$C$9)))*$C$7)*E44) -> 0 | F49: =((IF(OR((F$18-(Assumptions!$C$8-1)-$C$9)<1,(F$18-(Assumptions!$C$8-1)-$C$9)>36),0,INDEX(Schedules!$C$8:$AL$8,(F$18-(Assumptions!$C$8-1)-$C$9)))*$C$7)*F44) -> 0 | G49: =((IF(OR((G$18-(Assumptions!$C$8-1)-$C$9)<1,(G$18-(Assumptions!$C$8-1)-$C$9)>36),0,INDEX(Schedules!$C$8:$AL$8,(G$18-(Assumptions!$C$8-1)-$C$9)))*$C$7)*G44) -> 0 | H49: =((IF(OR((H$18-(Assumptions!$C$8-1)-$C$9)<1,(H$18-(Assumptions!$C$8-1)-$C$9)>36),0,INDEX(Schedules!$C$8:$AL$8,(H$18-(Assumptions!$C$8-1)-$C$9)))*$C$7)*H44) -> 0 | I49: =((IF(OR((I$18-(Assumptions!$C$8-1)-$C$9)<1,(I$18-(Assumptions!$C$8-1)-$C$9)>36),0,INDEX(Schedules!$C$8:$AL$8,(I$18-(Assumptions!$C$8-1)-$C$9)))*$C$7)*I44) -> 0 | J49: =((IF(OR((J$18-(Assumptions!$C$8-1)-$C$9)<1,(J$18-(Assumptions!$C$8-1)-$C$9)>36),0,INDEX(Schedules!$C$8:$AL$8,(J$18-(Assumptions!$C$8-1)-$C$9)))*$C$7)*J44) -> 0 | ... AL49: =((IF(OR((AL$18-(Assumptions!$C$8-1)-$C$9)<1,(AL$18-(Assumptions!$C$8-1)-$C$9)>36),0,INDEX(Schedules!$C$8:$AL$8,(AL$18-(Assumptions!$C$8-1)-$C$9)))*$C$7)*AL44) -> 0 | AN49: =SUM(C49:N49) -> 0 | AO49: =SUM(O49:Z49) -> 0 | AP49: =SUM(AA49:AL49) -> 3.6
A50: New billable institutions (paid pilot or direct), Department | B50: accts | C50: =(C46+C49) -> 0 | D50: =(D46+D49) -> 0 | E50: =(E46+E49) -> 0 | F50: =(F46+F49) -> 0 | G50: =(G46+G49) -> 0 | H50: =(H46+H49) -> 0 | I50: =(I46+I49) -> 0 | J50: =(J46+J49) -> 0 | ... AL50: =(AL46+AL49) -> 2.4 | AN50: =SUM(C50:N50) -> 0 | AO50: =SUM(O50:Z50) -> 3.6 | AP50: =SUM(AA50:AL50) -> 11.4
A51: Pilots running (paid + unpaid), Department | B51: accts | C51: =C48 -> 0 | D51: =SUM(C48:D48) -> 0 | E51: =SUM(C48:E48) -> 0 | F51: =SUM(C48:F48) -> 0 | G51: =SUM(C48:G48) -> 1 | H51: =SUM(C48:H48) -> 1 | I51: =SUM(D48:I48) -> 1 | J51: =SUM(E48:J48) -> 1 | K51: =SUM(F48:K48) -> 1 | L51: =SUM(G48:L48) -> 1 | M51: =SUM(H48:M48) -> 0 | N51: =SUM(I48:N48) -> 0 | O51: =SUM(J48:O48) -> 0 | ... AL51: =SUM(AG48:AL48) -> 4.2 | AN51: =N51 -> 0 | AO51: =Z51 -> 2.4 | AP51: =AL51 -> 4.2
A52: Paid pilots running, Department | B52: accts | C52: =C46 -> 0 | D52: =SUM(C46:D46) -> 0 | E52: =SUM(C46:E46) -> 0 | F52: =SUM(C46:F46) -> 0 | G52: =SUM(C46:G46) -> 0 | H52: =SUM(C46:H46) -> 0 | I52: =SUM(D46:I46) -> 0 | J52: =SUM(E46:J46) -> 0 | K52: =SUM(F46:K46) -> 0 | L52: =SUM(G46:L46) -> 0 | M52: =SUM(H46:M46) -> 0 | N52: =SUM(I46:N46) -> 0 | O52: =SUM(J46:O46) -> 0 | ... AL52: =SUM(AG46:AL46) -> 4.2 | AN52: =N52 -> 0 | AO52: =Z52 -> 2.4 | AP52: =AL52 -> 4.2
A53: Paid pilots converting to annual, Department | B53: accts | C53: =((Assumptions!$C$127*$C$8)*0) -> 0 | D53: =((Assumptions!$C$127*$C$8)*0) -> 0 | E53: =((Assumptions!$C$127*$C$8)*0) -> 0 | F53: =((Assumptions!$C$127*$C$8)*0) -> 0 | G53: =((Assumptions!$C$127*$C$8)*0) -> 0 | H53: =((Assumptions!$C$127*$C$8)*0) -> 0 | I53: =((Assumptions!$C$127*$C$8)*0) -> 0 | J53: =((Assumptions!$C$127*$C$8)*C46) -> 0 | K53: =((Assumptions!$C$127*$C$8)*D46) -> 0 | L53: =((Assumptions!$C$127*$C$8)*E46) -> 0 | M53: =((Assumptions!$C$127*$C$8)*F46) -> 0 | N53: =((Assumptions!$C$127*$C$8)*G46) -> 0 | O53: =((Assumptions!$C$127*$C$8)*H46) -> 0 | P53: =((Assumptions!$C$127*$C$8)*I46) -> 0 | Q53: =((Assumptions!$C$127*$C$8)*J46) -> 0 | ... AL53: =((Assumptions!$C$127*$C$8)*AE46) -> 0 | AN53: =SUM(C53:N53) -> 0 | AO53: =SUM(O53:Z53) -> 0.24 | AP53: =SUM(AA53:AL53) -> 1.92
A54: Design partners converting to annual, Department | B54: accts | C54: =((Assumptions!$C$10*$C$8)*IF((C$18=(Assumptions!$C$7+$C$9)),0,IF((C$18>(Assumptions!$C$7+$C$9)),0,0))) -> 0 | D54: =((Assumptions!$C$10*$C$8)*IF((D$18=(Assumptions!$C$7+$C$9)),0,IF((D$18>(Assumptions!$C$7+$C$9)),0,0))) -> 0 | E54: =((Assumptions!$C$10*$C$8)*IF((E$18=(Assumptions!$C$7+$C$9)),0,IF((E$18>(Assumptions!$C$7+$C$9)),0,0))) -> 0 | F54: =((Assumptions!$C$10*$C$8)*IF((F$18=(Assumptions!$C$7+$C$9)),0,IF((F$18>(Assumptions!$C$7+$C$9)),0,0))) -> 0 | G54: =((Assumptions!$C$10*$C$8)*IF((G$18=(Assumptions!$C$7+$C$9)),0,IF((G$18>(Assumptions!$C$7+$C$9)),0,0))) -> 0 | H54: =((Assumptions!$C$10*$C$8)*IF((H$18=(Assumptions!$C$7+$C$9)),0,IF((H$18>(Assumptions!$C$7+$C$9)),0,0))) -> 0 | I54: =((Assumptions!$C$10*$C$8)*IF((I$18=(Assumptions!$C$7+$C$9)),0,IF((I$18>(Assumptions!$C$7+$C$9)),0,0))) -> 0 | J54: =((Assumptions!$C$10*$C$8)*IF((J$18=(Assumptions!$C$7+$C$9)),C47,IF((J$18>(Assumptions!$C$7+$C$9)),C47,0))) -> 0 | K54: =((Assumptions!$C$10*$C$8)*IF((K$18=(Assumptions!$C$7+$C$9)),SUM(C47:D47),IF((K$18>(Assumptions!$C$7+$C$9)),D47,0))) -> 0 | L54: =((Assumptions!$C$10*$C$8)*IF((L$18=(Assumptions!$C$7+$C$9)),SUM(C47:E47),IF((L$18>(Assumptions!$C$7+$C$9)),E47,0))) -> 0 | M54: =((Assumptions!$C$10*$C$8)*IF((M$18=(Assumptions!$C$7+$C$9)),SUM(C47:F47),IF((M$18>(Assumptions!$C$7+$C$9)),F47,0))) -> 0 | N54: =((Assumptions!$C$10*$C$8)*IF((N$18=(Assumptions!$C$7+$C$9)),SUM(C47:G47),IF((N$18>(Assumptions!$C$7+$C$9)),G47,0))) -> 0 | O54: =((Assumptions!$C$10*$C$8)*IF((O$18=(Assumptions!$C$7+$C$9)),SUM(C47:H47),IF((O$18>(Assumptions!$C$7+$C$9)),H47,0))) -> 0 | P54: =((Assumptions!$C$10*$C$8)*IF((P$18=(Assumptions!$C$7+$C$9)),SUM(C47:I47),IF((P$18>(Assumptions!$C$7+$C$9)),I47,0))) -> 0.48 | Q54: =((Assumptions!$C$10*$C$8)*IF((Q$18=(Assumptions!$C$7+$C$9)),SUM(C47:J47),IF((Q$18>(Assumptions!$C$7+$C$9)),J47,0))) -> 0 | R54: =((Assumptions!$C$10*$C$8)*IF((R$18=(Assumptions!$C$7+$C$9)),SUM(C47:K47),IF((R$18>(Assumptions!$C$7+$C$9)),K47,0))) -> 0 | S54: =((Assumptions!$C$10*$C$8)*IF((S$18=(Assumptions!$C$7+$C$9)),SUM(C47:L47),IF((S$18>(Assumptions!$C$7+$C$9)),L47,0))) -> 0 | T54: =((Assumptions!$C$10*$C$8)*IF((T$18=(Assumptions!$C$7+$C$9)),SUM(C47:M47),IF((T$18>(Assumptions!$C$7+$C$9)),M47,0))) -> 0 | U54: =((Assumptions!$C$10*$C$8)*IF((U$18=(Assumptions!$C$7+$C$9)),SUM(C47:N47),IF((U$18>(Assumptions!$C$7+$C$9)),N47,0))) -> 0 | V54: =((Assumptions!$C$10*$C$8)*IF((V$18=(Assumptions!$C$7+$C$9)),SUM(C47:O47),IF((V$18>(Assumptions!$C$7+$C$9)),O47,0))) -> 0 | W54: =((Assumptions!$C$10*$C$8)*IF((W$18=(Assumptions!$C$7+$C$9)),SUM(C47:P47),IF((W$18>(Assumptions!$C$7+$C$9)),P47,0))) -> 0 | X54: =((Assumptions!$C$10*$C$8)*IF((X$18=(Assumptions!$C$7+$C$9)),SUM(C47:Q47),IF((X$18>(Assumptions!$C$7+$C$9)),Q47,0))) -> 0 | Y54: =((Assumptions!$C$10*$C$8)*IF((Y$18=(Assumptions!$C$7+$C$9)),SUM(C47:R47),IF((Y$18>(Assumptions!$C$7+$C$9)),R47,0))) -> 0 | Z54: =((Assumptions!$C$10*$C$8)*IF((Z$18=(Assumptions!$C$7+$C$9)),SUM(C47:S47),IF((Z$18>(Assumptions!$C$7+$C$9)),S47,0))) -> 0 | AA54: =((Assumptions!$C$10*$C$8)*IF((AA$18=(Assumptions!$C$7+$C$9)),SUM(C47:T47),IF((AA$18>(Assumptions!$C$7+$C$9)),T47,0))) -> 0 | AB54: =((Assumptions!$C$10*$C$8)*IF((AB$18=(Assumptions!$C$7+$C$9)),SUM(C47:U47),IF((AB$18>(Assumptions!$C$7+$C$9)),U47,0))) -> 0 | AC54: =((Assumptions!$C$10*$C$8)*IF((AC$18=(Assumptions!$C$7+$C$9)),SUM(C47:V47),IF((AC$18>(Assumptions!$C$7+$C$9)),V47,0))) -> 0 | AD54: =((Assumptions!$C$10*$C$8)*IF((AD$18=(Assumptions!$C$7+$C$9)),SUM(C47:W47),IF((AD$18>(Assumptions!$C$7+$C$9)),W47,0))) -> 0 | AE54: =((Assumptions!$C$10*$C$8)*IF((AE$18=(Assumptions!$C$7+$C$9)),SUM(C47:X47),IF((AE$18>(Assumptions!$C$7+$C$9)),X47,0))) -> 0 | AF54: =((Assumptions!$C$10*$C$8)*IF((AF$18=(Assumptions!$C$7+$C$9)),SUM(C47:Y47),IF((AF$18>(Assumptions!$C$7+$C$9)),Y47,0))) -> 0 | AG54: =((Assumptions!$C$10*$C$8)*IF((AG$18=(Assumptions!$C$7+$C$9)),SUM(C47:Z47),IF((AG$18>(Assumptions!$C$7+$C$9)),Z47,0))) -> 0 | AH54: =((Assumptions!$C$10*$C$8)*IF((AH$18=(Assumptions!$C$7+$C$9)),SUM(C47:AA47),IF((AH$18>(Assumptions!$C$7+$C$9)),AA47,0))) -> 0 | AI54: =((Assumptions!$C$10*$C$8)*IF((AI$18=(Assumptions!$C$7+$C$9)),SUM(C47:AB47),IF((AI$18>(Assumptions!$C$7+$C$9)),AB47,0))) -> 0 | AJ54: =((Assumptions!$C$10*$C$8)*IF((AJ$18=(Assumptions!$C$7+$C$9)),SUM(C47:AC47),IF((AJ$18>(Assumptions!$C$7+$C$9)),AC47,0))) -> 0 | AK54: =((Assumptions!$C$10*$C$8)*IF((AK$18=(Assumptions!$C$7+$C$9)),SUM(C47:AD47),IF((AK$18>(Assumptions!$C$7+$C$9)),AD47,0))) -> 0 | AL54: =((Assumptions!$C$10*$C$8)*IF((AL$18=(Assumptions!$C$7+$C$9)),SUM(C47:AE47),IF((AL$18>(Assumptions!$C$7+$C$9)),AE47,0))) -> 0 | AN54: =SUM(C54:N54) -> 0 | AO54: =SUM(O54:Z54) -> 0.48 | AP54: =SUM(AA54:AL54) -> 0
A55: New annual contracts, Department | B55: accts | C55: =((C53+C54)+C49) -> 0 | D55: =((D53+D54)+D49) -> 0 | E55: =((E53+E54)+E49) -> 0 | F55: =((F53+F54)+F49) -> 0 | G55: =((G53+G54)+G49) -> 0 | H55: =((H53+H54)+H49) -> 0 | I55: =((I53+I54)+I49) -> 0 | J55: =((J53+J54)+J49) -> 0 | ... AL55: =((AL53+AL54)+AL49) -> 0 | AN55: =SUM(C55:N55) -> 0 | AO55: =SUM(O55:Z55) -> 0.72 | AP55: =SUM(AA55:AL55) -> 5.52
A56: Annual contract starts (new + renewals), Department | B56: accts | C56: =(C55+(C45*0)) -> 0 | D56: =(D55+(D45*0)) -> 0 | E56: =(E55+(E45*0)) -> 0 | F56: =(F55+(F45*0)) -> 0 | G56: =(G55+(G45*0)) -> 0 | H56: =(H55+(H45*0)) -> 0 | I56: =(I55+(I45*0)) -> 0 | J56: =(J55+(J45*0)) -> 0 | ... N56: =(N55+(N45*0)) -> 0 | O56: =(O55+(O45*C56)) -> 0 | P56: =(P55+(P45*D56)) -> 0.48 | Q56: =(Q55+(Q45*E56)) -> 0 | R56: =(R55+(R45*F56)) -> 0 | S56: =(S55+(S45*G56)) -> 0 | T56: =(T55+(T45*H56)) -> 0 | U56: =(U55+(U45*I56)) -> 0 | V56: =(V55+(V45*J56)) -> 0 | ... AL56: =(AL55+(AL45*Z56)) -> 0 | AN56: =SUM(C56:N56) -> 0 | AO56: =SUM(O56:Z56) -> 0.72 | AP56: =SUM(AA56:AL56) -> 6.132
A57: Annual logos active, Department | B57: accts | C57: =C56 -> 0 | D57: =SUM(C56:D56) -> 0 | E57: =SUM(C56:E56) -> 0 | F57: =SUM(C56:F56) -> 0 | G57: =SUM(C56:G56) -> 0 | H57: =SUM(C56:H56) -> 0 | I57: =SUM(C56:I56) -> 0 | J57: =SUM(C56:J56) -> 0 | K57: =SUM(C56:K56) -> 0 | L57: =SUM(C56:L56) -> 0 | M57: =SUM(C56:M56) -> 0 | N57: =SUM(C56:N56) -> 0 | O57: =SUM(D56:O56) -> 0 | P57: =SUM(E56:P56) -> 0.48 | Q57: =SUM(F56:Q56) -> 0.48 | R57: =SUM(G56:R56) -> 0.48 | S57: =SUM(H56:S56) -> 0.48 | T57: =SUM(I56:T56) -> 0.48 | U57: =SUM(J56:U56) -> 0.48 | ... AL57: =SUM(AA56:AL56) -> 6.132 | AN57: =N57 -> 0 | AO57: =Z57 -> 0.72 | AP57: =AL57 -> 6.132
A58: Net ACV per new contract, Department | B58: $ | C58: =((Assumptions!$C$121*(1-Assumptions!$C$29))*$C$10) -> 25080 | D58: =((Assumptions!$C$121*(1-Assumptions!$C$29))*$C$10) -> 25080 | E58: =((Assumptions!$C$121*(1-Assumptions!$C$29))*$C$10) -> 25080 | F58: =((Assumptions!$C$121*(1-Assumptions!$C$29))*$C$10) -> 25080 | G58: =((Assumptions!$C$121*(1-Assumptions!$C$29))*$C$10) -> 25080 | H58: =((Assumptions!$C$121*(1-Assumptions!$C$29))*$C$10) -> 25080 | I58: =((Assumptions!$C$121*(1-Assumptions!$C$29))*$C$10) -> 25080 | J58: =((Assumptions!$C$121*(1-Assumptions!$C$29))*$C$10) -> 25080 | ... AL58: =((Assumptions!$C$121*(1-Assumptions!$C$29))*$C$10) -> 25080
A59: Contract value started or renewed, Department | B59: $ | C59: =((C55*C58)+((C45*(1+Assumptions!$C$31))*0)) -> 0 | D59: =((D55*D58)+((D45*(1+Assumptions!$C$31))*0)) -> 0 | E59: =((E55*E58)+((E45*(1+Assumptions!$C$31))*0)) -> 0 | F59: =((F55*F58)+((F45*(1+Assumptions!$C$31))*0)) -> 0 | G59: =((G55*G58)+((G45*(1+Assumptions!$C$31))*0)) -> 0 | H59: =((H55*H58)+((H45*(1+Assumptions!$C$31))*0)) -> 0 | I59: =((I55*I58)+((I45*(1+Assumptions!$C$31))*0)) -> 0 | J59: =((J55*J58)+((J45*(1+Assumptions!$C$31))*0)) -> 0 | ... N59: =((N55*N58)+((N45*(1+Assumptions!$C$31))*0)) -> 0 | O59: =((O55*O58)+((O45*(1+Assumptions!$C$31))*C59)) -> 0 | P59: =((P55*P58)+((P45*(1+Assumptions!$C$31))*D59)) -> 12038.4 | Q59: =((Q55*Q58)+((Q45*(1+Assumptions!$C$31))*E59)) -> 0 | R59: =((R55*R58)+((R45*(1+Assumptions!$C$31))*F59)) -> 0 | S59: =((S55*S58)+((S45*(1+Assumptions!$C$31))*G59)) -> 0 | T59: =((T55*T58)+((T45*(1+Assumptions!$C$31))*H59)) -> 0 | U59: =((U55*U58)+((U45*(1+Assumptions!$C$31))*I59)) -> 0 | V59: =((V55*V58)+((V45*(1+Assumptions!$C$31))*J59)) -> 0 | ... AL59: =((AL55*AL58)+((AL45*(1+Assumptions!$C$31))*Z59)) -> 0 | AN59: =SUM(C59:N59) -> 0 | AO59: =SUM(O59:Z59) -> 18057.6 | AP59: =SUM(AA59:AL59) -> 155325.46
A60: Pilot credit given at conversion, Department | B60: $ | C60: =(Assumptions!$C$126*C53) -> 0 | D60: =(Assumptions!$C$126*D53) -> 0 | E60: =(Assumptions!$C$126*E53) -> 0 | F60: =(Assumptions!$C$126*F53) -> 0 | G60: =(Assumptions!$C$126*G53) -> 0 | H60: =(Assumptions!$C$126*H53) -> 0 | I60: =(Assumptions!$C$126*I53) -> 0 | J60: =(Assumptions!$C$126*J53) -> 0 | ... AL60: =(Assumptions!$C$126*AL53) -> 0 | AN60: =SUM(C60:N60) -> 0 | AO60: =SUM(O60:Z60) -> 1800 | AP60: =SUM(AA60:AL60) -> 14400
A61: Platform subscription revenue, Department | B61: $ | C61: =((C59-C60)/12) -> 0 | D61: =((SUM(C59:D59)-SUM(C60:D60))/12) -> 0 | E61: =((SUM(C59:E59)-SUM(C60:E60))/12) -> 0 | F61: =((SUM(C59:F59)-SUM(C60:F60))/12) -> 0 | G61: =((SUM(C59:G59)-SUM(C60:G60))/12) -> 0 | H61: =((SUM(C59:H59)-SUM(C60:H60))/12) -> 0 | I61: =((SUM(C59:I59)-SUM(C60:I60))/12) -> 0 | J61: =((SUM(C59:J59)-SUM(C60:J60))/12) -> 0 | K61: =((SUM(C59:K59)-SUM(C60:K60))/12) -> 0 | L61: =((SUM(C59:L59)-SUM(C60:L60))/12) -> 0 | M61: =((SUM(C59:M59)-SUM(C60:M60))/12) -> 0 | N61: =((SUM(C59:N59)-SUM(C60:N60))/12) -> 0 | O61: =((SUM(D59:O59)-SUM(D60:O60))/12) -> 0 | P61: =((SUM(E59:P59)-SUM(E60:P60))/12) -> 1003.2 | Q61: =((SUM(F59:Q59)-SUM(F60:Q60))/12) -> 1003.2 | R61: =((SUM(G59:R59)-SUM(G60:R60))/12) -> 1003.2 | S61: =((SUM(H59:S59)-SUM(H60:S60))/12) -> 1003.2 | T61: =((SUM(I59:T59)-SUM(I60:T60))/12) -> 1003.2 | U61: =((SUM(J59:U59)-SUM(J60:U60))/12) -> 1003.2 | ... AL61: =((SUM(AA59:AL59)-SUM(AA60:AL60))/12) -> 11743.788 | AN61: =SUM(C61:N61) -> 0 | AO61: =SUM(O61:Z61) -> 12090 | AP61: =SUM(AA61:AL61) -> 82730.1
A62: Platform billings, Department | B62: $ | C62: =(C59-C60) -> 0 | D62: =(D59-D60) -> 0 | E62: =(E59-E60) -> 0 | F62: =(F59-F60) -> 0 | G62: =(G59-G60) -> 0 | H62: =(H59-H60) -> 0 | I62: =(I59-I60) -> 0 | J62: =(J59-J60) -> 0 | ... AL62: =(AL59-AL60) -> 0 | AN62: =SUM(C62:N62) -> 0 | AO62: =SUM(O62:Z62) -> 16257.6 | AP62: =SUM(AA62:AL62) -> 140925.46
A63: Pilot software revenue, Department | B63: $ | C63: =(((Assumptions!$C$122*$C$10)/6)*C52) -> 0 | D63: =(((Assumptions!$C$122*$C$10)/6)*D52) -> 0 | E63: =(((Assumptions!$C$122*$C$10)/6)*E52) -> 0 | F63: =(((Assumptions!$C$122*$C$10)/6)*F52) -> 0 | G63: =(((Assumptions!$C$122*$C$10)/6)*G52) -> 0 | H63: =(((Assumptions!$C$122*$C$10)/6)*H52) -> 0 | I63: =(((Assumptions!$C$122*$C$10)/6)*I52) -> 0 | J63: =(((Assumptions!$C$122*$C$10)/6)*J52) -> 0 | ... AL63: =(((Assumptions!$C$122*$C$10)/6)*AL52) -> 9975 | AN63: =SUM(C63:N63) -> 0 | AO63: =SUM(O63:Z63) -> 31350 | AP63: =SUM(AA63:AL63) -> 94050
A64: Pilot billings, Department | B64: $ | C64: =((Assumptions!$C$122*$C$10)*C46) -> 0 | D64: =((Assumptions!$C$122*$C$10)*D46) -> 0 | E64: =((Assumptions!$C$122*$C$10)*E46) -> 0 | F64: =((Assumptions!$C$122*$C$10)*F46) -> 0 | G64: =((Assumptions!$C$122*$C$10)*G46) -> 0 | H64: =((Assumptions!$C$122*$C$10)*H46) -> 0 | I64: =((Assumptions!$C$122*$C$10)*I46) -> 0 | J64: =((Assumptions!$C$122*$C$10)*J46) -> 0 | ... AL64: =((Assumptions!$C$122*$C$10)*AL46) -> 34200 | AN64: =SUM(C64:N64) -> 0 | AO64: =SUM(O64:Z64) -> 51300 | AP64: =SUM(AA64:AL64) -> 111150
A65: Services fee per new billable institution, Department | B65: $ | C65: =((Assumptions!$C$123*$C$10)+(Assumptions!$C$34*Assumptions!$C$35)) -> 20250 | D65: =((Assumptions!$C$123*$C$10)+(Assumptions!$C$34*Assumptions!$C$35)) -> 20250 | E65: =((Assumptions!$C$123*$C$10)+(Assumptions!$C$34*Assumptions!$C$35)) -> 20250 | F65: =((Assumptions!$C$123*$C$10)+(Assumptions!$C$34*Assumptions!$C$35)) -> 20250 | G65: =((Assumptions!$C$123*$C$10)+(Assumptions!$C$34*Assumptions!$C$35)) -> 20250 | H65: =((Assumptions!$C$123*$C$10)+(Assumptions!$C$34*Assumptions!$C$35)) -> 20250 | I65: =((Assumptions!$C$123*$C$10)+(Assumptions!$C$34*Assumptions!$C$35)) -> 20250 | J65: =((Assumptions!$C$123*$C$10)+(Assumptions!$C$34*Assumptions!$C$35)) -> 20250 | ... AL65: =((Assumptions!$C$123*$C$10)+(Assumptions!$C$34*Assumptions!$C$35)) -> 20250
A66: Implementation services revenue, Department | B66: $ | C66: =((C65/3)*C50) -> 0 | D66: =((D65/3)*SUM(C50:D50)) -> 0 | E66: =((E65/3)*SUM(C50:E50)) -> 0 | F66: =((F65/3)*SUM(D50:F50)) -> 0 | G66: =((G65/3)*SUM(E50:G50)) -> 0 | H66: =((H65/3)*SUM(F50:H50)) -> 0 | I66: =((I65/3)*SUM(G50:I50)) -> 0 | J66: =((J65/3)*SUM(H50:J50)) -> 0 | K66: =((K65/3)*SUM(I50:K50)) -> 0 | L66: =((L65/3)*SUM(J50:L50)) -> 0 | ... AL66: =((AL65/3)*SUM(AJ50:AL50)) -> 24300 | AN66: =SUM(C66:N66) -> 0 | AO66: =SUM(O66:Z66) -> 56700 | AP66: =SUM(AA66:AL66) -> 214650
A67: Implementation billings, Department | B67: $ | C67: =(C65*C50) -> 0 | D67: =(D65*D50) -> 0 | E67: =(E65*E50) -> 0 | F67: =(F65*F50) -> 0 | G67: =(G65*G50) -> 0 | H67: =(H65*H50) -> 0 | I67: =(I65*I50) -> 0 | J67: =(J65*J50) -> 0 | ... AL67: =(AL65*AL50) -> 48600 | AN67: =SUM(C67:N67) -> 0 | AO67: =SUM(O67:Z67) -> 72900 | AP67: =SUM(AA67:AL67) -> 230850
A68: Implementation hours demanded, Department | B68: hours | C68: =((C47*Assumptions!$C$124)+(C50*(Assumptions!$C$124+(Assumptions!$C$34*Assumptions!$C$36)))) -> 0 | D68: =((D47*Assumptions!$C$124)+(D50*(Assumptions!$C$124+(Assumptions!$C$34*Assumptions!$C$36)))) -> 0 | E68: =((E47*Assumptions!$C$124)+(E50*(Assumptions!$C$124+(Assumptions!$C$34*Assumptions!$C$36)))) -> 0 | F68: =((F47*Assumptions!$C$124)+(F50*(Assumptions!$C$124+(Assumptions!$C$34*Assumptions!$C$36)))) -> 0 | G68: =((G47*Assumptions!$C$124)+(G50*(Assumptions!$C$124+(Assumptions!$C$34*Assumptions!$C$36)))) -> 115 | H68: =((H47*Assumptions!$C$124)+(H50*(Assumptions!$C$124+(Assumptions!$C$34*Assumptions!$C$36)))) -> 0 | I68: =((I47*Assumptions!$C$124)+(I50*(Assumptions!$C$124+(Assumptions!$C$34*Assumptions!$C$36)))) -> 0 | J68: =((J47*Assumptions!$C$124)+(J50*(Assumptions!$C$124+(Assumptions!$C$34*Assumptions!$C$36)))) -> 0 | ... AL68: =((AL47*Assumptions!$C$124)+(AL50*(Assumptions!$C$124+(Assumptions!$C$34*Assumptions!$C$36)))) -> 381.6 | AN68: =SUM(C68:N68) -> 115 | AO68: =SUM(O68:Z68) -> 572.4 | AP68: =SUM(AA68:AL68) -> 1812.6
A69: Paid pilot starts, Campus | B69: accts | C69: =((IF(OR((C$18-(Assumptions!$C$7-1)-$C$9)<1,(C$18-(Assumptions!$C$7-1)-$C$9)>36),0,INDEX(Schedules!$C$6:$AL$6,(C$18-(Assumptions!$C$7-1)-$C$9)))*$C$7)*C44) -> 0 | D69: =((IF(OR((D$18-(Assumptions!$C$7-1)-$C$9)<1,(D$18-(Assumptions!$C$7-1)-$C$9)>36),0,INDEX(Schedules!$C$6:$AL$6,(D$18-(Assumptions!$C$7-1)-$C$9)))*$C$7)*D44) -> 0 | E69: =((IF(OR((E$18-(Assumptions!$C$7-1)-$C$9)<1,(E$18-(Assumptions!$C$7-1)-$C$9)>36),0,INDEX(Schedules!$C$6:$AL$6,(E$18-(Assumptions!$C$7-1)-$C$9)))*$C$7)*E44) -> 0 | F69: =((IF(OR((F$18-(Assumptions!$C$7-1)-$C$9)<1,(F$18-(Assumptions!$C$7-1)-$C$9)>36),0,INDEX(Schedules!$C$6:$AL$6,(F$18-(Assumptions!$C$7-1)-$C$9)))*$C$7)*F44) -> 0 | G69: =((IF(OR((G$18-(Assumptions!$C$7-1)-$C$9)<1,(G$18-(Assumptions!$C$7-1)-$C$9)>36),0,INDEX(Schedules!$C$6:$AL$6,(G$18-(Assumptions!$C$7-1)-$C$9)))*$C$7)*G44) -> 0 | H69: =((IF(OR((H$18-(Assumptions!$C$7-1)-$C$9)<1,(H$18-(Assumptions!$C$7-1)-$C$9)>36),0,INDEX(Schedules!$C$6:$AL$6,(H$18-(Assumptions!$C$7-1)-$C$9)))*$C$7)*H44) -> 0 | I69: =((IF(OR((I$18-(Assumptions!$C$7-1)-$C$9)<1,(I$18-(Assumptions!$C$7-1)-$C$9)>36),0,INDEX(Schedules!$C$6:$AL$6,(I$18-(Assumptions!$C$7-1)-$C$9)))*$C$7)*I44) -> 0 | J69: =((IF(OR((J$18-(Assumptions!$C$7-1)-$C$9)<1,(J$18-(Assumptions!$C$7-1)-$C$9)>36),0,INDEX(Schedules!$C$6:$AL$6,(J$18-(Assumptions!$C$7-1)-$C$9)))*$C$7)*J44) -> 0 | ... AL69: =((IF(OR((AL$18-(Assumptions!$C$7-1)-$C$9)<1,(AL$18-(Assumptions!$C$7-1)-$C$9)>36),0,INDEX(Schedules!$C$6:$AL$6,(AL$18-(Assumptions!$C$7-1)-$C$9)))*$C$7)*AL44) -> 1.2 | AN69: =SUM(C69:N69) -> 0 | AO69: =SUM(O69:Z69) -> 1.8 | AP69: =SUM(AA69:AL69) -> 4.2
A70: Unpaid design-partner pilot starts, Campus | B70: accts | C70: =INDEX(Schedules!$C$12:$AL$12,C$18) -> 0 | D70: =INDEX(Schedules!$C$12:$AL$12,D$18) -> 0 | E70: =INDEX(Schedules!$C$12:$AL$12,E$18) -> 0 | F70: =INDEX(Schedules!$C$12:$AL$12,F$18) -> 0 | G70: =INDEX(Schedules!$C$12:$AL$12,G$18) -> 0 | H70: =INDEX(Schedules!$C$12:$AL$12,H$18) -> 0 | I70: =INDEX(Schedules!$C$12:$AL$12,I$18) -> 0 | J70: =INDEX(Schedules!$C$12:$AL$12,J$18) -> 1 | ... AL70: =INDEX(Schedules!$C$12:$AL$12,AL$18) -> 0 | AN70: =SUM(C70:N70) -> 1 | AO70: =SUM(O70:Z70) -> 0 | AP70: =SUM(AA70:AL70) -> 0
A71: All pilot starts, Campus | B71: accts | C71: =(C69+C70) -> 0 | D71: =(D69+D70) -> 0 | E71: =(E69+E70) -> 0 | F71: =(F69+F70) -> 0 | G71: =(G69+G70) -> 0 | H71: =(H69+H70) -> 0 | I71: =(I69+I70) -> 0 | J71: =(J69+J70) -> 1 | ... AL71: =(AL69+AL70) -> 1.2 | AN71: =SUM(C71:N71) -> 1 | AO71: =SUM(O71:Z71) -> 1.8 | AP71: =SUM(AA71:AL71) -> 4.2
A72: Direct annual starts, Campus | B72: accts | C72: =((IF(OR((C$18-(Assumptions!$C$8-1)-$C$9)<1,(C$18-(Assumptions!$C$8-1)-$C$9)>36),0,INDEX(Schedules!$C$9:$AL$9,(C$18-(Assumptions!$C$8-1)-$C$9)))*$C$7)*C44) -> 0 | D72: =((IF(OR((D$18-(Assumptions!$C$8-1)-$C$9)<1,(D$18-(Assumptions!$C$8-1)-$C$9)>36),0,INDEX(Schedules!$C$9:$AL$9,(D$18-(Assumptions!$C$8-1)-$C$9)))*$C$7)*D44) -> 0 | E72: =((IF(OR((E$18-(Assumptions!$C$8-1)-$C$9)<1,(E$18-(Assumptions!$C$8-1)-$C$9)>36),0,INDEX(Schedules!$C$9:$AL$9,(E$18-(Assumptions!$C$8-1)-$C$9)))*$C$7)*E44) -> 0 | F72: =((IF(OR((F$18-(Assumptions!$C$8-1)-$C$9)<1,(F$18-(Assumptions!$C$8-1)-$C$9)>36),0,INDEX(Schedules!$C$9:$AL$9,(F$18-(Assumptions!$C$8-1)-$C$9)))*$C$7)*F44) -> 0 | G72: =((IF(OR((G$18-(Assumptions!$C$8-1)-$C$9)<1,(G$18-(Assumptions!$C$8-1)-$C$9)>36),0,INDEX(Schedules!$C$9:$AL$9,(G$18-(Assumptions!$C$8-1)-$C$9)))*$C$7)*G44) -> 0 | H72: =((IF(OR((H$18-(Assumptions!$C$8-1)-$C$9)<1,(H$18-(Assumptions!$C$8-1)-$C$9)>36),0,INDEX(Schedules!$C$9:$AL$9,(H$18-(Assumptions!$C$8-1)-$C$9)))*$C$7)*H44) -> 0 | I72: =((IF(OR((I$18-(Assumptions!$C$8-1)-$C$9)<1,(I$18-(Assumptions!$C$8-1)-$C$9)>36),0,INDEX(Schedules!$C$9:$AL$9,(I$18-(Assumptions!$C$8-1)-$C$9)))*$C$7)*I44) -> 0 | J72: =((IF(OR((J$18-(Assumptions!$C$8-1)-$C$9)<1,(J$18-(Assumptions!$C$8-1)-$C$9)>36),0,INDEX(Schedules!$C$9:$AL$9,(J$18-(Assumptions!$C$8-1)-$C$9)))*$C$7)*J44) -> 0 | ... AL72: =((IF(OR((AL$18-(Assumptions!$C$8-1)-$C$9)<1,(AL$18-(Assumptions!$C$8-1)-$C$9)>36),0,INDEX(Schedules!$C$9:$AL$9,(AL$18-(Assumptions!$C$8-1)-$C$9)))*$C$7)*AL44) -> 0 | AN72: =SUM(C72:N72) -> 0 | AO72: =SUM(O72:Z72) -> 0 | AP72: =SUM(AA72:AL72) -> 1.8
A73: New billable institutions (paid pilot or direct), Campus | B73: accts | C73: =(C69+C72) -> 0 | D73: =(D69+D72) -> 0 | E73: =(E69+E72) -> 0 | F73: =(F69+F72) -> 0 | G73: =(G69+G72) -> 0 | H73: =(H69+H72) -> 0 | I73: =(I69+I72) -> 0 | J73: =(J69+J72) -> 0 | ... AL73: =(AL69+AL72) -> 1.2 | AN73: =SUM(C73:N73) -> 0 | AO73: =SUM(O73:Z73) -> 1.8 | AP73: =SUM(AA73:AL73) -> 6
A74: Pilots running (paid + unpaid), Campus | B74: accts | C74: =C71 -> 0 | D74: =SUM(C71:D71) -> 0 | E74: =SUM(C71:E71) -> 0 | F74: =SUM(C71:F71) -> 0 | G74: =SUM(C71:G71) -> 0 | H74: =SUM(C71:H71) -> 0 | I74: =SUM(D71:I71) -> 0 | J74: =SUM(E71:J71) -> 1 | K74: =SUM(F71:K71) -> 1 | L74: =SUM(G71:L71) -> 1 | M74: =SUM(H71:M71) -> 1 | N74: =SUM(I71:N71) -> 1 | O74: =SUM(J71:O71) -> 1 | ... AL74: =SUM(AG71:AL71) -> 2.4 | AN74: =N74 -> 1 | AO74: =Z74 -> 1.2 | AP74: =AL74 -> 2.4
A75: Paid pilots running, Campus | B75: accts | C75: =C69 -> 0 | D75: =SUM(C69:D69) -> 0 | E75: =SUM(C69:E69) -> 0 | F75: =SUM(C69:F69) -> 0 | G75: =SUM(C69:G69) -> 0 | H75: =SUM(C69:H69) -> 0 | I75: =SUM(D69:I69) -> 0 | J75: =SUM(E69:J69) -> 0 | K75: =SUM(F69:K69) -> 0 | L75: =SUM(G69:L69) -> 0 | M75: =SUM(H69:M69) -> 0 | N75: =SUM(I69:N69) -> 0 | O75: =SUM(J69:O69) -> 0 | ... AL75: =SUM(AG69:AL69) -> 2.4 | AN75: =N75 -> 0 | AO75: =Z75 -> 1.2 | AP75: =AL75 -> 2.4
A76: Paid pilots converting to annual, Campus | B76: accts | C76: =((Assumptions!$D$127*$C$8)*0) -> 0 | D76: =((Assumptions!$D$127*$C$8)*0) -> 0 | E76: =((Assumptions!$D$127*$C$8)*0) -> 0 | F76: =((Assumptions!$D$127*$C$8)*0) -> 0 | G76: =((Assumptions!$D$127*$C$8)*0) -> 0 | H76: =((Assumptions!$D$127*$C$8)*0) -> 0 | I76: =((Assumptions!$D$127*$C$8)*0) -> 0 | J76: =((Assumptions!$D$127*$C$8)*C69) -> 0 | K76: =((Assumptions!$D$127*$C$8)*D69) -> 0 | L76: =((Assumptions!$D$127*$C$8)*E69) -> 0 | M76: =((Assumptions!$D$127*$C$8)*F69) -> 0 | N76: =((Assumptions!$D$127*$C$8)*G69) -> 0 | O76: =((Assumptions!$D$127*$C$8)*H69) -> 0 | P76: =((Assumptions!$D$127*$C$8)*I69) -> 0 | Q76: =((Assumptions!$D$127*$C$8)*J69) -> 0 | ... AL76: =((Assumptions!$D$127*$C$8)*AE69) -> 0 | AN76: =SUM(C76:N76) -> 0 | AO76: =SUM(O76:Z76) -> 0 | AP76: =SUM(AA76:AL76) -> 0.864
A77: Design partners converting to annual, Campus | B77: accts | C77: =((Assumptions!$C$10*$C$8)*IF((C$18=(Assumptions!$C$7+$C$9)),0,IF((C$18>(Assumptions!$C$7+$C$9)),0,0))) -> 0 | D77: =((Assumptions!$C$10*$C$8)*IF((D$18=(Assumptions!$C$7+$C$9)),0,IF((D$18>(Assumptions!$C$7+$C$9)),0,0))) -> 0 | E77: =((Assumptions!$C$10*$C$8)*IF((E$18=(Assumptions!$C$7+$C$9)),0,IF((E$18>(Assumptions!$C$7+$C$9)),0,0))) -> 0 | F77: =((Assumptions!$C$10*$C$8)*IF((F$18=(Assumptions!$C$7+$C$9)),0,IF((F$18>(Assumptions!$C$7+$C$9)),0,0))) -> 0 | G77: =((Assumptions!$C$10*$C$8)*IF((G$18=(Assumptions!$C$7+$C$9)),0,IF((G$18>(Assumptions!$C$7+$C$9)),0,0))) -> 0 | H77: =((Assumptions!$C$10*$C$8)*IF((H$18=(Assumptions!$C$7+$C$9)),0,IF((H$18>(Assumptions!$C$7+$C$9)),0,0))) -> 0 | I77: =((Assumptions!$C$10*$C$8)*IF((I$18=(Assumptions!$C$7+$C$9)),0,IF((I$18>(Assumptions!$C$7+$C$9)),0,0))) -> 0 | J77: =((Assumptions!$C$10*$C$8)*IF((J$18=(Assumptions!$C$7+$C$9)),C70,IF((J$18>(Assumptions!$C$7+$C$9)),C70,0))) -> 0 | K77: =((Assumptions!$C$10*$C$8)*IF((K$18=(Assumptions!$C$7+$C$9)),SUM(C70:D70),IF((K$18>(Assumptions!$C$7+$C$9)),D70,0))) -> 0 | L77: =((Assumptions!$C$10*$C$8)*IF((L$18=(Assumptions!$C$7+$C$9)),SUM(C70:E70),IF((L$18>(Assumptions!$C$7+$C$9)),E70,0))) -> 0 | M77: =((Assumptions!$C$10*$C$8)*IF((M$18=(Assumptions!$C$7+$C$9)),SUM(C70:F70),IF((M$18>(Assumptions!$C$7+$C$9)),F70,0))) -> 0 | N77: =((Assumptions!$C$10*$C$8)*IF((N$18=(Assumptions!$C$7+$C$9)),SUM(C70:G70),IF((N$18>(Assumptions!$C$7+$C$9)),G70,0))) -> 0 | O77: =((Assumptions!$C$10*$C$8)*IF((O$18=(Assumptions!$C$7+$C$9)),SUM(C70:H70),IF((O$18>(Assumptions!$C$7+$C$9)),H70,0))) -> 0 | P77: =((Assumptions!$C$10*$C$8)*IF((P$18=(Assumptions!$C$7+$C$9)),SUM(C70:I70),IF((P$18>(Assumptions!$C$7+$C$9)),I70,0))) -> 0 | Q77: =((Assumptions!$C$10*$C$8)*IF((Q$18=(Assumptions!$C$7+$C$9)),SUM(C70:J70),IF((Q$18>(Assumptions!$C$7+$C$9)),J70,0))) -> 0.48 | R77: =((Assumptions!$C$10*$C$8)*IF((R$18=(Assumptions!$C$7+$C$9)),SUM(C70:K70),IF((R$18>(Assumptions!$C$7+$C$9)),K70,0))) -> 0 | S77: =((Assumptions!$C$10*$C$8)*IF((S$18=(Assumptions!$C$7+$C$9)),SUM(C70:L70),IF((S$18>(Assumptions!$C$7+$C$9)),L70,0))) -> 0 | T77: =((Assumptions!$C$10*$C$8)*IF((T$18=(Assumptions!$C$7+$C$9)),SUM(C70:M70),IF((T$18>(Assumptions!$C$7+$C$9)),M70,0))) -> 0 | U77: =((Assumptions!$C$10*$C$8)*IF((U$18=(Assumptions!$C$7+$C$9)),SUM(C70:N70),IF((U$18>(Assumptions!$C$7+$C$9)),N70,0))) -> 0 | V77: =((Assumptions!$C$10*$C$8)*IF((V$18=(Assumptions!$C$7+$C$9)),SUM(C70:O70),IF((V$18>(Assumptions!$C$7+$C$9)),O70,0))) -> 0 | W77: =((Assumptions!$C$10*$C$8)*IF((W$18=(Assumptions!$C$7+$C$9)),SUM(C70:P70),IF((W$18>(Assumptions!$C$7+$C$9)),P70,0))) -> 0 | X77: =((Assumptions!$C$10*$C$8)*IF((X$18=(Assumptions!$C$7+$C$9)),SUM(C70:Q70),IF((X$18>(Assumptions!$C$7+$C$9)),Q70,0))) -> 0 | Y77: =((Assumptions!$C$10*$C$8)*IF((Y$18=(Assumptions!$C$7+$C$9)),SUM(C70:R70),IF((Y$18>(Assumptions!$C$7+$C$9)),R70,0))) -> 0 | Z77: =((Assumptions!$C$10*$C$8)*IF((Z$18=(Assumptions!$C$7+$C$9)),SUM(C70:S70),IF((Z$18>(Assumptions!$C$7+$C$9)),S70,0))) -> 0 | AA77: =((Assumptions!$C$10*$C$8)*IF((AA$18=(Assumptions!$C$7+$C$9)),SUM(C70:T70),IF((AA$18>(Assumptions!$C$7+$C$9)),T70,0))) -> 0 | AB77: =((Assumptions!$C$10*$C$8)*IF((AB$18=(Assumptions!$C$7+$C$9)),SUM(C70:U70),IF((AB$18>(Assumptions!$C$7+$C$9)),U70,0))) -> 0 | AC77: =((Assumptions!$C$10*$C$8)*IF((AC$18=(Assumptions!$C$7+$C$9)),SUM(C70:V70),IF((AC$18>(Assumptions!$C$7+$C$9)),V70,0))) -> 0 | AD77: =((Assumptions!$C$10*$C$8)*IF((AD$18=(Assumptions!$C$7+$C$9)),SUM(C70:W70),IF((AD$18>(Assumptions!$C$7+$C$9)),W70,0))) -> 0 | AE77: =((Assumptions!$C$10*$C$8)*IF((AE$18=(Assumptions!$C$7+$C$9)),SUM(C70:X70),IF((AE$18>(Assumptions!$C$7+$C$9)),X70,0))) -> 0 | AF77: =((Assumptions!$C$10*$C$8)*IF((AF$18=(Assumptions!$C$7+$C$9)),SUM(C70:Y70),IF((AF$18>(Assumptions!$C$7+$C$9)),Y70,0))) -> 0 | AG77: =((Assumptions!$C$10*$C$8)*IF((AG$18=(Assumptions!$C$7+$C$9)),SUM(C70:Z70),IF((AG$18>(Assumptions!$C$7+$C$9)),Z70,0))) -> 0 | AH77: =((Assumptions!$C$10*$C$8)*IF((AH$18=(Assumptions!$C$7+$C$9)),SUM(C70:AA70),IF((AH$18>(Assumptions!$C$7+$C$9)),AA70,0))) -> 0 | AI77: =((Assumptions!$C$10*$C$8)*IF((AI$18=(Assumptions!$C$7+$C$9)),SUM(C70:AB70),IF((AI$18>(Assumptions!$C$7+$C$9)),AB70,0))) -> 0 | AJ77: =((Assumptions!$C$10*$C$8)*IF((AJ$18=(Assumptions!$C$7+$C$9)),SUM(C70:AC70),IF((AJ$18>(Assumptions!$C$7+$C$9)),AC70,0))) -> 0 | AK77: =((Assumptions!$C$10*$C$8)*IF((AK$18=(Assumptions!$C$7+$C$9)),SUM(C70:AD70),IF((AK$18>(Assumptions!$C$7+$C$9)),AD70,0))) -> 0 | AL77: =((Assumptions!$C$10*$C$8)*IF((AL$18=(Assumptions!$C$7+$C$9)),SUM(C70:AE70),IF((AL$18>(Assumptions!$C$7+$C$9)),AE70,0))) -> 0 | AN77: =SUM(C77:N77) -> 0 | AO77: =SUM(O77:Z77) -> 0.48 | AP77: =SUM(AA77:AL77) -> 0
A78: New annual contracts, Campus | B78: accts | C78: =((C76+C77)+C72) -> 0 | D78: =((D76+D77)+D72) -> 0 | E78: =((E76+E77)+E72) -> 0 | F78: =((F76+F77)+F72) -> 0 | G78: =((G76+G77)+G72) -> 0 | H78: =((H76+H77)+H72) -> 0 | I78: =((I76+I77)+I72) -> 0 | J78: =((J76+J77)+J72) -> 0 | ... AL78: =((AL76+AL77)+AL72) -> 0 | AN78: =SUM(C78:N78) -> 0 | AO78: =SUM(O78:Z78) -> 0.48 | AP78: =SUM(AA78:AL78) -> 2.664
A79: Annual contract starts (new + renewals), Campus | B79: accts | C79: =(C78+(C45*0)) -> 0 | D79: =(D78+(D45*0)) -> 0 | E79: =(E78+(E45*0)) -> 0 | F79: =(F78+(F45*0)) -> 0 | G79: =(G78+(G45*0)) -> 0 | H79: =(H78+(H45*0)) -> 0 | I79: =(I78+(I45*0)) -> 0 | J79: =(J78+(J45*0)) -> 0 | ... N79: =(N78+(N45*0)) -> 0 | O79: =(O78+(O45*C79)) -> 0 | P79: =(P78+(P45*D79)) -> 0 | Q79: =(Q78+(Q45*E79)) -> 0.48 | R79: =(R78+(R45*F79)) -> 0 | S79: =(S78+(S45*G79)) -> 0 | T79: =(T78+(T45*H79)) -> 0 | U79: =(U78+(U45*I79)) -> 0 | V79: =(V78+(V45*J79)) -> 0 | ... AL79: =(AL78+(AL45*Z79)) -> 0 | AN79: =SUM(C79:N79) -> 0 | AO79: =SUM(O79:Z79) -> 0.48 | AP79: =SUM(AA79:AL79) -> 3.072
A80: Annual logos active, Campus | B80: accts | C80: =C79 -> 0 | D80: =SUM(C79:D79) -> 0 | E80: =SUM(C79:E79) -> 0 | F80: =SUM(C79:F79) -> 0 | G80: =SUM(C79:G79) -> 0 | H80: =SUM(C79:H79) -> 0 | I80: =SUM(C79:I79) -> 0 | J80: =SUM(C79:J79) -> 0 | K80: =SUM(C79:K79) -> 0 | L80: =SUM(C79:L79) -> 0 | M80: =SUM(C79:M79) -> 0 | N80: =SUM(C79:N79) -> 0 | O80: =SUM(D79:O79) -> 0 | P80: =SUM(E79:P79) -> 0 | Q80: =SUM(F79:Q79) -> 0.48 | R80: =SUM(G79:R79) -> 0.48 | S80: =SUM(H79:S79) -> 0.48 | T80: =SUM(I79:T79) -> 0.48 | U80: =SUM(J79:U79) -> 0.48 | ... AL80: =SUM(AA79:AL79) -> 3.072 | AN80: =N80 -> 0 | AO80: =Z80 -> 0.48 | AP80: =AL80 -> 3.072
A81: Net ACV per new contract, Campus | B81: $ | C81: =((Assumptions!$D$121*(1-Assumptions!$C$29))*$C$10) -> 71060 | D81: =((Assumptions!$D$121*(1-Assumptions!$C$29))*$C$10) -> 71060 | E81: =((Assumptions!$D$121*(1-Assumptions!$C$29))*$C$10) -> 71060 | F81: =((Assumptions!$D$121*(1-Assumptions!$C$29))*$C$10) -> 71060 | G81: =((Assumptions!$D$121*(1-Assumptions!$C$29))*$C$10) -> 71060 | H81: =((Assumptions!$D$121*(1-Assumptions!$C$29))*$C$10) -> 71060 | I81: =((Assumptions!$D$121*(1-Assumptions!$C$29))*$C$10) -> 71060 | J81: =((Assumptions!$D$121*(1-Assumptions!$C$29))*$C$10) -> 71060 | ... AL81: =((Assumptions!$D$121*(1-Assumptions!$C$29))*$C$10) -> 71060
A82: Contract value started or renewed, Campus | B82: $ | C82: =((C78*C81)+((C45*(1+Assumptions!$C$31))*0)) -> 0 | D82: =((D78*D81)+((D45*(1+Assumptions!$C$31))*0)) -> 0 | E82: =((E78*E81)+((E45*(1+Assumptions!$C$31))*0)) -> 0 | F82: =((F78*F81)+((F45*(1+Assumptions!$C$31))*0)) -> 0 | G82: =((G78*G81)+((G45*(1+Assumptions!$C$31))*0)) -> 0 | H82: =((H78*H81)+((H45*(1+Assumptions!$C$31))*0)) -> 0 | I82: =((I78*I81)+((I45*(1+Assumptions!$C$31))*0)) -> 0 | J82: =((J78*J81)+((J45*(1+Assumptions!$C$31))*0)) -> 0 | ... N82: =((N78*N81)+((N45*(1+Assumptions!$C$31))*0)) -> 0 | O82: =((O78*O81)+((O45*(1+Assumptions!$C$31))*C82)) -> 0 | P82: =((P78*P81)+((P45*(1+Assumptions!$C$31))*D82)) -> 0 | Q82: =((Q78*Q81)+((Q45*(1+Assumptions!$C$31))*E82)) -> 34108.8 | R82: =((R78*R81)+((R45*(1+Assumptions!$C$31))*F82)) -> 0 | S82: =((S78*S81)+((S45*(1+Assumptions!$C$31))*G82)) -> 0 | T82: =((T78*T81)+((T45*(1+Assumptions!$C$31))*H82)) -> 0 | U82: =((U78*U81)+((U45*(1+Assumptions!$C$31))*I82)) -> 0 | V82: =((V78*V81)+((V45*(1+Assumptions!$C$31))*J82)) -> 0 | ... AL82: =((AL78*AL81)+((AL45*(1+Assumptions!$C$31))*Z82)) -> 0 | AN82: =SUM(C82:N82) -> 0 | AO82: =SUM(O82:Z82) -> 34108.8 | AP82: =SUM(AA82:AL82) -> 221195.57
A83: Pilot credit given at conversion, Campus | B83: $ | C83: =(Assumptions!$D$126*C76) -> 0 | D83: =(Assumptions!$D$126*D76) -> 0 | E83: =(Assumptions!$D$126*E76) -> 0 | F83: =(Assumptions!$D$126*F76) -> 0 | G83: =(Assumptions!$D$126*G76) -> 0 | H83: =(Assumptions!$D$126*H76) -> 0 | I83: =(Assumptions!$D$126*I76) -> 0 | J83: =(Assumptions!$D$126*J76) -> 0 | ... AL83: =(Assumptions!$D$126*AL76) -> 0 | AN83: =SUM(C83:N83) -> 0 | AO83: =SUM(O83:Z83) -> 0 | AP83: =SUM(AA83:AL83) -> 12960
A84: Platform subscription revenue, Campus | B84: $ | C84: =((C82-C83)/12) -> 0 | D84: =((SUM(C82:D82)-SUM(C83:D83))/12) -> 0 | E84: =((SUM(C82:E82)-SUM(C83:E83))/12) -> 0 | F84: =((SUM(C82:F82)-SUM(C83:F83))/12) -> 0 | G84: =((SUM(C82:G82)-SUM(C83:G83))/12) -> 0 | H84: =((SUM(C82:H82)-SUM(C83:H83))/12) -> 0 | I84: =((SUM(C82:I82)-SUM(C83:I83))/12) -> 0 | J84: =((SUM(C82:J82)-SUM(C83:J83))/12) -> 0 | K84: =((SUM(C82:K82)-SUM(C83:K83))/12) -> 0 | L84: =((SUM(C82:L82)-SUM(C83:L83))/12) -> 0 | M84: =((SUM(C82:M82)-SUM(C83:M83))/12) -> 0 | N84: =((SUM(C82:N82)-SUM(C83:N83))/12) -> 0 | O84: =((SUM(D82:O82)-SUM(D83:O83))/12) -> 0 | P84: =((SUM(E82:P82)-SUM(E83:P83))/12) -> 0 | Q84: =((SUM(F82:Q82)-SUM(F83:Q83))/12) -> 2842.4 | R84: =((SUM(G82:R82)-SUM(G83:R83))/12) -> 2842.4 | S84: =((SUM(H82:S82)-SUM(H83:S83))/12) -> 2842.4 | T84: =((SUM(I82:T82)-SUM(I83:T83))/12) -> 2842.4 | U84: =((SUM(J82:U82)-SUM(J83:U83))/12) -> 2842.4 | ... AL84: =((SUM(AA82:AL82)-SUM(AA83:AL83))/12) -> 17352.964 | AN84: =SUM(C84:N84) -> 0 | AO84: =SUM(O84:Z84) -> 28424 | AP84: =SUM(AA84:AL84) -> 126487.64
A85: Platform billings, Campus | B85: $ | C85: =(C82-C83) -> 0 | D85: =(D82-D83) -> 0 | E85: =(E82-E83) -> 0 | F85: =(F82-F83) -> 0 | G85: =(G82-G83) -> 0 | H85: =(H82-H83) -> 0 | I85: =(I82-I83) -> 0 | J85: =(J82-J83) -> 0 | ... AL85: =(AL82-AL83) -> 0 | AN85: =SUM(C85:N85) -> 0 | AO85: =SUM(O85:Z85) -> 34108.8 | AP85: =SUM(AA85:AL85) -> 208235.57
A86: Pilot software revenue, Campus | B86: $ | C86: =(((Assumptions!$D$122*$C$10)/6)*C75) -> 0 | D86: =(((Assumptions!$D$122*$C$10)/6)*D75) -> 0 | E86: =(((Assumptions!$D$122*$C$10)/6)*E75) -> 0 | F86: =(((Assumptions!$D$122*$C$10)/6)*F75) -> 0 | G86: =(((Assumptions!$D$122*$C$10)/6)*G75) -> 0 | H86: =(((Assumptions!$D$122*$C$10)/6)*H75) -> 0 | I86: =(((Assumptions!$D$122*$C$10)/6)*I75) -> 0 | J86: =(((Assumptions!$D$122*$C$10)/6)*J75) -> 0 | ... AL86: =(((Assumptions!$D$122*$C$10)/6)*AL75) -> 11400 | AN86: =SUM(C86:N86) -> 0 | AO86: =SUM(O86:Z86) -> 31350 | AP86: =SUM(AA86:AL86) -> 99750
A87: Pilot billings, Campus | B87: $ | C87: =((Assumptions!$D$122*$C$10)*C69) -> 0 | D87: =((Assumptions!$D$122*$C$10)*D69) -> 0 | E87: =((Assumptions!$D$122*$C$10)*E69) -> 0 | F87: =((Assumptions!$D$122*$C$10)*F69) -> 0 | G87: =((Assumptions!$D$122*$C$10)*G69) -> 0 | H87: =((Assumptions!$D$122*$C$10)*H69) -> 0 | I87: =((Assumptions!$D$122*$C$10)*I69) -> 0 | J87: =((Assumptions!$D$122*$C$10)*J69) -> 0 | ... AL87: =((Assumptions!$D$122*$C$10)*AL69) -> 34200 | AN87: =SUM(C87:N87) -> 0 | AO87: =SUM(O87:Z87) -> 51300 | AP87: =SUM(AA87:AL87) -> 119700
A88: Services fee per new billable institution, Campus | B88: $ | C88: =((Assumptions!$D$123*$C$10)+(Assumptions!$C$34*Assumptions!$C$35)) -> 44000 | D88: =((Assumptions!$D$123*$C$10)+(Assumptions!$C$34*Assumptions!$C$35)) -> 44000 | E88: =((Assumptions!$D$123*$C$10)+(Assumptions!$C$34*Assumptions!$C$35)) -> 44000 | F88: =((Assumptions!$D$123*$C$10)+(Assumptions!$C$34*Assumptions!$C$35)) -> 44000 | G88: =((Assumptions!$D$123*$C$10)+(Assumptions!$C$34*Assumptions!$C$35)) -> 44000 | H88: =((Assumptions!$D$123*$C$10)+(Assumptions!$C$34*Assumptions!$C$35)) -> 44000 | I88: =((Assumptions!$D$123*$C$10)+(Assumptions!$C$34*Assumptions!$C$35)) -> 44000 | J88: =((Assumptions!$D$123*$C$10)+(Assumptions!$C$34*Assumptions!$C$35)) -> 44000 | ... AL88: =((Assumptions!$D$123*$C$10)+(Assumptions!$C$34*Assumptions!$C$35)) -> 44000
A89: Implementation services revenue, Campus | B89: $ | C89: =((C88/3)*C73) -> 0 | D89: =((D88/3)*SUM(C73:D73)) -> 0 | E89: =((E88/3)*SUM(C73:E73)) -> 0 | F89: =((F88/3)*SUM(D73:F73)) -> 0 | G89: =((G88/3)*SUM(E73:G73)) -> 0 | H89: =((H88/3)*SUM(F73:H73)) -> 0 | I89: =((I88/3)*SUM(G73:I73)) -> 0 | J89: =((J88/3)*SUM(H73:J73)) -> 0 | K89: =((K88/3)*SUM(I73:K73)) -> 0 | L89: =((L88/3)*SUM(J73:L73)) -> 0 | ... AL89: =((AL88/3)*SUM(AJ73:AL73)) -> 26400 | AN89: =SUM(C89:N89) -> 0 | AO89: =SUM(O89:Z89) -> 61600 | AP89: =SUM(AA89:AL89) -> 246400
A90: Implementation billings, Campus | B90: $ | C90: =(C88*C73) -> 0 | D90: =(D88*D73) -> 0 | E90: =(E88*E73) -> 0 | F90: =(F88*F73) -> 0 | G90: =(G88*G73) -> 0 | H90: =(H88*H73) -> 0 | I90: =(I88*I73) -> 0 | J90: =(J88*J73) -> 0 | ... AL90: =(AL88*AL73) -> 52800 | AN90: =SUM(C90:N90) -> 0 | AO90: =SUM(O90:Z90) -> 79200 | AP90: =SUM(AA90:AL90) -> 264000
A91: Implementation hours demanded, Campus | B91: hours | C91: =((C70*Assumptions!$D$124)+(C73*(Assumptions!$D$124+(Assumptions!$C$34*Assumptions!$C$36)))) -> 0 | D91: =((D70*Assumptions!$D$124)+(D73*(Assumptions!$D$124+(Assumptions!$C$34*Assumptions!$C$36)))) -> 0 | E91: =((E70*Assumptions!$D$124)+(E73*(Assumptions!$D$124+(Assumptions!$C$34*Assumptions!$C$36)))) -> 0 | F91: =((F70*Assumptions!$D$124)+(F73*(Assumptions!$D$124+(Assumptions!$C$34*Assumptions!$C$36)))) -> 0 | G91: =((G70*Assumptions!$D$124)+(G73*(Assumptions!$D$124+(Assumptions!$C$34*Assumptions!$C$36)))) -> 0 | H91: =((H70*Assumptions!$D$124)+(H73*(Assumptions!$D$124+(Assumptions!$C$34*Assumptions!$C$36)))) -> 0 | I91: =((I70*Assumptions!$D$124)+(I73*(Assumptions!$D$124+(Assumptions!$C$34*Assumptions!$C$36)))) -> 0 | J91: =((J70*Assumptions!$D$124)+(J73*(Assumptions!$D$124+(Assumptions!$C$34*Assumptions!$C$36)))) -> 330 | ... AL91: =((AL70*Assumptions!$D$124)+(AL73*(Assumptions!$D$124+(Assumptions!$C$34*Assumptions!$C$36)))) -> 448.8 | AN91: =SUM(C91:N91) -> 330 | AO91: =SUM(O91:Z91) -> 673.2 | AP91: =SUM(AA91:AL91) -> 2244
A92: Paid pilot starts, System | B92: accts | C92: =((IF(OR((C$18-(Assumptions!$C$9-1)-$C$9)<1,(C$18-(Assumptions!$C$9-1)-$C$9)>36),0,INDEX(Schedules!$C$7:$AL$7,(C$18-(Assumptions!$C$9-1)-$C$9)))*$C$7)*C44) -> 0 | D92: =((IF(OR((D$18-(Assumptions!$C$9-1)-$C$9)<1,(D$18-(Assumptions!$C$9-1)-$C$9)>36),0,INDEX(Schedules!$C$7:$AL$7,(D$18-(Assumptions!$C$9-1)-$C$9)))*$C$7)*D44) -> 0 | E92: =((IF(OR((E$18-(Assumptions!$C$9-1)-$C$9)<1,(E$18-(Assumptions!$C$9-1)-$C$9)>36),0,INDEX(Schedules!$C$7:$AL$7,(E$18-(Assumptions!$C$9-1)-$C$9)))*$C$7)*E44) -> 0 | F92: =((IF(OR((F$18-(Assumptions!$C$9-1)-$C$9)<1,(F$18-(Assumptions!$C$9-1)-$C$9)>36),0,INDEX(Schedules!$C$7:$AL$7,(F$18-(Assumptions!$C$9-1)-$C$9)))*$C$7)*F44) -> 0 | G92: =((IF(OR((G$18-(Assumptions!$C$9-1)-$C$9)<1,(G$18-(Assumptions!$C$9-1)-$C$9)>36),0,INDEX(Schedules!$C$7:$AL$7,(G$18-(Assumptions!$C$9-1)-$C$9)))*$C$7)*G44) -> 0 | H92: =((IF(OR((H$18-(Assumptions!$C$9-1)-$C$9)<1,(H$18-(Assumptions!$C$9-1)-$C$9)>36),0,INDEX(Schedules!$C$7:$AL$7,(H$18-(Assumptions!$C$9-1)-$C$9)))*$C$7)*H44) -> 0 | I92: =((IF(OR((I$18-(Assumptions!$C$9-1)-$C$9)<1,(I$18-(Assumptions!$C$9-1)-$C$9)>36),0,INDEX(Schedules!$C$7:$AL$7,(I$18-(Assumptions!$C$9-1)-$C$9)))*$C$7)*I44) -> 0 | J92: =((IF(OR((J$18-(Assumptions!$C$9-1)-$C$9)<1,(J$18-(Assumptions!$C$9-1)-$C$9)>36),0,INDEX(Schedules!$C$7:$AL$7,(J$18-(Assumptions!$C$9-1)-$C$9)))*$C$7)*J44) -> 0 | ... AL92: =((IF(OR((AL$18-(Assumptions!$C$9-1)-$C$9)<1,(AL$18-(Assumptions!$C$9-1)-$C$9)>36),0,INDEX(Schedules!$C$7:$AL$7,(AL$18-(Assumptions!$C$9-1)-$C$9)))*$C$7)*AL44) -> 0 | AN92: =SUM(C92:N92) -> 0 | AO92: =SUM(O92:Z92) -> 0 | AP92: =SUM(AA92:AL92) -> 0.6
A93: Unpaid design-partner pilot starts, System | B93: accts | C93: =INDEX(Schedules!$C$13:$AL$13,C$18) -> 0 | D93: =INDEX(Schedules!$C$13:$AL$13,D$18) -> 0 | E93: =INDEX(Schedules!$C$13:$AL$13,E$18) -> 0 | F93: =INDEX(Schedules!$C$13:$AL$13,F$18) -> 0 | G93: =INDEX(Schedules!$C$13:$AL$13,G$18) -> 0 | H93: =INDEX(Schedules!$C$13:$AL$13,H$18) -> 0 | I93: =INDEX(Schedules!$C$13:$AL$13,I$18) -> 0 | J93: =INDEX(Schedules!$C$13:$AL$13,J$18) -> 0 | ... AL93: =INDEX(Schedules!$C$13:$AL$13,AL$18) -> 0 | AN93: =SUM(C93:N93) -> 0 | AO93: =SUM(O93:Z93) -> 0 | AP93: =SUM(AA93:AL93) -> 0
A94: All pilot starts, System | B94: accts | C94: =(C92+C93) -> 0 | D94: =(D92+D93) -> 0 | E94: =(E92+E93) -> 0 | F94: =(F92+F93) -> 0 | G94: =(G92+G93) -> 0 | H94: =(H92+H93) -> 0 | I94: =(I92+I93) -> 0 | J94: =(J92+J93) -> 0 | ... AL94: =(AL92+AL93) -> 0 | AN94: =SUM(C94:N94) -> 0 | AO94: =SUM(O94:Z94) -> 0 | AP94: =SUM(AA94:AL94) -> 0.6
A95: Direct annual starts, System | B95: accts | C95: =((IF(OR((C$18-(Assumptions!$C$9-1)-$C$9)<1,(C$18-(Assumptions!$C$9-1)-$C$9)>36),0,INDEX(Schedules!$C$10:$AL$10,(C$18-(Assumptions!$C$9-1)-$C$9)))*$C$7)*C44) -> 0 | D95: =((IF(OR((D$18-(Assumptions!$C$9-1)-$C$9)<1,(D$18-(Assumptions!$C$9-1)-$C$9)>36),0,INDEX(Schedules!$C$10:$AL$10,(D$18-(Assumptions!$C$9-1)-$C$9)))*$C$7)*D44) -> 0 | E95: =((IF(OR((E$18-(Assumptions!$C$9-1)-$C$9)<1,(E$18-(Assumptions!$C$9-1)-$C$9)>36),0,INDEX(Schedules!$C$10:$AL$10,(E$18-(Assumptions!$C$9-1)-$C$9)))*$C$7)*E44) -> 0 | F95: =((IF(OR((F$18-(Assumptions!$C$9-1)-$C$9)<1,(F$18-(Assumptions!$C$9-1)-$C$9)>36),0,INDEX(Schedules!$C$10:$AL$10,(F$18-(Assumptions!$C$9-1)-$C$9)))*$C$7)*F44) -> 0 | G95: =((IF(OR((G$18-(Assumptions!$C$9-1)-$C$9)<1,(G$18-(Assumptions!$C$9-1)-$C$9)>36),0,INDEX(Schedules!$C$10:$AL$10,(G$18-(Assumptions!$C$9-1)-$C$9)))*$C$7)*G44) -> 0 | H95: =((IF(OR((H$18-(Assumptions!$C$9-1)-$C$9)<1,(H$18-(Assumptions!$C$9-1)-$C$9)>36),0,INDEX(Schedules!$C$10:$AL$10,(H$18-(Assumptions!$C$9-1)-$C$9)))*$C$7)*H44) -> 0 | I95: =((IF(OR((I$18-(Assumptions!$C$9-1)-$C$9)<1,(I$18-(Assumptions!$C$9-1)-$C$9)>36),0,INDEX(Schedules!$C$10:$AL$10,(I$18-(Assumptions!$C$9-1)-$C$9)))*$C$7)*I44) -> 0 | J95: =((IF(OR((J$18-(Assumptions!$C$9-1)-$C$9)<1,(J$18-(Assumptions!$C$9-1)-$C$9)>36),0,INDEX(Schedules!$C$10:$AL$10,(J$18-(Assumptions!$C$9-1)-$C$9)))*$C$7)*J44) -> 0 | ... AL95: =((IF(OR((AL$18-(Assumptions!$C$9-1)-$C$9)<1,(AL$18-(Assumptions!$C$9-1)-$C$9)>36),0,INDEX(Schedules!$C$10:$AL$10,(AL$18-(Assumptions!$C$9-1)-$C$9)))*$C$7)*AL44) -> 0 | AN95: =SUM(C95:N95) -> 0 | AO95: =SUM(O95:Z95) -> 0 | AP95: =SUM(AA95:AL95) -> 0
A96: New billable institutions (paid pilot or direct), System | B96: accts | C96: =(C92+C95) -> 0 | D96: =(D92+D95) -> 0 | E96: =(E92+E95) -> 0 | F96: =(F92+F95) -> 0 | G96: =(G92+G95) -> 0 | H96: =(H92+H95) -> 0 | I96: =(I92+I95) -> 0 | J96: =(J92+J95) -> 0 | ... AL96: =(AL92+AL95) -> 0 | AN96: =SUM(C96:N96) -> 0 | AO96: =SUM(O96:Z96) -> 0 | AP96: =SUM(AA96:AL96) -> 0.6
A97: Pilots running (paid + unpaid), System | B97: accts | C97: =C94 -> 0 | D97: =SUM(C94:D94) -> 0 | E97: =SUM(C94:E94) -> 0 | F97: =SUM(C94:F94) -> 0 | G97: =SUM(C94:G94) -> 0 | H97: =SUM(C94:H94) -> 0 | I97: =SUM(D94:I94) -> 0 | J97: =SUM(E94:J94) -> 0 | K97: =SUM(F94:K94) -> 0 | L97: =SUM(G94:L94) -> 0 | M97: =SUM(H94:M94) -> 0 | N97: =SUM(I94:N94) -> 0 | O97: =SUM(J94:O94) -> 0 | ... AL97: =SUM(AG94:AL94) -> 0.6 | AN97: =N97 -> 0 | AO97: =Z97 -> 0 | AP97: =AL97 -> 0.6
A98: Paid pilots running, System | B98: accts | C98: =C92 -> 0 | D98: =SUM(C92:D92) -> 0 | E98: =SUM(C92:E92) -> 0 | F98: =SUM(C92:F92) -> 0 | G98: =SUM(C92:G92) -> 0 | H98: =SUM(C92:H92) -> 0 | I98: =SUM(D92:I92) -> 0 | J98: =SUM(E92:J92) -> 0 | K98: =SUM(F92:K92) -> 0 | L98: =SUM(G92:L92) -> 0 | M98: =SUM(H92:M92) -> 0 | N98: =SUM(I92:N92) -> 0 | O98: =SUM(J92:O92) -> 0 | ... AL98: =SUM(AG92:AL92) -> 0.6 | AN98: =N98 -> 0 | AO98: =Z98 -> 0 | AP98: =AL98 -> 0.6
A99: Paid pilots converting to annual, System | B99: accts | C99: =((Assumptions!$E$127*$C$8)*0) -> 0 | D99: =((Assumptions!$E$127*$C$8)*0) -> 0 | E99: =((Assumptions!$E$127*$C$8)*0) -> 0 | F99: =((Assumptions!$E$127*$C$8)*0) -> 0 | G99: =((Assumptions!$E$127*$C$8)*0) -> 0 | H99: =((Assumptions!$E$127*$C$8)*0) -> 0 | I99: =((Assumptions!$E$127*$C$8)*0) -> 0 | J99: =((Assumptions!$E$127*$C$8)*C92) -> 0 | K99: =((Assumptions!$E$127*$C$8)*D92) -> 0 | L99: =((Assumptions!$E$127*$C$8)*E92) -> 0 | M99: =((Assumptions!$E$127*$C$8)*F92) -> 0 | N99: =((Assumptions!$E$127*$C$8)*G92) -> 0 | O99: =((Assumptions!$E$127*$C$8)*H92) -> 0 | P99: =((Assumptions!$E$127*$C$8)*I92) -> 0 | Q99: =((Assumptions!$E$127*$C$8)*J92) -> 0 | ... AL99: =((Assumptions!$E$127*$C$8)*AE92) -> 0 | AN99: =SUM(C99:N99) -> 0 | AO99: =SUM(O99:Z99) -> 0 | AP99: =SUM(AA99:AL99) -> 0
A100: Design partners converting to annual, System | B100: accts | C100: =((Assumptions!$C$10*$C$8)*IF((C$18=(Assumptions!$C$9+$C$9)),0,IF((C$18>(Assumptions!$C$9+$C$9)),0,0))) -> 0 | D100: =((Assumptions!$C$10*$C$8)*IF((D$18=(Assumptions!$C$9+$C$9)),0,IF((D$18>(Assumptions!$C$9+$C$9)),0,0))) -> 0 | E100: =((Assumptions!$C$10*$C$8)*IF((E$18=(Assumptions!$C$9+$C$9)),0,IF((E$18>(Assumptions!$C$9+$C$9)),0,0))) -> 0 | F100: =((Assumptions!$C$10*$C$8)*IF((F$18=(Assumptions!$C$9+$C$9)),0,IF((F$18>(Assumptions!$C$9+$C$9)),0,0))) -> 0 | G100: =((Assumptions!$C$10*$C$8)*IF((G$18=(Assumptions!$C$9+$C$9)),0,IF((G$18>(Assumptions!$C$9+$C$9)),0,0))) -> 0 | H100: =((Assumptions!$C$10*$C$8)*IF((H$18=(Assumptions!$C$9+$C$9)),0,IF((H$18>(Assumptions!$C$9+$C$9)),0,0))) -> 0 | I100: =((Assumptions!$C$10*$C$8)*IF((I$18=(Assumptions!$C$9+$C$9)),0,IF((I$18>(Assumptions!$C$9+$C$9)),0,0))) -> 0 | J100: =((Assumptions!$C$10*$C$8)*IF((J$18=(Assumptions!$C$9+$C$9)),C93,IF((J$18>(Assumptions!$C$9+$C$9)),C93,0))) -> 0 | K100: =((Assumptions!$C$10*$C$8)*IF((K$18=(Assumptions!$C$9+$C$9)),SUM(C93:D93),IF((K$18>(Assumptions!$C$9+$C$9)),D93,0))) -> 0 | L100: =((Assumptions!$C$10*$C$8)*IF((L$18=(Assumptions!$C$9+$C$9)),SUM(C93:E93),IF((L$18>(Assumptions!$C$9+$C$9)),E93,0))) -> 0 | M100: =((Assumptions!$C$10*$C$8)*IF((M$18=(Assumptions!$C$9+$C$9)),SUM(C93:F93),IF((M$18>(Assumptions!$C$9+$C$9)),F93,0))) -> 0 | N100: =((Assumptions!$C$10*$C$8)*IF((N$18=(Assumptions!$C$9+$C$9)),SUM(C93:G93),IF((N$18>(Assumptions!$C$9+$C$9)),G93,0))) -> 0 | O100: =((Assumptions!$C$10*$C$8)*IF((O$18=(Assumptions!$C$9+$C$9)),SUM(C93:H93),IF((O$18>(Assumptions!$C$9+$C$9)),H93,0))) -> 0 | P100: =((Assumptions!$C$10*$C$8)*IF((P$18=(Assumptions!$C$9+$C$9)),SUM(C93:I93),IF((P$18>(Assumptions!$C$9+$C$9)),I93,0))) -> 0 | Q100: =((Assumptions!$C$10*$C$8)*IF((Q$18=(Assumptions!$C$9+$C$9)),SUM(C93:J93),IF((Q$18>(Assumptions!$C$9+$C$9)),J93,0))) -> 0 | R100: =((Assumptions!$C$10*$C$8)*IF((R$18=(Assumptions!$C$9+$C$9)),SUM(C93:K93),IF((R$18>(Assumptions!$C$9+$C$9)),K93,0))) -> 0 | S100: =((Assumptions!$C$10*$C$8)*IF((S$18=(Assumptions!$C$9+$C$9)),SUM(C93:L93),IF((S$18>(Assumptions!$C$9+$C$9)),L93,0))) -> 0 | T100: =((Assumptions!$C$10*$C$8)*IF((T$18=(Assumptions!$C$9+$C$9)),SUM(C93:M93),IF((T$18>(Assumptions!$C$9+$C$9)),M93,0))) -> 0 | U100: =((Assumptions!$C$10*$C$8)*IF((U$18=(Assumptions!$C$9+$C$9)),SUM(C93:N93),IF((U$18>(Assumptions!$C$9+$C$9)),N93,0))) -> 0 | V100: =((Assumptions!$C$10*$C$8)*IF((V$18=(Assumptions!$C$9+$C$9)),SUM(C93:O93),IF((V$18>(Assumptions!$C$9+$C$9)),O93,0))) -> 0 | W100: =((Assumptions!$C$10*$C$8)*IF((W$18=(Assumptions!$C$9+$C$9)),SUM(C93:P93),IF((W$18>(Assumptions!$C$9+$C$9)),P93,0))) -> 0 | X100: =((Assumptions!$C$10*$C$8)*IF((X$18=(Assumptions!$C$9+$C$9)),SUM(C93:Q93),IF((X$18>(Assumptions!$C$9+$C$9)),Q93,0))) -> 0 | Y100: =((Assumptions!$C$10*$C$8)*IF((Y$18=(Assumptions!$C$9+$C$9)),SUM(C93:R93),IF((Y$18>(Assumptions!$C$9+$C$9)),R93,0))) -> 0 | Z100: =((Assumptions!$C$10*$C$8)*IF((Z$18=(Assumptions!$C$9+$C$9)),SUM(C93:S93),IF((Z$18>(Assumptions!$C$9+$C$9)),S93,0))) -> 0 | AA100: =((Assumptions!$C$10*$C$8)*IF((AA$18=(Assumptions!$C$9+$C$9)),SUM(C93:T93),IF((AA$18>(Assumptions!$C$9+$C$9)),T93,0))) -> 0 | AB100: =((Assumptions!$C$10*$C$8)*IF((AB$18=(Assumptions!$C$9+$C$9)),SUM(C93:U93),IF((AB$18>(Assumptions!$C$9+$C$9)),U93,0))) -> 0 | AC100: =((Assumptions!$C$10*$C$8)*IF((AC$18=(Assumptions!$C$9+$C$9)),SUM(C93:V93),IF((AC$18>(Assumptions!$C$9+$C$9)),V93,0))) -> 0 | AD100: =((Assumptions!$C$10*$C$8)*IF((AD$18=(Assumptions!$C$9+$C$9)),SUM(C93:W93),IF((AD$18>(Assumptions!$C$9+$C$9)),W93,0))) -> 0 | AE100: =((Assumptions!$C$10*$C$8)*IF((AE$18=(Assumptions!$C$9+$C$9)),SUM(C93:X93),IF((AE$18>(Assumptions!$C$9+$C$9)),X93,0))) -> 0 | AF100: =((Assumptions!$C$10*$C$8)*IF((AF$18=(Assumptions!$C$9+$C$9)),SUM(C93:Y93),IF((AF$18>(Assumptions!$C$9+$C$9)),Y93,0))) -> 0 | AG100: =((Assumptions!$C$10*$C$8)*IF((AG$18=(Assumptions!$C$9+$C$9)),SUM(C93:Z93),IF((AG$18>(Assumptions!$C$9+$C$9)),Z93,0))) -> 0 | AH100: =((Assumptions!$C$10*$C$8)*IF((AH$18=(Assumptions!$C$9+$C$9)),SUM(C93:AA93),IF((AH$18>(Assumptions!$C$9+$C$9)),AA93,0))) -> 0 | AI100: =((Assumptions!$C$10*$C$8)*IF((AI$18=(Assumptions!$C$9+$C$9)),SUM(C93:AB93),IF((AI$18>(Assumptions!$C$9+$C$9)),AB93,0))) -> 0 | AJ100: =((Assumptions!$C$10*$C$8)*IF((AJ$18=(Assumptions!$C$9+$C$9)),SUM(C93:AC93),IF((AJ$18>(Assumptions!$C$9+$C$9)),AC93,0))) -> 0 | AK100: =((Assumptions!$C$10*$C$8)*IF((AK$18=(Assumptions!$C$9+$C$9)),SUM(C93:AD93),IF((AK$18>(Assumptions!$C$9+$C$9)),AD93,0))) -> 0 | AL100: =((Assumptions!$C$10*$C$8)*IF((AL$18=(Assumptions!$C$9+$C$9)),SUM(C93:AE93),IF((AL$18>(Assumptions!$C$9+$C$9)),AE93,0))) -> 0 | AN100: =SUM(C100:N100) -> 0 | AO100: =SUM(O100:Z100) -> 0 | AP100: =SUM(AA100:AL100) -> 0
A101: New annual contracts, System | B101: accts | C101: =((C99+C100)+C95) -> 0 | D101: =((D99+D100)+D95) -> 0 | E101: =((E99+E100)+E95) -> 0 | F101: =((F99+F100)+F95) -> 0 | G101: =((G99+G100)+G95) -> 0 | H101: =((H99+H100)+H95) -> 0 | I101: =((I99+I100)+I95) -> 0 | J101: =((J99+J100)+J95) -> 0 | ... AL101: =((AL99+AL100)+AL95) -> 0 | AN101: =SUM(C101:N101) -> 0 | AO101: =SUM(O101:Z101) -> 0 | AP101: =SUM(AA101:AL101) -> 0
A102: Annual contract starts (new + renewals), System | B102: accts | C102: =(C101+(C45*0)) -> 0 | D102: =(D101+(D45*0)) -> 0 | E102: =(E101+(E45*0)) -> 0 | F102: =(F101+(F45*0)) -> 0 | G102: =(G101+(G45*0)) -> 0 | H102: =(H101+(H45*0)) -> 0 | I102: =(I101+(I45*0)) -> 0 | J102: =(J101+(J45*0)) -> 0 | ... N102: =(N101+(N45*0)) -> 0 | O102: =(O101+(O45*C102)) -> 0 | P102: =(P101+(P45*D102)) -> 0 | Q102: =(Q101+(Q45*E102)) -> 0 | R102: =(R101+(R45*F102)) -> 0 | S102: =(S101+(S45*G102)) -> 0 | T102: =(T101+(T45*H102)) -> 0 | U102: =(U101+(U45*I102)) -> 0 | V102: =(V101+(V45*J102)) -> 0 | ... AL102: =(AL101+(AL45*Z102)) -> 0 | AN102: =SUM(C102:N102) -> 0 | AO102: =SUM(O102:Z102) -> 0 | AP102: =SUM(AA102:AL102) -> 0
...

Sheet Base
A1: Scenario 2: Base
A2: All cells are formulas on Assumptions, Headcount, Schedules and the scenario parameters below.
A3: Scenario parameters (linked to Scenarios sheet)
A4: Organic student acquisition multiplier | B4: x | C4: =Scenarios!D4 -> 1
A5: Free-to-paid conversion multiplier | B5: x | C5: =Scenarios!D5 -> 1
A6: Churn multiplier (students and institutions) | B6: x | C6: =Scenarios!D6 -> 1
A7: Pilot and direct-deal volume multiplier | B7: x | C7: =Scenarios!D7 -> 1
A8: Pilot-to-annual conversion multiplier | B8: x | C8: =Scenarios!D8 -> 1
A9: Institutional gates slip by (months) | B9: months | C9: =Scenarios!D9 -> 0
A10: Institutional price realization multiplier | B10: x | C10: =Scenarios!D10 -> 1
A11: Paid acquisition cost multiplier | B11: x | C11: =Scenarios!D11 -> 1
A12: AI unit cost multiplier (price or model-mix shift) | B12: x | C12: =Scenarios!D12 -> 1
A13: AI usage multiplier (requests per user) | B13: x | C13: =Scenarios!D13 -> 1
A14: Incident switch (1 = on) | B14: 0/1 | C14: =Scenarios!D14 -> 0
A15: Delay for gated hires (months) | B15: months | C15: =Scenarios!D15 -> 0
A16: Full-scope staffing switch (1 = include the CTO-pack staffing roles) | B16: 0/1 | C16: =Scenarios!D16 -> 0
A18: Month | C18: 1 | D18: 2 | E18: 3 | F18: 4 | G18: 5 | H18: 6 | I18: 7 | J18: 8 | K18: 9 | L18: 10 | M18: 11 | N18: 12 | O18: 13 | P18: 14 | Q18: 15 | R18: 16 | S18: 17 | T18: 18 | U18: 19 | V18: 20 | W18: 21 | X18: 22 | Y18: 23 | Z18: 24 | AA18: 25 | AB18: 26 | AC18: 27 | AD18: 28 | AE18: 29 | AF18: 30 | AG18: 31 | AH18: 32 | AI18: 33 | AJ18: 34 | AK18: 35 | AL18: 36 | AN18: Year 1 | AO18: Year 2 | AP18: Year 3
A19: Calendar | C19: Jan-27 | D19: Feb-27 | E19: Mar-27 | F19: Apr-27 | G19: May-27 | H19: Jun-27 | I19: Jul-27 | J19: Aug-27 | K19: Sep-27 | L19: Oct-27 | M19: Nov-27 | N19: Dec-27 | O19: Jan-28 | P19: Feb-28 | Q19: Mar-28 | R19: Apr-28 | S19: May-28 | T19: Jun-28 | U19: Jul-28 | V19: Aug-28 | W19: Sep-28 | X19: Oct-28 | Y19: Nov-28 | Z19: Dec-28 | AA19: Jan-29 | AB19: Feb-29 | AC19: Mar-29 | AD19: Apr-29 | AE19: May-29 | AF19: Jun-29 | AG19: Jul-29 | AH19: Aug-29 | AI19: Sep-29 | AJ19: Oct-29 | AK19: Nov-29 | AL19: Dec-29 | AN19: 2027 | AO19: 2028 | AP19: 2029
A20: Year | C20: =INT((C18-1)/12)+1 -> 1 | D20: =INT((D18-1)/12)+1 -> 1 | E20: =INT((E18-1)/12)+1 -> 1 | F20: =INT((F18-1)/12)+1 -> 1 | G20: =INT((G18-1)/12)+1 -> 1 | H20: =INT((H18-1)/12)+1 -> 1 | I20: =INT((I18-1)/12)+1 -> 1 | J20: =INT((J18-1)/12)+1 -> 1 | ... AL20: =INT((AL18-1)/12)+1 -> 3
A21: Month of year | C21: =MOD(C18-1,12)+1 -> 1 | D21: =MOD(D18-1,12)+1 -> 2 | E21: =MOD(E18-1,12)+1 -> 3 | F21: =MOD(F18-1,12)+1 -> 4 | G21: =MOD(G18-1,12)+1 -> 5 | H21: =MOD(H18-1,12)+1 -> 6 | I21: =MOD(I18-1,12)+1 -> 7 | J21: =MOD(J18-1,12)+1 -> 8 | ... AL21: =MOD(AL18-1,12)+1 -> 12
A23: Student subscription: funnel and subscribers
A24: Organic signup trend (pre-seasonality) | B24: users | C24: =IF((C$18=1),Assumptions!$C$16,(0*(1+Assumptions!$C$133))) -> 1200 | D24: =IF((D$18=1),Assumptions!$C$16,(C24*(1+Assumptions!$C$133))) -> 1272 | E24: =IF((E$18=1),Assumptions!$C$16,(D24*(1+Assumptions!$C$133))) -> 1348.32 | F24: =IF((F$18=1),Assumptions!$C$16,(E24*(1+Assumptions!$C$133))) -> 1429.2192 | G24: =IF((G$18=1),Assumptions!$C$16,(F24*(1+Assumptions!$C$133))) -> 1514.9724 | H24: =IF((H$18=1),Assumptions!$C$16,(G24*(1+Assumptions!$C$133))) -> 1605.8707 | I24: =IF((I$18=1),Assumptions!$C$16,(H24*(1+Assumptions!$C$133))) -> 1702.2229 | J24: =IF((J$18=1),Assumptions!$C$16,(I24*(1+Assumptions!$C$133))) -> 1804.3563 | K24: =IF((K$18=1),Assumptions!$C$16,(J24*(1+Assumptions!$C$133))) -> 1912.6177 | ... N24: =IF((N$18=1),Assumptions!$C$16,(M24*(1+Assumptions!$C$133))) -> 2277.9583 | O24: =IF((O$18=1),Assumptions!$C$16,(N24*(1+Assumptions!$D$133))) -> 2369.0766 | P24: =IF((P$18=1),Assumptions!$C$16,(O24*(1+Assumptions!$D$133))) -> 2463.8397 | Q24: =IF((Q$18=1),Assumptions!$C$16,(P24*(1+Assumptions!$D$133))) -> 2562.3933 | R24: =IF((R$18=1),Assumptions!$C$16,(Q24*(1+Assumptions!$D$133))) -> 2664.889 | S24: =IF((S$18=1),Assumptions!$C$16,(R24*(1+Assumptions!$D$133))) -> 2771.4845 | T24: =IF((T$18=1),Assumptions!$C$16,(S24*(1+Assumptions!$D$133))) -> 2882.3439 | U24: =IF((U$18=1),Assumptions!$C$16,(T24*(1+Assumptions!$D$133))) -> 2997.6377 | V24: =IF((V$18=1),Assumptions!$C$16,(U24*(1+Assumptions!$D$133))) -> 3117.5432 | ... Z24: =IF((Z$18=1),Assumptions!$C$16,(Y24*(1+Assumptions!$D$133))) -> 3647.0846 | AA24: =IF((AA$18=1),Assumptions!$C$16,(Z24*(1+Assumptions!$E$133))) -> 3738.2617 | AB24: =IF((AB$18=1),Assumptions!$C$16,(AA24*(1+Assumptions!$E$133))) -> 3831.7182 | AC24: =IF((AC$18=1),Assumptions!$C$16,(AB24*(1+Assumptions!$E$133))) -> 3927.5112 | AD24: =IF((AD$18=1),Assumptions!$C$16,(AC24*(1+Assumptions!$E$133))) -> 4025.699 | AE24: =IF((AE$18=1),Assumptions!$C$16,(AD24*(1+Assumptions!$E$133))) -> 4126.3415 | AF24: =IF((AF$18=1),Assumptions!$C$16,(AE24*(1+Assumptions!$E$133))) -> 4229.5 | AG24: =IF((AG$18=1),Assumptions!$C$16,(AF24*(1+Assumptions!$E$133))) -> 4335.2375 | AH24: =IF((AH$18=1),Assumptions!$C$16,(AG24*(1+Assumptions!$E$133))) -> 4443.6184 | ... AL24: =IF((AL$18=1),Assumptions!$C$16,(AK24*(1+Assumptions!$E$133))) -> 4904.9233
A25: Organic + campus-led free signups | B25: users | C25: =(((C24*INDEX(Assumptions!$C$167:$C$178,C$21))*$C$4)*IF((C$18<Assumptions!$C$5),Assumptions!$C$6,1)) -> 390 | D25: =(((D24*INDEX(Assumptions!$C$167:$C$178,D$21))*$C$4)*IF((D$18<Assumptions!$C$5),Assumptions!$C$6,1)) -> 349.8 | E25: =(((E24*INDEX(Assumptions!$C$167:$C$178,E$21))*$C$4)*IF((E$18<Assumptions!$C$5),Assumptions!$C$6,1)) -> 303.372 | F25: =(((F24*INDEX(Assumptions!$C$167:$C$178,F$21))*$C$4)*IF((F$18<Assumptions!$C$5),Assumptions!$C$6,1)) -> 285.84384 | G25: =(((G24*INDEX(Assumptions!$C$167:$C$178,G$21))*$C$4)*IF((G$18<Assumptions!$C$5),Assumptions!$C$6,1)) -> 227.24585 | H25: =(((H24*INDEX(Assumptions!$C$167:$C$178,H$21))*$C$4)*IF((H$18<Assumptions!$C$5),Assumptions!$C$6,1)) -> 200.73384 | I25: =(((I24*INDEX(Assumptions!$C$167:$C$178,I$21))*$C$4)*IF((I$18<Assumptions!$C$5),Assumptions!$C$6,1)) -> 297.88901 | J25: =(((J24*INDEX(Assumptions!$C$167:$C$178,J$21))*$C$4)*IF((J$18<Assumptions!$C$5),Assumptions!$C$6,1)) -> 721.74252 | ... AL25: =(((AL24*INDEX(Assumptions!$C$167:$C$178,AL$21))*$C$4)*IF((AL$18<Assumptions!$C$5),Assumptions!$C$6,1)) -> 3433.4463 | AN25: =SUM(C25:N25) -> 5077.0047 | AO25: =SUM(O25:Z25) -> 35672.826 | AP25: =SUM(AA25:AL25) -> 51639.079
A26: Paid-acquisition free signups | B26: users | C26: =IF((C$18>=Assumptions!$C$5),(Assumptions!$C$134/(Assumptions!$C$17*$C$11)),0) -> 0 | D26: =IF((D$18>=Assumptions!$C$5),(Assumptions!$C$134/(Assumptions!$C$17*$C$11)),0) -> 0 | E26: =IF((E$18>=Assumptions!$C$5),(Assumptions!$C$134/(Assumptions!$C$17*$C$11)),0) -> 0 | F26: =IF((F$18>=Assumptions!$C$5),(Assumptions!$C$134/(Assumptions!$C$17*$C$11)),0) -> 0 | G26: =IF((G$18>=Assumptions!$C$5),(Assumptions!$C$134/(Assumptions!$C$17*$C$11)),0) -> 0 | H26: =IF((H$18>=Assumptions!$C$5),(Assumptions!$C$134/(Assumptions!$C$17*$C$11)),0) -> 0 | I26: =IF((I$18>=Assumptions!$C$5),(Assumptions!$C$134/(Assumptions!$C$17*$C$11)),0) -> 0 | J26: =IF((J$18>=Assumptions!$C$5),(Assumptions!$C$134/(Assumptions!$C$17*$C$11)),0) -> 0 | ... N26: =IF((N$18>=Assumptions!$C$5),(Assumptions!$C$134/(Assumptions!$C$17*$C$11)),0) -> 0 | O26: =IF((O$18>=Assumptions!$C$5),(Assumptions!$D$134/(Assumptions!$C$17*$C$11)),0) -> 1000 | P26: =IF((P$18>=Assumptions!$C$5),(Assumptions!$D$134/(Assumptions!$C$17*$C$11)),0) -> 1000 | Q26: =IF((Q$18>=Assumptions!$C$5),(Assumptions!$D$134/(Assumptions!$C$17*$C$11)),0) -> 1000 | R26: =IF((R$18>=Assumptions!$C$5),(Assumptions!$D$134/(Assumptions!$C$17*$C$11)),0) -> 1000 | S26: =IF((S$18>=Assumptions!$C$5),(Assumptions!$D$134/(Assumptions!$C$17*$C$11)),0) -> 1000 | T26: =IF((T$18>=Assumptions!$C$5),(Assumptions!$D$134/(Assumptions!$C$17*$C$11)),0) -> 1000 | U26: =IF((U$18>=Assumptions!$C$5),(Assumptions!$D$134/(Assumptions!$C$17*$C$11)),0) -> 1000 | V26: =IF((V$18>=Assumptions!$C$5),(Assumptions!$D$134/(Assumptions!$C$17*$C$11)),0) -> 1000 | ... Z26: =IF((Z$18>=Assumptions!$C$5),(Assumptions!$D$134/(Assumptions!$C$17*$C$11)),0) -> 1000 | AA26: =IF((AA$18>=Assumptions!$C$5),(Assumptions!$E$134/(Assumptions!$C$17*$C$11)),0) -> 1666.6667 | AB26: =IF((AB$18>=Assumptions!$C$5),(Assumptions!$E$134/(Assumptions!$C$17*$C$11)),0) -> 1666.6667 | AC26: =IF((AC$18>=Assumptions!$C$5),(Assumptions!$E$134/(Assumptions!$C$17*$C$11)),0) -> 1666.6667 | AD26: =IF((AD$18>=Assumptions!$C$5),(Assumptions!$E$134/(Assumptions!$C$17*$C$11)),0) -> 1666.6667 | AE26: =IF((AE$18>=Assumptions!$C$5),(Assumptions!$E$134/(Assumptions!$C$17*$C$11)),0) -> 1666.6667 | AF26: =IF((AF$18>=Assumptions!$C$5),(Assumptions!$E$134/(Assumptions!$C$17*$C$11)),0) -> 1666.6667 | AG26: =IF((AG$18>=Assumptions!$C$5),(Assumptions!$E$134/(Assumptions!$C$17*$C$11)),0) -> 1666.6667 | AH26: =IF((AH$18>=Assumptions!$C$5),(Assumptions!$E$134/(Assumptions!$C$17*$C$11)),0) -> 1666.6667 | ... AL26: =IF((AL$18>=Assumptions!$C$5),(Assumptions!$E$134/(Assumptions!$C$17*$C$11)),0) -> 1666.6667 | AN26: =SUM(C26:N26) -> 0 | AO26: =SUM(O26:Z26) -> 12000 | AP26: =SUM(AA26:AL26) -> 20000
A27: New monthly-active free users | B27: users | C27: =((C25+C26)*Assumptions!$C$18) -> 234 | D27: =((D25+D26)*Assumptions!$C$18) -> 209.88 | E27: =((E25+E26)*Assumptions!$C$18) -> 182.0232 | F27: =((F25+F26)*Assumptions!$C$18) -> 171.5063 | G27: =((G25+G26)*Assumptions!$C$18) -> 136.34751 | H27: =((H25+H26)*Assumptions!$C$18) -> 120.4403 | I27: =((I25+I26)*Assumptions!$C$18) -> 178.73341 | J27: =((J25+J26)*Assumptions!$C$18) -> 433.04551 | ... AL27: =((AL25+AL26)*Assumptions!$C$18) -> 3060.0678 | AN27: =SUM(C27:N27) -> 3046.2028 | AO27: =SUM(O27:Z27) -> 28603.695 | AP27: =SUM(AA27:AL27) -> 42983.447
A28: New paying subscribers (conversions) | B28: users | C28: =IF((C$18>=Assumptions!$C$5),((Assumptions!$C$20*$C$5)*0),0) -> 0 | D28: =IF((D$18>=Assumptions!$C$5),((Assumptions!$C$20*$C$5)*C29),0) -> 0 | E28: =IF((E$18>=Assumptions!$C$5),((Assumptions!$C$20*$C$5)*D29),0) -> 0 | F28: =IF((F$18>=Assumptions!$C$5),((Assumptions!$C$20*$C$5)*E29),0) -> 0 | G28: =IF((G$18>=Assumptions!$C$5),((Assumptions!$C$20*$C$5)*F29),0) -> 0 | H28: =IF((H$18>=Assumptions!$C$5),((Assumptions!$C$20*$C$5)*G29),0) -> 0 | I28: =IF((I$18>=Assumptions!$C$5),((Assumptions!$C$20*$C$5)*H29),0) -> 0 | J28: =IF((J$18>=Assumptions!$C$5),((Assumptions!$C$20*$C$5)*I29),0) -> 0 | K28: =IF((K$18>=Assumptions!$C$5),((Assumptions!$C$20*$C$5)*J29),0) -> 0 | ... AL28: =IF((AL$18>=Assumptions!$C$5),((Assumptions!$C$20*$C$5)*AK29),0) -> 69.024874 | AN28: =SUM(C28:N28) -> 0 | AO28: =SUM(O28:Z28) -> 283.74822 | AP28: =SUM(AA28:AL28) -> 657.18156
A29: Active free users (end of month) | B29: users | C29: =MAX(0,(((0*(1-Assumptions!$C$19))+C27)-C28)) -> 234 | D29: =MAX(0,(((C29*(1-Assumptions!$C$19))+D27)-D28)) -> 415.8 | E29: =MAX(0,(((D29*(1-Assumptions!$C$19))+E27)-E28)) -> 547.9272 | F29: =MAX(0,(((E29*(1-Assumptions!$C$19))+F27)-F28)) -> 653.68224 | G29: =MAX(0,(((F29*(1-Assumptions!$C$19))+G27)-G28)) -> 711.58788 | H29: =MAX(0,(((G29*(1-Assumptions!$C$19))+H27)-H28)) -> 746.63764 | I29: =MAX(0,(((H29*(1-Assumptions!$C$19))+I27)-I28)) -> 835.77453 | J29: =MAX(0,(((I29*(1-Assumptions!$C$19))+J27)-J28)) -> 1168.5271 | K29: =MAX(0,(((J29*(1-Assumptions!$C$19))+K27)-K28)) -> 1544.7106 | ... AL29: =MAX(0,(((AK29*(1-Assumptions!$C$19))+AL27)-AL28)) -> 27287.799 | AN29: =N29 -> 1806.2157 | AO29: =Z29 -> 16506.248 | AP29: =AL29 -> 27287.799
A30: Incident: extra monthly paid churn | B30: % | C30: =IF(AND(($C$14=1),(C$18>=(Assumptions!$C$106+1)),(C$18<=(Assumptions!$C$106+3))),Assumptions!$C$115,0) -> 0 | D30: =IF(AND(($C$14=1),(D$18>=(Assumptions!$C$106+1)),(D$18<=(Assumptions!$C$106+3))),Assumptions!$C$115,0) -> 0 | E30: =IF(AND(($C$14=1),(E$18>=(Assumptions!$C$106+1)),(E$18<=(Assumptions!$C$106+3))),Assumptions!$C$115,0) -> 0 | F30: =IF(AND(($C$14=1),(F$18>=(Assumptions!$C$106+1)),(F$18<=(Assumptions!$C$106+3))),Assumptions!$C$115,0) -> 0 | G30: =IF(AND(($C$14=1),(G$18>=(Assumptions!$C$106+1)),(G$18<=(Assumptions!$C$106+3))),Assumptions!$C$115,0) -> 0 | H30: =IF(AND(($C$14=1),(H$18>=(Assumptions!$C$106+1)),(H$18<=(Assumptions!$C$106+3))),Assumptions!$C$115,0) -> 0 | I30: =IF(AND(($C$14=1),(I$18>=(Assumptions!$C$106+1)),(I$18<=(Assumptions!$C$106+3))),Assumptions!$C$115,0) -> 0 | J30: =IF(AND(($C$14=1),(J$18>=(Assumptions!$C$106+1)),(J$18<=(Assumptions!$C$106+3))),Assumptions!$C$115,0) -> 0 | ... AL30: =IF(AND(($C$14=1),(AL$18>=(Assumptions!$C$106+1)),(AL$18<=(Assumptions!$C$106+3))),Assumptions!$C$115,0) -> 0
A31: Effective monthly plan churn | B31: % | C31: =MIN(1,((Assumptions!$C$22*$C$6)+C30)) -> 0.05 | D31: =MIN(1,((Assumptions!$C$22*$C$6)+D30)) -> 0.05 | E31: =MIN(1,((Assumptions!$C$22*$C$6)+E30)) -> 0.05 | F31: =MIN(1,((Assumptions!$C$22*$C$6)+F30)) -> 0.05 | G31: =MIN(1,((Assumptions!$C$22*$C$6)+G30)) -> 0.05 | H31: =MIN(1,((Assumptions!$C$22*$C$6)+H30)) -> 0.05 | I31: =MIN(1,((Assumptions!$C$22*$C$6)+I30)) -> 0.05 | J31: =MIN(1,((Assumptions!$C$22*$C$6)+J30)) -> 0.05 | ... AL31: =MIN(1,((Assumptions!$C$22*$C$6)+AL30)) -> 0.05
A32: New monthly-plan subscribers | B32: users | C32: =(C28*(1-Assumptions!$C$21)) -> 0 | D32: =(D28*(1-Assumptions!$C$21)) -> 0 | E32: =(E28*(1-Assumptions!$C$21)) -> 0 | F32: =(F28*(1-Assumptions!$C$21)) -> 0 | G32: =(G28*(1-Assumptions!$C$21)) -> 0 | H32: =(H28*(1-Assumptions!$C$21)) -> 0 | I32: =(I28*(1-Assumptions!$C$21)) -> 0 | J32: =(J28*(1-Assumptions!$C$21)) -> 0 | ... AL32: =(AL28*(1-Assumptions!$C$21)) -> 37.963681 | AN32: =SUM(C32:N32) -> 0 | AO32: =SUM(O32:Z32) -> 156.06152 | AP32: =SUM(AA32:AL32) -> 361.44986
A33: New annual-plan subscribers | B33: users | C33: =(C28*Assumptions!$C$21) -> 0 | D33: =(D28*Assumptions!$C$21) -> 0 | E33: =(E28*Assumptions!$C$21) -> 0 | F33: =(F28*Assumptions!$C$21) -> 0 | G33: =(G28*Assumptions!$C$21) -> 0 | H33: =(H28*Assumptions!$C$21) -> 0 | I33: =(I28*Assumptions!$C$21) -> 0 | J33: =(J28*Assumptions!$C$21) -> 0 | ... AL33: =(AL28*Assumptions!$C$21) -> 31.061193 | AN33: =SUM(C33:N33) -> 0 | AO33: =SUM(O33:Z33) -> 127.6867 | AP33: =SUM(AA33:AL33) -> 295.7317
A34: Monthly-plan subscribers (end) | B34: users | C34: =((0*(1-C31))+C32) -> 0 | D34: =((C34*(1-D31))+D32) -> 0 | E34: =((D34*(1-E31))+E32) -> 0 | F34: =((E34*(1-F31))+F32) -> 0 | G34: =((F34*(1-G31))+G32) -> 0 | H34: =((G34*(1-H31))+H32) -> 0 | I34: =((H34*(1-I31))+I32) -> 0 | J34: =((I34*(1-J31))+J32) -> 0 | K34: =((J34*(1-K31))+K32) -> 0 | ... AL34: =((AK34*(1-AL31))+AL32) -> 354.00781 | AN34: =N34 -> 0 | AO34: =Z34 -> 129.2797 | AP34: =AL34 -> 354.00781
A35: Effective annual renewal rate | B35: % | C35: =MAX(0,(1-((1-Assumptions!$C$23)*$C$6))) -> 0.55 | D35: =MAX(0,(1-((1-Assumptions!$C$23)*$C$6))) -> 0.55 | E35: =MAX(0,(1-((1-Assumptions!$C$23)*$C$6))) -> 0.55 | F35: =MAX(0,(1-((1-Assumptions!$C$23)*$C$6))) -> 0.55 | G35: =MAX(0,(1-((1-Assumptions!$C$23)*$C$6))) -> 0.55 | H35: =MAX(0,(1-((1-Assumptions!$C$23)*$C$6))) -> 0.55 | I35: =MAX(0,(1-((1-Assumptions!$C$23)*$C$6))) -> 0.55 | J35: =MAX(0,(1-((1-Assumptions!$C$23)*$C$6))) -> 0.55 | ... AL35: =MAX(0,(1-((1-Assumptions!$C$23)*$C$6))) -> 0.55
A36: Annual renewals this month | B36: users | C36: =(C35*0) -> 0 | D36: =(D35*0) -> 0 | E36: =(E35*0) -> 0 | F36: =(F35*0) -> 0 | G36: =(G35*0) -> 0 | H36: =(H35*0) -> 0 | I36: =(I35*0) -> 0 | J36: =(J35*0) -> 0 | ... N36: =(N35*0) -> 0 | O36: =(O35*C37) -> 0 | P36: =(P35*D37) -> 0 | Q36: =(Q35*E37) -> 0 | R36: =(R35*F37) -> 0 | S36: =(S35*G37) -> 0 | T36: =(T35*H37) -> 0 | U36: =(U35*I37) -> 0 | V36: =(V35*J37) -> 0 | ... AL36: =(AL35*Z37) -> 10.135846 | AN36: =SUM(C36:N36) -> 0 | AO36: =SUM(O36:Z36) -> 0 | AP36: =SUM(AA36:AL36) -> 70.227685
A37: Annual plan starts (new + renewals) | B37: users | C37: =(C33+C36) -> 0 | D37: =(D33+D36) -> 0 | E37: =(E33+E36) -> 0 | F37: =(F33+F36) -> 0 | G37: =(G33+G36) -> 0 | H37: =(H33+H36) -> 0 | I37: =(I33+I36) -> 0 | J37: =(J33+J36) -> 0 | ... AL37: =(AL33+AL36) -> 41.19704 | AN37: =SUM(C37:N37) -> 0 | AO37: =SUM(O37:Z37) -> 127.6867 | AP37: =SUM(AA37:AL37) -> 365.95939
A38: Annual-plan subscribers (end) | B38: users | C38: =C37 -> 0 | D38: =SUM(C37:D37) -> 0 | E38: =SUM(C37:E37) -> 0 | F38: =SUM(C37:F37) -> 0 | G38: =SUM(C37:G37) -> 0 | H38: =SUM(C37:H37) -> 0 | I38: =SUM(C37:I37) -> 0 | J38: =SUM(C37:J37) -> 0 | K38: =SUM(C37:K37) -> 0 | L38: =SUM(C37:L37) -> 0 | M38: =SUM(C37:M37) -> 0 | N38: =SUM(C37:N37) -> 0 | O38: =SUM(D37:O37) -> 2.0319927 | P38: =SUM(E37:P37) -> 6.568931 | Q38: =SUM(F37:Q37) -> 13.054495 | R38: =SUM(G37:R37) -> 20.977232 | S38: =SUM(H37:S37) -> 30.043473 | T38: =SUM(I37:T37) -> 39.796551 | U38: =SUM(J37:U37) -> 50.002669 | ... AL38: =SUM(AA37:AL37) -> 365.95939 | AN38: =N38 -> 0 | AO38: =Z38 -> 127.6867 | AP38: =AL38 -> 365.95939
A39: Paying subscribers (end) | B39: users | C39: =(C34+C38) -> 0 | D39: =(D34+D38) -> 0 | E39: =(E34+E38) -> 0 | F39: =(F34+F38) -> 0 | G39: =(G34+G38) -> 0 | H39: =(H34+H38) -> 0 | I39: =(I34+I38) -> 0 | J39: =(J34+J38) -> 0 | ... AL39: =(AL34+AL38) -> 719.9672 | AN39: =N39 -> 0 | AO39: =Z39 -> 256.9664 | AP39: =AL39 -> 719.9672
A40: Subscribers lost (churn + non-renewal) | B40: users | C40: =((0+C28)-C39) -> 0 | D40: =((C39+D28)-D39) -> 0 | E40: =((D39+E28)-E39) -> 0 | F40: =((E39+F28)-F39) -> 0 | G40: =((F39+G28)-G39) -> 0 | H40: =((G39+H28)-H39) -> 0 | I40: =((H39+I28)-I39) -> 0 | J40: =((I39+J28)-J39) -> 0 | K40: =((J39+K28)-K39) -> 0 | ... AL40: =((AK39+AL28)-AL39) -> 24.926867 | AN40: =SUM(C40:N40) -> 0 | AO40: =SUM(O40:Z40) -> 26.781824 | AP40: =SUM(AA40:AL40) -> 194.18076
A41: Student billings (net of refunds) | B41: $ | C41: =((((Assumptions!$C$12*(1-Assumptions!$C$14))*C34)+((Assumptions!$C$13*(1-Assumptions!$C$14))*C37))*(1-Assumptions!$C$15)) -> 0 | D41: =((((Assumptions!$C$12*(1-Assumptions!$C$14))*D34)+((Assumptions!$C$13*(1-Assumptions!$C$14))*D37))*(1-Assumptions!$C$15)) -> 0 | E41: =((((Assumptions!$C$12*(1-Assumptions!$C$14))*E34)+((Assumptions!$C$13*(1-Assumptions!$C$14))*E37))*(1-Assumptions!$C$15)) -> 0 | F41: =((((Assumptions!$C$12*(1-Assumptions!$C$14))*F34)+((Assumptions!$C$13*(1-Assumptions!$C$14))*F37))*(1-Assumptions!$C$15)) -> 0 | G41: =((((Assumptions!$C$12*(1-Assumptions!$C$14))*G34)+((Assumptions!$C$13*(1-Assumptions!$C$14))*G37))*(1-Assumptions!$C$15)) -> 0 | H41: =((((Assumptions!$C$12*(1-Assumptions!$C$14))*H34)+((Assumptions!$C$13*(1-Assumptions!$C$14))*H37))*(1-Assumptions!$C$15)) -> 0 | I41: =((((Assumptions!$C$12*(1-Assumptions!$C$14))*I34)+((Assumptions!$C$13*(1-Assumptions!$C$14))*I37))*(1-Assumptions!$C$15)) -> 0 | J41: =((((Assumptions!$C$12*(1-Assumptions!$C$14))*J34)+((Assumptions!$C$13*(1-Assumptions!$C$14))*J37))*(1-Assumptions!$C$15)) -> 0 | ... AL41: =((((Assumptions!$C$12*(1-Assumptions!$C$14))*AL34)+((Assumptions!$C$13*(1-Assumptions!$C$14))*AL37))*(1-Assumptions!$C$15)) -> 4577.0363 | AN41: =SUM(C41:N41) -> 0 | AO41: =SUM(O41:Z41) -> 11180.044 | AP41: =SUM(AA41:AL41) -> 39368.296
A42: Student subscription revenue | B42: $ | C42: =((((Assumptions!$C$12*(1-Assumptions!$C$14))*C34)+(((Assumptions!$C$13*(1-Assumptions!$C$14))/12)*C38))*(1-Assumptions!$C$15)) -> 0 | D42: =((((Assumptions!$C$12*(1-Assumptions!$C$14))*D34)+(((Assumptions!$C$13*(1-Assumptions!$C$14))/12)*D38))*(1-Assumptions!$C$15)) -> 0 | E42: =((((Assumptions!$C$12*(1-Assumptions!$C$14))*E34)+(((Assumptions!$C$13*(1-Assumptions!$C$14))/12)*E38))*(1-Assumptions!$C$15)) -> 0 | F42: =((((Assumptions!$C$12*(1-Assumptions!$C$14))*F34)+(((Assumptions!$C$13*(1-Assumptions!$C$14))/12)*F38))*(1-Assumptions!$C$15)) -> 0 | G42: =((((Assumptions!$C$12*(1-Assumptions!$C$14))*G34)+(((Assumptions!$C$13*(1-Assumptions!$C$14))/12)*G38))*(1-Assumptions!$C$15)) -> 0 | H42: =((((Assumptions!$C$12*(1-Assumptions!$C$14))*H34)+(((Assumptions!$C$13*(1-Assumptions!$C$14))/12)*H38))*(1-Assumptions!$C$15)) -> 0 | I42: =((((Assumptions!$C$12*(1-Assumptions!$C$14))*I34)+(((Assumptions!$C$13*(1-Assumptions!$C$14))/12)*I38))*(1-Assumptions!$C$15)) -> 0 | J42: =((((Assumptions!$C$12*(1-Assumptions!$C$14))*J34)+(((Assumptions!$C$13*(1-Assumptions!$C$14))/12)*J38))*(1-Assumptions!$C$15)) -> 0 | ... AL42: =((((Assumptions!$C$12*(1-Assumptions!$C$14))*AL34)+(((Assumptions!$C$13*(1-Assumptions!$C$14))/12)*AL38))*(1-Assumptions!$C$15)) -> 4027.5941 | AN42: =SUM(C42:N42) -> 0 | AO42: =SUM(O42:Z42) -> 7305.2982 | AP42: =SUM(AA42:AL42) -> 33510.939
A43: Institutional platform: pilots, contracts, logos
A44: Incident: multiplier on new starts | B44: x | C44: =IF(AND(($C$14=1),(C$18>=(Assumptions!$C$106+1)),(C$18<=(Assumptions!$C$106+6))),Assumptions!$C$117,1) -> 1 | D44: =IF(AND(($C$14=1),(D$18>=(Assumptions!$C$106+1)),(D$18<=(Assumptions!$C$106+6))),Assumptions!$C$117,1) -> 1 | E44: =IF(AND(($C$14=1),(E$18>=(Assumptions!$C$106+1)),(E$18<=(Assumptions!$C$106+6))),Assumptions!$C$117,1) -> 1 | F44: =IF(AND(($C$14=1),(F$18>=(Assumptions!$C$106+1)),(F$18<=(Assumptions!$C$106+6))),Assumptions!$C$117,1) -> 1 | G44: =IF(AND(($C$14=1),(G$18>=(Assumptions!$C$106+1)),(G$18<=(Assumptions!$C$106+6))),Assumptions!$C$117,1) -> 1 | H44: =IF(AND(($C$14=1),(H$18>=(Assumptions!$C$106+1)),(H$18<=(Assumptions!$C$106+6))),Assumptions!$C$117,1) -> 1 | I44: =IF(AND(($C$14=1),(I$18>=(Assumptions!$C$106+1)),(I$18<=(Assumptions!$C$106+6))),Assumptions!$C$117,1) -> 1 | J44: =IF(AND(($C$14=1),(J$18>=(Assumptions!$C$106+1)),(J$18<=(Assumptions!$C$106+6))),Assumptions!$C$117,1) -> 1 | ... AL44: =IF(AND(($C$14=1),(AL$18>=(Assumptions!$C$106+1)),(AL$18<=(Assumptions!$C$106+6))),Assumptions!$C$117,1) -> 1
A45: Effective gross logo renewal rate | B45: % | C45: =MAX(0,((1-((1-Assumptions!$C$30)*$C$6))-IF(AND(($C$14=1),(C$18>=Assumptions!$C$106),(C$18<=(Assumptions!$C$106+11))),Assumptions!$C$116,0))) -> 0.88 | D45: =MAX(0,((1-((1-Assumptions!$C$30)*$C$6))-IF(AND(($C$14=1),(D$18>=Assumptions!$C$106),(D$18<=(Assumptions!$C$106+11))),Assumptions!$C$116,0))) -> 0.88 | E45: =MAX(0,((1-((1-Assumptions!$C$30)*$C$6))-IF(AND(($C$14=1),(E$18>=Assumptions!$C$106),(E$18<=(Assumptions!$C$106+11))),Assumptions!$C$116,0))) -> 0.88 | F45: =MAX(0,((1-((1-Assumptions!$C$30)*$C$6))-IF(AND(($C$14=1),(F$18>=Assumptions!$C$106),(F$18<=(Assumptions!$C$106+11))),Assumptions!$C$116,0))) -> 0.88 | G45: =MAX(0,((1-((1-Assumptions!$C$30)*$C$6))-IF(AND(($C$14=1),(G$18>=Assumptions!$C$106),(G$18<=(Assumptions!$C$106+11))),Assumptions!$C$116,0))) -> 0.88 | H45: =MAX(0,((1-((1-Assumptions!$C$30)*$C$6))-IF(AND(($C$14=1),(H$18>=Assumptions!$C$106),(H$18<=(Assumptions!$C$106+11))),Assumptions!$C$116,0))) -> 0.88 | I45: =MAX(0,((1-((1-Assumptions!$C$30)*$C$6))-IF(AND(($C$14=1),(I$18>=Assumptions!$C$106),(I$18<=(Assumptions!$C$106+11))),Assumptions!$C$116,0))) -> 0.88 | J45: =MAX(0,((1-((1-Assumptions!$C$30)*$C$6))-IF(AND(($C$14=1),(J$18>=Assumptions!$C$106),(J$18<=(Assumptions!$C$106+11))),Assumptions!$C$116,0))) -> 0.88 | ... AL45: =MAX(0,((1-((1-Assumptions!$C$30)*$C$6))-IF(AND(($C$14=1),(AL$18>=Assumptions!$C$106),(AL$18<=(Assumptions!$C$106+11))),Assumptions!$C$116,0))) -> 0.88
A46: Paid pilot starts, Department | B46: accts | C46: =((IF(OR((C$18-(Assumptions!$C$7-1)-$C$9)<1,(C$18-(Assumptions!$C$7-1)-$C$9)>36),0,INDEX(Schedules!$C$5:$AL$5,(C$18-(Assumptions!$C$7-1)-$C$9)))*$C$7)*C44) -> 0 | D46: =((IF(OR((D$18-(Assumptions!$C$7-1)-$C$9)<1,(D$18-(Assumptions!$C$7-1)-$C$9)>36),0,INDEX(Schedules!$C$5:$AL$5,(D$18-(Assumptions!$C$7-1)-$C$9)))*$C$7)*D44) -> 0 | E46: =((IF(OR((E$18-(Assumptions!$C$7-1)-$C$9)<1,(E$18-(Assumptions!$C$7-1)-$C$9)>36),0,INDEX(Schedules!$C$5:$AL$5,(E$18-(Assumptions!$C$7-1)-$C$9)))*$C$7)*E44) -> 0 | F46: =((IF(OR((F$18-(Assumptions!$C$7-1)-$C$9)<1,(F$18-(Assumptions!$C$7-1)-$C$9)>36),0,INDEX(Schedules!$C$5:$AL$5,(F$18-(Assumptions!$C$7-1)-$C$9)))*$C$7)*F44) -> 0 | G46: =((IF(OR((G$18-(Assumptions!$C$7-1)-$C$9)<1,(G$18-(Assumptions!$C$7-1)-$C$9)>36),0,INDEX(Schedules!$C$5:$AL$5,(G$18-(Assumptions!$C$7-1)-$C$9)))*$C$7)*G44) -> 0 | H46: =((IF(OR((H$18-(Assumptions!$C$7-1)-$C$9)<1,(H$18-(Assumptions!$C$7-1)-$C$9)>36),0,INDEX(Schedules!$C$5:$AL$5,(H$18-(Assumptions!$C$7-1)-$C$9)))*$C$7)*H44) -> 0 | I46: =((IF(OR((I$18-(Assumptions!$C$7-1)-$C$9)<1,(I$18-(Assumptions!$C$7-1)-$C$9)>36),0,INDEX(Schedules!$C$5:$AL$5,(I$18-(Assumptions!$C$7-1)-$C$9)))*$C$7)*I44) -> 0 | J46: =((IF(OR((J$18-(Assumptions!$C$7-1)-$C$9)<1,(J$18-(Assumptions!$C$7-1)-$C$9)>36),0,INDEX(Schedules!$C$5:$AL$5,(J$18-(Assumptions!$C$7-1)-$C$9)))*$C$7)*J44) -> 0 | ... AL46: =((IF(OR((AL$18-(Assumptions!$C$7-1)-$C$9)<1,(AL$18-(Assumptions!$C$7-1)-$C$9)>36),0,INDEX(Schedules!$C$5:$AL$5,(AL$18-(Assumptions!$C$7-1)-$C$9)))*$C$7)*AL44) -> 0 | AN46: =SUM(C46:N46) -> 0 | AO46: =SUM(O46:Z46) -> 6 | AP46: =SUM(AA46:AL46) -> 13
A47: Unpaid design-partner pilot starts, Department | B47: accts | C47: =INDEX(Schedules!$C$11:$AL$11,C$18) -> 0 | D47: =INDEX(Schedules!$C$11:$AL$11,D$18) -> 0 | E47: =INDEX(Schedules!$C$11:$AL$11,E$18) -> 0 | F47: =INDEX(Schedules!$C$11:$AL$11,F$18) -> 0 | G47: =INDEX(Schedules!$C$11:$AL$11,G$18) -> 1 | H47: =INDEX(Schedules!$C$11:$AL$11,H$18) -> 0 | I47: =INDEX(Schedules!$C$11:$AL$11,I$18) -> 0 | J47: =INDEX(Schedules!$C$11:$AL$11,J$18) -> 0 | ... AL47: =INDEX(Schedules!$C$11:$AL$11,AL$18) -> 0 | AN47: =SUM(C47:N47) -> 1 | AO47: =SUM(O47:Z47) -> 0 | AP47: =SUM(AA47:AL47) -> 0
A48: All pilot starts, Department | B48: accts | C48: =(C46+C47) -> 0 | D48: =(D46+D47) -> 0 | E48: =(E46+E47) -> 0 | F48: =(F46+F47) -> 0 | G48: =(G46+G47) -> 1 | H48: =(H46+H47) -> 0 | I48: =(I46+I47) -> 0 | J48: =(J46+J47) -> 0 | ... AL48: =(AL46+AL47) -> 0 | AN48: =SUM(C48:N48) -> 1 | AO48: =SUM(O48:Z48) -> 6 | AP48: =SUM(AA48:AL48) -> 13
A49: Direct annual starts, Department | B49: accts | C49: =((IF(OR((C$18-(Assumptions!$C$8-1)-$C$9)<1,(C$18-(Assumptions!$C$8-1)-$C$9)>36),0,INDEX(Schedules!$C$8:$AL$8,(C$18-(Assumptions!$C$8-1)-$C$9)))*$C$7)*C44) -> 0 | D49: =((IF(OR((D$18-(Assumptions!$C$8-1)-$C$9)<1,(D$18-(Assumptions!$C$8-1)-$C$9)>36),0,INDEX(Schedules!$C$8:$AL$8,(D$18-(Assumptions!$C$8-1)-$C$9)))*$C$7)*D44) -> 0 | E49: =((IF(OR((E$18-(Assumptions!$C$8-1)-$C$9)<1,(E$18-(Assumptions!$C$8-1)-$C$9)>36),0,INDEX(Schedules!$C$8:$AL$8,(E$18-(Assumptions!$C$8-1)-$C$9)))*$C$7)*E44) -> 0 | F49: =((IF(OR((F$18-(Assumptions!$C$8-1)-$C$9)<1,(F$18-(Assumptions!$C$8-1)-$C$9)>36),0,INDEX(Schedules!$C$8:$AL$8,(F$18-(Assumptions!$C$8-1)-$C$9)))*$C$7)*F44) -> 0 | G49: =((IF(OR((G$18-(Assumptions!$C$8-1)-$C$9)<1,(G$18-(Assumptions!$C$8-1)-$C$9)>36),0,INDEX(Schedules!$C$8:$AL$8,(G$18-(Assumptions!$C$8-1)-$C$9)))*$C$7)*G44) -> 0 | H49: =((IF(OR((H$18-(Assumptions!$C$8-1)-$C$9)<1,(H$18-(Assumptions!$C$8-1)-$C$9)>36),0,INDEX(Schedules!$C$8:$AL$8,(H$18-(Assumptions!$C$8-1)-$C$9)))*$C$7)*H44) -> 0 | I49: =((IF(OR((I$18-(Assumptions!$C$8-1)-$C$9)<1,(I$18-(Assumptions!$C$8-1)-$C$9)>36),0,INDEX(Schedules!$C$8:$AL$8,(I$18-(Assumptions!$C$8-1)-$C$9)))*$C$7)*I44) -> 0 | J49: =((IF(OR((J$18-(Assumptions!$C$8-1)-$C$9)<1,(J$18-(Assumptions!$C$8-1)-$C$9)>36),0,INDEX(Schedules!$C$8:$AL$8,(J$18-(Assumptions!$C$8-1)-$C$9)))*$C$7)*J44) -> 0 | ... AL49: =((IF(OR((AL$18-(Assumptions!$C$8-1)-$C$9)<1,(AL$18-(Assumptions!$C$8-1)-$C$9)>36),0,INDEX(Schedules!$C$8:$AL$8,(AL$18-(Assumptions!$C$8-1)-$C$9)))*$C$7)*AL44) -> 0 | AN49: =SUM(C49:N49) -> 0 | AO49: =SUM(O49:Z49) -> 1 | AP49: =SUM(AA49:AL49) -> 8
A50: New billable institutions (paid pilot or direct), Department | B50: accts | C50: =(C46+C49) -> 0 | D50: =(D46+D49) -> 0 | E50: =(E46+E49) -> 0 | F50: =(F46+F49) -> 0 | G50: =(G46+G49) -> 0 | H50: =(H46+H49) -> 0 | I50: =(I46+I49) -> 0 | J50: =(J46+J49) -> 0 | ... AL50: =(AL46+AL49) -> 0 | AN50: =SUM(C50:N50) -> 0 | AO50: =SUM(O50:Z50) -> 7 | AP50: =SUM(AA50:AL50) -> 21
A51: Pilots running (paid + unpaid), Department | B51: accts | C51: =C48 -> 0 | D51: =SUM(C48:D48) -> 0 | E51: =SUM(C48:E48) -> 0 | F51: =SUM(C48:F48) -> 0 | G51: =SUM(C48:G48) -> 1 | H51: =SUM(C48:H48) -> 1 | I51: =SUM(D48:I48) -> 1 | J51: =SUM(E48:J48) -> 1 | K51: =SUM(F48:K48) -> 1 | L51: =SUM(G48:L48) -> 1 | M51: =SUM(H48:M48) -> 0 | N51: =SUM(I48:N48) -> 0 | O51: =SUM(J48:O48) -> 1 | ... AL51: =SUM(AG48:AL48) -> 7 | AN51: =N51 -> 0 | AO51: =Z51 -> 4 | AP51: =AL51 -> 7
A52: Paid pilots running, Department | B52: accts | C52: =C46 -> 0 | D52: =SUM(C46:D46) -> 0 | E52: =SUM(C46:E46) -> 0 | F52: =SUM(C46:F46) -> 0 | G52: =SUM(C46:G46) -> 0 | H52: =SUM(C46:H46) -> 0 | I52: =SUM(D46:I46) -> 0 | J52: =SUM(E46:J46) -> 0 | K52: =SUM(F46:K46) -> 0 | L52: =SUM(G46:L46) -> 0 | M52: =SUM(H46:M46) -> 0 | N52: =SUM(I46:N46) -> 0 | O52: =SUM(J46:O46) -> 1 | ... AL52: =SUM(AG46:AL46) -> 7 | AN52: =N52 -> 0 | AO52: =Z52 -> 4 | AP52: =AL52 -> 7
A53: Paid pilots converting to annual, Department | B53: accts | C53: =((Assumptions!$C$127*$C$8)*0) -> 0 | D53: =((Assumptions!$C$127*$C$8)*0) -> 0 | E53: =((Assumptions!$C$127*$C$8)*0) -> 0 | F53: =((Assumptions!$C$127*$C$8)*0) -> 0 | G53: =((Assumptions!$C$127*$C$8)*0) -> 0 | H53: =((Assumptions!$C$127*$C$8)*0) -> 0 | I53: =((Assumptions!$C$127*$C$8)*0) -> 0 | J53: =((Assumptions!$C$127*$C$8)*C46) -> 0 | K53: =((Assumptions!$C$127*$C$8)*D46) -> 0 | L53: =((Assumptions!$C$127*$C$8)*E46) -> 0 | M53: =((Assumptions!$C$127*$C$8)*F46) -> 0 | N53: =((Assumptions!$C$127*$C$8)*G46) -> 0 | O53: =((Assumptions!$C$127*$C$8)*H46) -> 0 | P53: =((Assumptions!$C$127*$C$8)*I46) -> 0 | Q53: =((Assumptions!$C$127*$C$8)*J46) -> 0 | ... AL53: =((Assumptions!$C$127*$C$8)*AE46) -> 0 | AN53: =SUM(C53:N53) -> 0 | AO53: =SUM(O53:Z53) -> 1 | AP53: =SUM(AA53:AL53) -> 5
A54: Design partners converting to annual, Department | B54: accts | C54: =((Assumptions!$C$10*$C$8)*IF((C$18=(Assumptions!$C$7+$C$9)),0,IF((C$18>(Assumptions!$C$7+$C$9)),0,0))) -> 0 | D54: =((Assumptions!$C$10*$C$8)*IF((D$18=(Assumptions!$C$7+$C$9)),0,IF((D$18>(Assumptions!$C$7+$C$9)),0,0))) -> 0 | E54: =((Assumptions!$C$10*$C$8)*IF((E$18=(Assumptions!$C$7+$C$9)),0,IF((E$18>(Assumptions!$C$7+$C$9)),0,0))) -> 0 | F54: =((Assumptions!$C$10*$C$8)*IF((F$18=(Assumptions!$C$7+$C$9)),0,IF((F$18>(Assumptions!$C$7+$C$9)),0,0))) -> 0 | G54: =((Assumptions!$C$10*$C$8)*IF((G$18=(Assumptions!$C$7+$C$9)),0,IF((G$18>(Assumptions!$C$7+$C$9)),0,0))) -> 0 | H54: =((Assumptions!$C$10*$C$8)*IF((H$18=(Assumptions!$C$7+$C$9)),0,IF((H$18>(Assumptions!$C$7+$C$9)),0,0))) -> 0 | I54: =((Assumptions!$C$10*$C$8)*IF((I$18=(Assumptions!$C$7+$C$9)),0,IF((I$18>(Assumptions!$C$7+$C$9)),0,0))) -> 0 | J54: =((Assumptions!$C$10*$C$8)*IF((J$18=(Assumptions!$C$7+$C$9)),C47,IF((J$18>(Assumptions!$C$7+$C$9)),C47,0))) -> 0 | K54: =((Assumptions!$C$10*$C$8)*IF((K$18=(Assumptions!$C$7+$C$9)),SUM(C47:D47),IF((K$18>(Assumptions!$C$7+$C$9)),D47,0))) -> 0 | L54: =((Assumptions!$C$10*$C$8)*IF((L$18=(Assumptions!$C$7+$C$9)),SUM(C47:E47),IF((L$18>(Assumptions!$C$7+$C$9)),E47,0))) -> 0 | M54: =((Assumptions!$C$10*$C$8)*IF((M$18=(Assumptions!$C$7+$C$9)),SUM(C47:F47),IF((M$18>(Assumptions!$C$7+$C$9)),F47,0))) -> 0 | N54: =((Assumptions!$C$10*$C$8)*IF((N$18=(Assumptions!$C$7+$C$9)),SUM(C47:G47),IF((N$18>(Assumptions!$C$7+$C$9)),G47,0))) -> 0.6 | O54: =((Assumptions!$C$10*$C$8)*IF((O$18=(Assumptions!$C$7+$C$9)),SUM(C47:H47),IF((O$18>(Assumptions!$C$7+$C$9)),H47,0))) -> 0 | P54: =((Assumptions!$C$10*$C$8)*IF((P$18=(Assumptions!$C$7+$C$9)),SUM(C47:I47),IF((P$18>(Assumptions!$C$7+$C$9)),I47,0))) -> 0 | Q54: =((Assumptions!$C$10*$C$8)*IF((Q$18=(Assumptions!$C$7+$C$9)),SUM(C47:J47),IF((Q$18>(Assumptions!$C$7+$C$9)),J47,0))) -> 0 | R54: =((Assumptions!$C$10*$C$8)*IF((R$18=(Assumptions!$C$7+$C$9)),SUM(C47:K47),IF((R$18>(Assumptions!$C$7+$C$9)),K47,0))) -> 0 | S54: =((Assumptions!$C$10*$C$8)*IF((S$18=(Assumptions!$C$7+$C$9)),SUM(C47:L47),IF((S$18>(Assumptions!$C$7+$C$9)),L47,0))) -> 0 | T54: =((Assumptions!$C$10*$C$8)*IF((T$18=(Assumptions!$C$7+$C$9)),SUM(C47:M47),IF((T$18>(Assumptions!$C$7+$C$9)),M47,0))) -> 0 | U54: =((Assumptions!$C$10*$C$8)*IF((U$18=(Assumptions!$C$7+$C$9)),SUM(C47:N47),IF((U$18>(Assumptions!$C$7+$C$9)),N47,0))) -> 0 | V54: =((Assumptions!$C$10*$C$8)*IF((V$18=(Assumptions!$C$7+$C$9)),SUM(C47:O47),IF((V$18>(Assumptions!$C$7+$C$9)),O47,0))) -> 0 | W54: =((Assumptions!$C$10*$C$8)*IF((W$18=(Assumptions!$C$7+$C$9)),SUM(C47:P47),IF((W$18>(Assumptions!$C$7+$C$9)),P47,0))) -> 0 | X54: =((Assumptions!$C$10*$C$8)*IF((X$18=(Assumptions!$C$7+$C$9)),SUM(C47:Q47),IF((X$18>(Assumptions!$C$7+$C$9)),Q47,0))) -> 0 | Y54: =((Assumptions!$C$10*$C$8)*IF((Y$18=(Assumptions!$C$7+$C$9)),SUM(C47:R47),IF((Y$18>(Assumptions!$C$7+$C$9)),R47,0))) -> 0 | Z54: =((Assumptions!$C$10*$C$8)*IF((Z$18=(Assumptions!$C$7+$C$9)),SUM(C47:S47),IF((Z$18>(Assumptions!$C$7+$C$9)),S47,0))) -> 0 | AA54: =((Assumptions!$C$10*$C$8)*IF((AA$18=(Assumptions!$C$7+$C$9)),SUM(C47:T47),IF((AA$18>(Assumptions!$C$7+$C$9)),T47,0))) -> 0 | AB54: =((Assumptions!$C$10*$C$8)*IF((AB$18=(Assumptions!$C$7+$C$9)),SUM(C47:U47),IF((AB$18>(Assumptions!$C$7+$C$9)),U47,0))) -> 0 | AC54: =((Assumptions!$C$10*$C$8)*IF((AC$18=(Assumptions!$C$7+$C$9)),SUM(C47:V47),IF((AC$18>(Assumptions!$C$7+$C$9)),V47,0))) -> 0 | AD54: =((Assumptions!$C$10*$C$8)*IF((AD$18=(Assumptions!$C$7+$C$9)),SUM(C47:W47),IF((AD$18>(Assumptions!$C$7+$C$9)),W47,0))) -> 0 | AE54: =((Assumptions!$C$10*$C$8)*IF((AE$18=(Assumptions!$C$7+$C$9)),SUM(C47:X47),IF((AE$18>(Assumptions!$C$7+$C$9)),X47,0))) -> 0 | AF54: =((Assumptions!$C$10*$C$8)*IF((AF$18=(Assumptions!$C$7+$C$9)),SUM(C47:Y47),IF((AF$18>(Assumptions!$C$7+$C$9)),Y47,0))) -> 0 | AG54: =((Assumptions!$C$10*$C$8)*IF((AG$18=(Assumptions!$C$7+$C$9)),SUM(C47:Z47),IF((AG$18>(Assumptions!$C$7+$C$9)),Z47,0))) -> 0 | AH54: =((Assumptions!$C$10*$C$8)*IF((AH$18=(Assumptions!$C$7+$C$9)),SUM(C47:AA47),IF((AH$18>(Assumptions!$C$7+$C$9)),AA47,0))) -> 0 | AI54: =((Assumptions!$C$10*$C$8)*IF((AI$18=(Assumptions!$C$7+$C$9)),SUM(C47:AB47),IF((AI$18>(Assumptions!$C$7+$C$9)),AB47,0))) -> 0 | AJ54: =((Assumptions!$C$10*$C$8)*IF((AJ$18=(Assumptions!$C$7+$C$9)),SUM(C47:AC47),IF((AJ$18>(Assumptions!$C$7+$C$9)),AC47,0))) -> 0 | AK54: =((Assumptions!$C$10*$C$8)*IF((AK$18=(Assumptions!$C$7+$C$9)),SUM(C47:AD47),IF((AK$18>(Assumptions!$C$7+$C$9)),AD47,0))) -> 0 | AL54: =((Assumptions!$C$10*$C$8)*IF((AL$18=(Assumptions!$C$7+$C$9)),SUM(C47:AE47),IF((AL$18>(Assumptions!$C$7+$C$9)),AE47,0))) -> 0 | AN54: =SUM(C54:N54) -> 0.6 | AO54: =SUM(O54:Z54) -> 0 | AP54: =SUM(AA54:AL54) -> 0
A55: New annual contracts, Department | B55: accts | C55: =((C53+C54)+C49) -> 0 | D55: =((D53+D54)+D49) -> 0 | E55: =((E53+E54)+E49) -> 0 | F55: =((F53+F54)+F49) -> 0 | G55: =((G53+G54)+G49) -> 0 | H55: =((H53+H54)+H49) -> 0 | I55: =((I53+I54)+I49) -> 0 | J55: =((J53+J54)+J49) -> 0 | ... AL55: =((AL53+AL54)+AL49) -> 0 | AN55: =SUM(C55:N55) -> 0.6 | AO55: =SUM(O55:Z55) -> 2 | AP55: =SUM(AA55:AL55) -> 13
A56: Annual contract starts (new + renewals), Department | B56: accts | C56: =(C55+(C45*0)) -> 0 | D56: =(D55+(D45*0)) -> 0 | E56: =(E55+(E45*0)) -> 0 | F56: =(F55+(F45*0)) -> 0 | G56: =(G55+(G45*0)) -> 0 | H56: =(H55+(H45*0)) -> 0 | I56: =(I55+(I45*0)) -> 0 | J56: =(J55+(J45*0)) -> 0 | ... N56: =(N55+(N45*0)) -> 0.6 | O56: =(O55+(O45*C56)) -> 0 | P56: =(P55+(P45*D56)) -> 0 | Q56: =(Q55+(Q45*E56)) -> 0 | R56: =(R55+(R45*F56)) -> 0 | S56: =(S55+(S45*G56)) -> 0 | T56: =(T55+(T45*H56)) -> 0 | U56: =(U55+(U45*I56)) -> 0 | V56: =(V55+(V45*J56)) -> 0.5 | ... AL56: =(AL55+(AL45*Z56)) -> 0.46464 | AN56: =SUM(C56:N56) -> 0.6 | AO56: =SUM(O56:Z56) -> 2.528 | AP56: =SUM(AA56:AL56) -> 15.22464
A57: Annual logos active, Department | B57: accts | C57: =C56 -> 0 | D57: =SUM(C56:D56) -> 0 | E57: =SUM(C56:E56) -> 0 | F57: =SUM(C56:F56) -> 0 | G57: =SUM(C56:G56) -> 0 | H57: =SUM(C56:H56) -> 0 | I57: =SUM(C56:I56) -> 0 | J57: =SUM(C56:J56) -> 0 | K57: =SUM(C56:K56) -> 0 | L57: =SUM(C56:L56) -> 0 | M57: =SUM(C56:M56) -> 0 | N57: =SUM(C56:N56) -> 0.6 | O57: =SUM(D56:O56) -> 0.6 | P57: =SUM(E56:P56) -> 0.6 | Q57: =SUM(F56:Q56) -> 0.6 | R57: =SUM(G56:R56) -> 0.6 | S57: =SUM(H56:S56) -> 0.6 | T57: =SUM(I56:T56) -> 0.6 | U57: =SUM(J56:U56) -> 0.6 | ... AL57: =SUM(AA56:AL56) -> 15.22464 | AN57: =N57 -> 0.6 | AO57: =Z57 -> 2.528 | AP57: =AL57 -> 15.22464
A58: Net ACV per new contract, Department | B58: $ | C58: =((Assumptions!$C$121*(1-Assumptions!$C$29))*$C$10) -> 26400 | D58: =((Assumptions!$C$121*(1-Assumptions!$C$29))*$C$10) -> 26400 | E58: =((Assumptions!$C$121*(1-Assumptions!$C$29))*$C$10) -> 26400 | F58: =((Assumptions!$C$121*(1-Assumptions!$C$29))*$C$10) -> 26400 | G58: =((Assumptions!$C$121*(1-Assumptions!$C$29))*$C$10) -> 26400 | H58: =((Assumptions!$C$121*(1-Assumptions!$C$29))*$C$10) -> 26400 | I58: =((Assumptions!$C$121*(1-Assumptions!$C$29))*$C$10) -> 26400 | J58: =((Assumptions!$C$121*(1-Assumptions!$C$29))*$C$10) -> 26400 | ... AL58: =((Assumptions!$C$121*(1-Assumptions!$C$29))*$C$10) -> 26400
A59: Contract value started or renewed, Department | B59: $ | C59: =((C55*C58)+((C45*(1+Assumptions!$C$31))*0)) -> 0 | D59: =((D55*D58)+((D45*(1+Assumptions!$C$31))*0)) -> 0 | E59: =((E55*E58)+((E45*(1+Assumptions!$C$31))*0)) -> 0 | F59: =((F55*F58)+((F45*(1+Assumptions!$C$31))*0)) -> 0 | G59: =((G55*G58)+((G45*(1+Assumptions!$C$31))*0)) -> 0 | H59: =((H55*H58)+((H45*(1+Assumptions!$C$31))*0)) -> 0 | I59: =((I55*I58)+((I45*(1+Assumptions!$C$31))*0)) -> 0 | J59: =((J55*J58)+((J45*(1+Assumptions!$C$31))*0)) -> 0 | ... N59: =((N55*N58)+((N45*(1+Assumptions!$C$31))*0)) -> 15840 | O59: =((O55*O58)+((O45*(1+Assumptions!$C$31))*C59)) -> 0 | P59: =((P55*P58)+((P45*(1+Assumptions!$C$31))*D59)) -> 0 | Q59: =((Q55*Q58)+((Q45*(1+Assumptions!$C$31))*E59)) -> 0 | R59: =((R55*R58)+((R45*(1+Assumptions!$C$31))*F59)) -> 0 | S59: =((S55*S58)+((S45*(1+Assumptions!$C$31))*G59)) -> 0 | T59: =((T55*T58)+((T45*(1+Assumptions!$C$31))*H59)) -> 0 | U59: =((U55*U58)+((U45*(1+Assumptions!$C$31))*I59)) -> 0 | V59: =((V55*V58)+((V45*(1+Assumptions!$C$31))*J59)) -> 13200 | ... AL59: =((AL55*AL58)+((AL45*(1+Assumptions!$C$31))*Z59)) -> 14842.46 | AN59: =SUM(C59:N59) -> 15840 | AO59: =SUM(O59:Z59) -> 68133.12 | AP59: =SUM(AA59:AL59) -> 409152.86
A60: Pilot credit given at conversion, Department | B60: $ | C60: =(Assumptions!$C$126*C53) -> 0 | D60: =(Assumptions!$C$126*D53) -> 0 | E60: =(Assumptions!$C$126*E53) -> 0 | F60: =(Assumptions!$C$126*F53) -> 0 | G60: =(Assumptions!$C$126*G53) -> 0 | H60: =(Assumptions!$C$126*H53) -> 0 | I60: =(Assumptions!$C$126*I53) -> 0 | J60: =(Assumptions!$C$126*J53) -> 0 | ... AL60: =(Assumptions!$C$126*AL53) -> 0 | AN60: =SUM(C60:N60) -> 0 | AO60: =SUM(O60:Z60) -> 7500 | AP60: =SUM(AA60:AL60) -> 37500
A61: Platform subscription revenue, Department | B61: $ | C61: =((C59-C60)/12) -> 0 | D61: =((SUM(C59:D59)-SUM(C60:D60))/12) -> 0 | E61: =((SUM(C59:E59)-SUM(C60:E60))/12) -> 0 | F61: =((SUM(C59:F59)-SUM(C60:F60))/12) -> 0 | G61: =((SUM(C59:G59)-SUM(C60:G60))/12) -> 0 | H61: =((SUM(C59:H59)-SUM(C60:H60))/12) -> 0 | I61: =((SUM(C59:I59)-SUM(C60:I60))/12) -> 0 | J61: =((SUM(C59:J59)-SUM(C60:J60))/12) -> 0 | K61: =((SUM(C59:K59)-SUM(C60:K60))/12) -> 0 | L61: =((SUM(C59:L59)-SUM(C60:L60))/12) -> 0 | M61: =((SUM(C59:M59)-SUM(C60:M60))/12) -> 0 | N61: =((SUM(C59:N59)-SUM(C60:N60))/12) -> 1320 | O61: =((SUM(D59:O59)-SUM(D60:O60))/12) -> 1320 | P61: =((SUM(E59:P59)-SUM(E60:P60))/12) -> 1320 | Q61: =((SUM(F59:Q59)-SUM(F60:Q60))/12) -> 1320 | R61: =((SUM(G59:R59)-SUM(G60:R60))/12) -> 1320 | S61: =((SUM(H59:S59)-SUM(H60:S60))/12) -> 1320 | T61: =((SUM(I59:T59)-SUM(I60:T60))/12) -> 1320 | U61: =((SUM(J59:U59)-SUM(J60:U60))/12) -> 1320 | ... AL61: =((SUM(AA59:AL59)-SUM(AA60:AL60))/12) -> 30971.072 | AN61: =SUM(C61:N61) -> 1320 | AO61: =SUM(O61:Z61) -> 25710.26 | AP61: =SUM(AA61:AL61) -> 203455.03
A62: Platform billings, Department | B62: $ | C62: =(C59-C60) -> 0 | D62: =(D59-D60) -> 0 | E62: =(E59-E60) -> 0 | F62: =(F59-F60) -> 0 | G62: =(G59-G60) -> 0 | H62: =(H59-H60) -> 0 | I62: =(I59-I60) -> 0 | J62: =(J59-J60) -> 0 | ... AL62: =(AL59-AL60) -> 14842.46 | AN62: =SUM(C62:N62) -> 15840 | AO62: =SUM(O62:Z62) -> 60633.12 | AP62: =SUM(AA62:AL62) -> 371652.86
A63: Pilot software revenue, Department | B63: $ | C63: =(((Assumptions!$C$122*$C$10)/6)*C52) -> 0 | D63: =(((Assumptions!$C$122*$C$10)/6)*D52) -> 0 | E63: =(((Assumptions!$C$122*$C$10)/6)*E52) -> 0 | F63: =(((Assumptions!$C$122*$C$10)/6)*F52) -> 0 | G63: =(((Assumptions!$C$122*$C$10)/6)*G52) -> 0 | H63: =(((Assumptions!$C$122*$C$10)/6)*H52) -> 0 | I63: =(((Assumptions!$C$122*$C$10)/6)*I52) -> 0 | J63: =(((Assumptions!$C$122*$C$10)/6)*J52) -> 0 | ... AL63: =(((Assumptions!$C$122*$C$10)/6)*AL52) -> 17500 | AN63: =SUM(C63:N63) -> 0 | AO63: =SUM(O63:Z63) -> 75000 | AP63: =SUM(AA63:AL63) -> 180000
A64: Pilot billings, Department | B64: $ | C64: =((Assumptions!$C$122*$C$10)*C46) -> 0 | D64: =((Assumptions!$C$122*$C$10)*D46) -> 0 | E64: =((Assumptions!$C$122*$C$10)*E46) -> 0 | F64: =((Assumptions!$C$122*$C$10)*F46) -> 0 | G64: =((Assumptions!$C$122*$C$10)*G46) -> 0 | H64: =((Assumptions!$C$122*$C$10)*H46) -> 0 | I64: =((Assumptions!$C$122*$C$10)*I46) -> 0 | J64: =((Assumptions!$C$122*$C$10)*J46) -> 0 | ... AL64: =((Assumptions!$C$122*$C$10)*AL46) -> 0 | AN64: =SUM(C64:N64) -> 0 | AO64: =SUM(O64:Z64) -> 90000 | AP64: =SUM(AA64:AL64) -> 195000
A65: Services fee per new billable institution, Department | B65: $ | C65: =((Assumptions!$C$123*$C$10)+(Assumptions!$C$34*Assumptions!$C$35)) -> 21000 | D65: =((Assumptions!$C$123*$C$10)+(Assumptions!$C$34*Assumptions!$C$35)) -> 21000 | E65: =((Assumptions!$C$123*$C$10)+(Assumptions!$C$34*Assumptions!$C$35)) -> 21000 | F65: =((Assumptions!$C$123*$C$10)+(Assumptions!$C$34*Assumptions!$C$35)) -> 21000 | G65: =((Assumptions!$C$123*$C$10)+(Assumptions!$C$34*Assumptions!$C$35)) -> 21000 | H65: =((Assumptions!$C$123*$C$10)+(Assumptions!$C$34*Assumptions!$C$35)) -> 21000 | I65: =((Assumptions!$C$123*$C$10)+(Assumptions!$C$34*Assumptions!$C$35)) -> 21000 | J65: =((Assumptions!$C$123*$C$10)+(Assumptions!$C$34*Assumptions!$C$35)) -> 21000 | ... AL65: =((Assumptions!$C$123*$C$10)+(Assumptions!$C$34*Assumptions!$C$35)) -> 21000
A66: Implementation services revenue, Department | B66: $ | C66: =((C65/3)*C50) -> 0 | D66: =((D65/3)*SUM(C50:D50)) -> 0 | E66: =((E65/3)*SUM(C50:E50)) -> 0 | F66: =((F65/3)*SUM(D50:F50)) -> 0 | G66: =((G65/3)*SUM(E50:G50)) -> 0 | H66: =((H65/3)*SUM(F50:H50)) -> 0 | I66: =((I65/3)*SUM(G50:I50)) -> 0 | J66: =((J65/3)*SUM(H50:J50)) -> 0 | K66: =((K65/3)*SUM(I50:K50)) -> 0 | L66: =((L65/3)*SUM(J50:L50)) -> 0 | ... AL66: =((AL65/3)*SUM(AJ50:AL50)) -> 49000 | AN66: =SUM(C66:N66) -> 0 | AO66: =SUM(O66:Z66) -> 140000 | AP66: =SUM(AA66:AL66) -> 427000
A67: Implementation billings, Department | B67: $ | C67: =(C65*C50) -> 0 | D67: =(D65*D50) -> 0 | E67: =(E65*E50) -> 0 | F67: =(F65*F50) -> 0 | G67: =(G65*G50) -> 0 | H67: =(H65*H50) -> 0 | I67: =(I65*I50) -> 0 | J67: =(J65*J50) -> 0 | ... AL67: =(AL65*AL50) -> 0 | AN67: =SUM(C67:N67) -> 0 | AO67: =SUM(O67:Z67) -> 147000 | AP67: =SUM(AA67:AL67) -> 441000
A68: Implementation hours demanded, Department | B68: hours | C68: =((C47*Assumptions!$C$124)+(C50*(Assumptions!$C$124+(Assumptions!$C$34*Assumptions!$C$36)))) -> 0 | D68: =((D47*Assumptions!$C$124)+(D50*(Assumptions!$C$124+(Assumptions!$C$34*Assumptions!$C$36)))) -> 0 | E68: =((E47*Assumptions!$C$124)+(E50*(Assumptions!$C$124+(Assumptions!$C$34*Assumptions!$C$36)))) -> 0 | F68: =((F47*Assumptions!$C$124)+(F50*(Assumptions!$C$124+(Assumptions!$C$34*Assumptions!$C$36)))) -> 0 | G68: =((G47*Assumptions!$C$124)+(G50*(Assumptions!$C$124+(Assumptions!$C$34*Assumptions!$C$36)))) -> 115 | H68: =((H47*Assumptions!$C$124)+(H50*(Assumptions!$C$124+(Assumptions!$C$34*Assumptions!$C$36)))) -> 0 | I68: =((I47*Assumptions!$C$124)+(I50*(Assumptions!$C$124+(Assumptions!$C$34*Assumptions!$C$36)))) -> 0 | J68: =((J47*Assumptions!$C$124)+(J50*(Assumptions!$C$124+(Assumptions!$C$34*Assumptions!$C$36)))) -> 0 | ... AL68: =((AL47*Assumptions!$C$124)+(AL50*(Assumptions!$C$124+(Assumptions!$C$34*Assumptions!$C$36)))) -> 0 | AN68: =SUM(C68:N68) -> 115 | AO68: =SUM(O68:Z68) -> 1113 | AP68: =SUM(AA68:AL68) -> 3339
A69: Paid pilot starts, Campus | B69: accts | C69: =((IF(OR((C$18-(Assumptions!$C$7-1)-$C$9)<1,(C$18-(Assumptions!$C$7-1)-$C$9)>36),0,INDEX(Schedules!$C$6:$AL$6,(C$18-(Assumptions!$C$7-1)-$C$9)))*$C$7)*C44) -> 0 | D69: =((IF(OR((D$18-(Assumptions!$C$7-1)-$C$9)<1,(D$18-(Assumptions!$C$7-1)-$C$9)>36),0,INDEX(Schedules!$C$6:$AL$6,(D$18-(Assumptions!$C$7-1)-$C$9)))*$C$7)*D44) -> 0 | E69: =((IF(OR((E$18-(Assumptions!$C$7-1)-$C$9)<1,(E$18-(Assumptions!$C$7-1)-$C$9)>36),0,INDEX(Schedules!$C$6:$AL$6,(E$18-(Assumptions!$C$7-1)-$C$9)))*$C$7)*E44) -> 0 | F69: =((IF(OR((F$18-(Assumptions!$C$7-1)-$C$9)<1,(F$18-(Assumptions!$C$7-1)-$C$9)>36),0,INDEX(Schedules!$C$6:$AL$6,(F$18-(Assumptions!$C$7-1)-$C$9)))*$C$7)*F44) -> 0 | G69: =((IF(OR((G$18-(Assumptions!$C$7-1)-$C$9)<1,(G$18-(Assumptions!$C$7-1)-$C$9)>36),0,INDEX(Schedules!$C$6:$AL$6,(G$18-(Assumptions!$C$7-1)-$C$9)))*$C$7)*G44) -> 0 | H69: =((IF(OR((H$18-(Assumptions!$C$7-1)-$C$9)<1,(H$18-(Assumptions!$C$7-1)-$C$9)>36),0,INDEX(Schedules!$C$6:$AL$6,(H$18-(Assumptions!$C$7-1)-$C$9)))*$C$7)*H44) -> 0 | I69: =((IF(OR((I$18-(Assumptions!$C$7-1)-$C$9)<1,(I$18-(Assumptions!$C$7-1)-$C$9)>36),0,INDEX(Schedules!$C$6:$AL$6,(I$18-(Assumptions!$C$7-1)-$C$9)))*$C$7)*I44) -> 0 | J69: =((IF(OR((J$18-(Assumptions!$C$7-1)-$C$9)<1,(J$18-(Assumptions!$C$7-1)-$C$9)>36),0,INDEX(Schedules!$C$6:$AL$6,(J$18-(Assumptions!$C$7-1)-$C$9)))*$C$7)*J44) -> 0 | ... AL69: =((IF(OR((AL$18-(Assumptions!$C$7-1)-$C$9)<1,(AL$18-(Assumptions!$C$7-1)-$C$9)>36),0,INDEX(Schedules!$C$6:$AL$6,(AL$18-(Assumptions!$C$7-1)-$C$9)))*$C$7)*AL44) -> 0 | AN69: =SUM(C69:N69) -> 0 | AO69: =SUM(O69:Z69) -> 3 | AP69: =SUM(AA69:AL69) -> 7
A70: Unpaid design-partner pilot starts, Campus | B70: accts | C70: =INDEX(Schedules!$C$12:$AL$12,C$18) -> 0 | D70: =INDEX(Schedules!$C$12:$AL$12,D$18) -> 0 | E70: =INDEX(Schedules!$C$12:$AL$12,E$18) -> 0 | F70: =INDEX(Schedules!$C$12:$AL$12,F$18) -> 0 | G70: =INDEX(Schedules!$C$12:$AL$12,G$18) -> 0 | H70: =INDEX(Schedules!$C$12:$AL$12,H$18) -> 0 | I70: =INDEX(Schedules!$C$12:$AL$12,I$18) -> 0 | J70: =INDEX(Schedules!$C$12:$AL$12,J$18) -> 1 | ... AL70: =INDEX(Schedules!$C$12:$AL$12,AL$18) -> 0 | AN70: =SUM(C70:N70) -> 1 | AO70: =SUM(O70:Z70) -> 0 | AP70: =SUM(AA70:AL70) -> 0
A71: All pilot starts, Campus | B71: accts | C71: =(C69+C70) -> 0 | D71: =(D69+D70) -> 0 | E71: =(E69+E70) -> 0 | F71: =(F69+F70) -> 0 | G71: =(G69+G70) -> 0 | H71: =(H69+H70) -> 0 | I71: =(I69+I70) -> 0 | J71: =(J69+J70) -> 1 | ... AL71: =(AL69+AL70) -> 0 | AN71: =SUM(C71:N71) -> 1 | AO71: =SUM(O71:Z71) -> 3 | AP71: =SUM(AA71:AL71) -> 7
A72: Direct annual starts, Campus | B72: accts | C72: =((IF(OR((C$18-(Assumptions!$C$8-1)-$C$9)<1,(C$18-(Assumptions!$C$8-1)-$C$9)>36),0,INDEX(Schedules!$C$9:$AL$9,(C$18-(Assumptions!$C$8-1)-$C$9)))*$C$7)*C44) -> 0 | D72: =((IF(OR((D$18-(Assumptions!$C$8-1)-$C$9)<1,(D$18-(Assumptions!$C$8-1)-$C$9)>36),0,INDEX(Schedules!$C$9:$AL$9,(D$18-(Assumptions!$C$8-1)-$C$9)))*$C$7)*D44) -> 0 | E72: =((IF(OR((E$18-(Assumptions!$C$8-1)-$C$9)<1,(E$18-(Assumptions!$C$8-1)-$C$9)>36),0,INDEX(Schedules!$C$9:$AL$9,(E$18-(Assumptions!$C$8-1)-$C$9)))*$C$7)*E44) -> 0 | F72: =((IF(OR((F$18-(Assumptions!$C$8-1)-$C$9)<1,(F$18-(Assumptions!$C$8-1)-$C$9)>36),0,INDEX(Schedules!$C$9:$AL$9,(F$18-(Assumptions!$C$8-1)-$C$9)))*$C$7)*F44) -> 0 | G72: =((IF(OR((G$18-(Assumptions!$C$8-1)-$C$9)<1,(G$18-(Assumptions!$C$8-1)-$C$9)>36),0,INDEX(Schedules!$C$9:$AL$9,(G$18-(Assumptions!$C$8-1)-$C$9)))*$C$7)*G44) -> 0 | H72: =((IF(OR((H$18-(Assumptions!$C$8-1)-$C$9)<1,(H$18-(Assumptions!$C$8-1)-$C$9)>36),0,INDEX(Schedules!$C$9:$AL$9,(H$18-(Assumptions!$C$8-1)-$C$9)))*$C$7)*H44) -> 0 | I72: =((IF(OR((I$18-(Assumptions!$C$8-1)-$C$9)<1,(I$18-(Assumptions!$C$8-1)-$C$9)>36),0,INDEX(Schedules!$C$9:$AL$9,(I$18-(Assumptions!$C$8-1)-$C$9)))*$C$7)*I44) -> 0 | J72: =((IF(OR((J$18-(Assumptions!$C$8-1)-$C$9)<1,(J$18-(Assumptions!$C$8-1)-$C$9)>36),0,INDEX(Schedules!$C$9:$AL$9,(J$18-(Assumptions!$C$8-1)-$C$9)))*$C$7)*J44) -> 0 | ... AL72: =((IF(OR((AL$18-(Assumptions!$C$8-1)-$C$9)<1,(AL$18-(Assumptions!$C$8-1)-$C$9)>36),0,INDEX(Schedules!$C$9:$AL$9,(AL$18-(Assumptions!$C$8-1)-$C$9)))*$C$7)*AL44) -> 0 | AN72: =SUM(C72:N72) -> 0 | AO72: =SUM(O72:Z72) -> 0 | AP72: =SUM(AA72:AL72) -> 5
A73: New billable institutions (paid pilot or direct), Campus | B73: accts | C73: =(C69+C72) -> 0 | D73: =(D69+D72) -> 0 | E73: =(E69+E72) -> 0 | F73: =(F69+F72) -> 0 | G73: =(G69+G72) -> 0 | H73: =(H69+H72) -> 0 | I73: =(I69+I72) -> 0 | J73: =(J69+J72) -> 0 | ... AL73: =(AL69+AL72) -> 0 | AN73: =SUM(C73:N73) -> 0 | AO73: =SUM(O73:Z73) -> 3 | AP73: =SUM(AA73:AL73) -> 12
A74: Pilots running (paid + unpaid), Campus | B74: accts | C74: =C71 -> 0 | D74: =SUM(C71:D71) -> 0 | E74: =SUM(C71:E71) -> 0 | F74: =SUM(C71:F71) -> 0 | G74: =SUM(C71:G71) -> 0 | H74: =SUM(C71:H71) -> 0 | I74: =SUM(D71:I71) -> 0 | J74: =SUM(E71:J71) -> 1 | K74: =SUM(F71:K71) -> 1 | L74: =SUM(G71:L71) -> 1 | M74: =SUM(H71:M71) -> 1 | N74: =SUM(I71:N71) -> 1 | O74: =SUM(J71:O71) -> 1 | ... AL74: =SUM(AG71:AL71) -> 4 | AN74: =N74 -> 1 | AO74: =Z74 -> 2 | AP74: =AL74 -> 4
A75: Paid pilots running, Campus | B75: accts | C75: =C69 -> 0 | D75: =SUM(C69:D69) -> 0 | E75: =SUM(C69:E69) -> 0 | F75: =SUM(C69:F69) -> 0 | G75: =SUM(C69:G69) -> 0 | H75: =SUM(C69:H69) -> 0 | I75: =SUM(D69:I69) -> 0 | J75: =SUM(E69:J69) -> 0 | K75: =SUM(F69:K69) -> 0 | L75: =SUM(G69:L69) -> 0 | M75: =SUM(H69:M69) -> 0 | N75: =SUM(I69:N69) -> 0 | O75: =SUM(J69:O69) -> 0 | ... AL75: =SUM(AG69:AL69) -> 4 | AN75: =N75 -> 0 | AO75: =Z75 -> 2 | AP75: =AL75 -> 4
A76: Paid pilots converting to annual, Campus | B76: accts | C76: =((Assumptions!$D$127*$C$8)*0) -> 0 | D76: =((Assumptions!$D$127*$C$8)*0) -> 0 | E76: =((Assumptions!$D$127*$C$8)*0) -> 0 | F76: =((Assumptions!$D$127*$C$8)*0) -> 0 | G76: =((Assumptions!$D$127*$C$8)*0) -> 0 | H76: =((Assumptions!$D$127*$C$8)*0) -> 0 | I76: =((Assumptions!$D$127*$C$8)*0) -> 0 | J76: =((Assumptions!$D$127*$C$8)*C69) -> 0 | K76: =((Assumptions!$D$127*$C$8)*D69) -> 0 | L76: =((Assumptions!$D$127*$C$8)*E69) -> 0 | M76: =((Assumptions!$D$127*$C$8)*F69) -> 0 | N76: =((Assumptions!$D$127*$C$8)*G69) -> 0 | O76: =((Assumptions!$D$127*$C$8)*H69) -> 0 | P76: =((Assumptions!$D$127*$C$8)*I69) -> 0 | Q76: =((Assumptions!$D$127*$C$8)*J69) -> 0 | ... AL76: =((Assumptions!$D$127*$C$8)*AE69) -> 0 | AN76: =SUM(C76:N76) -> 0 | AO76: =SUM(O76:Z76) -> 0.45 | AP76: =SUM(AA76:AL76) -> 2.25
